Workbook

Sheet README
C3: Notas importantes
B5: 1 | C5: Llenar por favor TODAS las hojas y los espacios en blanco de este libro de Excel.
B6: 2 | C6: Acompañe los datos de las casillas con comentarios para facilitar la comprensión de los datos, su origen, los cálculos, los supuestos, entre otros.
B7: 3 | C7: Si requiere agregar más hojas, más filas o columnas, más tecnologías u otro para completar todos los datos necesarios de los 3 escenarios complementarios al BAU, hágalo por favor.
B8: 4 | C8: Agregue comentarios explicativos bajo las tablas de los datos para la mejor comprensión de los escenarios.
B9: 5 | C9: Si tiene dudas, contacte a los equipos o personas correspondientes para aclararlas.
B10: 6 | C10: Si las variables dentro de las hojas no varían en comparación con el escenario BAU, replicar los datos donde corresponda e indicar que esto pasa.
B11: 7 | C11: Siempre que sea posible, acompañe los datos con la referencia de procedencia (enlaces de la web, nombre del informe u otro).
B12: 8 | C12: No se detallan necesariamente todas las tecnologías. Se incorporaron algunas de ellas y es cuestión de agregar más líneas para caracterizar cada tecnología, sobretodo con las tecnologías reductoras de emisiones o indicadores mejorados de los 3 escenarios de emisiones reducidas.
B13: 9 | C13: En algunos casos, se incluyeros unidades predeterminadas para los datos. Si los datos están en otras unidades o es mejor verlos en otras unidades, modifíquelo por favor.
B14: 10 | C14: Si solo se tienen valores en años puntuales o años meta y no en todo el intervalo, colóquelos en el año correspondiente de igual manera. Se usará algún método de interpolación o extrapolación para completar todo el intervalo.
B15: 11 | C15: Si existen datos de la recuperación de metano consumido para generación de electricidad con plantas instaladas en vertederos, crear una nueva hoja e indicar la evolución esperada en el tiempo de esa tecnología.

Sheet ProduccionResiduosSolidos
C1: Ecuador | D1: 2010 | E1: 2011 | F1: 2012 | G1: 2013 | H1: 2014 | I1: 2015 | J1: 2016 | K1: 2017 | L1: 2018 | M1: 2019 | N1: 2020 | O1: 2021 | P1: 2022 | Q1: 2023 | R1: 2024 | S1: 2025 | T1: 2026 | U1: 2027 | V1: 2028 | W1: 2029 | X1: 2030 | Y1: 2031 | Z1: 2032 | AA1: 2033 | AB1: 2034 | AC1: 2035
C4: RESIDUOS SÓLIDOS
C5: Población INEN | D5: 14883661 | E5: 15160587 | F5: 15440550 | G5: 15717514 | H5: 15994366 | I5: 16269171 | J5: 16532265 | K5: 16792803 | L5: 17023408 | M5: 17267986 | N5: 17510643 | O5: 17751277 | P5: 17989912 | Q5: 18226512 | R5: 17966573 | S5: 18103660 | T5: 18243816 | U5: 18385975 | V5: 18529121 | W5: 18672456 | X5: 18815497 | Y5: 18957924 | Z5: 19099478 | AA5: 19239759 | AB5: 19378452 | AC5: 19515303
C6: Fuente: INEC 2024. https://www.ecuadorencifras.gob.ec/proyecciones-poblacionales/
C8: Producción per cápita PPC [kg residuos sólidos/año]
C9: Tendencial Nacional | D9: 0.74868269 | E9: 0.76193328 | F9: 0.77153461 | G9: 0.8651815 | H9: 0.96349654 | I9: 0.89204956 | J9: 0.83803574 | K9: 0.82253337 | L9: 0.80888483 | M9: 0.79910816 | N9: 0.83 | O9: 0.78 | P9: 0.83779624 | Q9: 0.8803189 | R9: 0.9225226 | S9: 0.96463385 | T9: 1.0067584 | U9: 1.0488757 | V9: 1.0910322 | W9: 1.1332685 | X9: 1.1755241 | Y9: 1.1894809 | Z9: 1.2033134 | AA9: 1.2170086 | AB9: 1.2306063 | AC9: 1.2441141
C10: Fuente: Base de datos PLAN MICC y 2NDC
C11: Producción de residuos sólidos [Mt]
C12: Tendencial Nacional | D12: =(D9*D5*365)/1000000000 -> 4.0672459 | E12: =(E9*E5*365)/1000000000 -> 4.2162448 | F12: =(F9*F5*365)/1000000000 -> 4.3482153 | G12: =(G9*G5*365)/1000000000 -> 4.9634533 | H12: =(H9*H5*365)/1000000000 -> 5.6248384 | I12: =(I9*I5*365)/1000000000 -> 5.297211 | J12: =(J9*J5*365)/1000000000 -> 5.0569395 | K12: =(K9*K5*365)/1000000000 -> 5.0416139 | ... AC12: =(AC9*AC5*365)/1000000000 -> 8.8619312

Sheet ParticipacionTechsSolidosBA (2)
D1: Ecuador | E1: 2010 | F1: 2011 | G1: 2012 | H1: 2013 | I1: 2014 | J1: 2015 | K1: 2016 | L1: 2017 | M1: 2018 | N1: 2019 | O1: 2020 | P1: 2021 | Q1: 2022 | R1: 2023 | S1: 2024 | T1: 2025 | U1: 2026 | V1: 2027 | W1: 2028 | X1: 2029 | Y1: 2030 | Z1: 2031 | AA1: 2032 | AB1: 2033 | AC1: 2034 | AD1: 2035 | AE1: 2036 | AF1: 2037 | AG1: 2038 | AH1: 2039 | AI1: 2040 | AJ1: 2041 | AK1: 2042 | AL1: 2043 | AM1: 2044 | AN1: 2045 | AO1: 2046 | AP1: 2047 | AQ1: 2048 | AR1: 2049 | AS1: 2050 | AT1: 2051 | AU1: 2052 | AV1: 2053 | AW1: 2054 | AX1: 2055 | AY1: 2056 | AZ1: 2057 | BA1: 2058 | BB1: 2059 | BC1: 2060 | BD1: 2061 | BE1: 2062 | BF1: 2063 | BG1: 2064 | BH1: 2065 | BI1: 2066 | BJ1: 2067 | BK1: 2068 | BL1: 2069 | BM1: 2070
D4: Residuos sólidos (PORCENTAJES)
C6: Códificación OSeMOSYS | D6: BAU
C8: Etapa 4: Disposición final
C9: INORG_RCY_OS | D9: Inorgánicos u otros sin emisiones | E9: =1-E10-E11-E12-E13-E14-E15-E16-E17-E18 -> 0.41274758 | F9: =1-F10-F11-F12-F13-F14-F15-F16-F17-F18 -> 0.41274758 | G9: =1-G10-G11-G12-G13-G14-G15-G16-G17-G18 -> 0.41274758 | H9: =1-H10-H11-H12-H13-H14-H15-H16-H17-H18 -> 0.41274758 | I9: =1-I10-I11-I12-I13-I14-I15-I16-I17-I18 -> 0.41274758 | J9: =1-J10-J11-J12-J13-J14-J15-J16-J17-J18 -> 0.41178481 | K9: =1-K10-K11-K12-K13-K14-K15-K16-K17-K18 -> 0.40541367 | L9: =1-L10-L11-L12-L13-L14-L15-L16-L17-L18 -> 0.39926298 | ... BM9: =1-BM10-BM11-BM12-BM13-BM14-BM15-BM16-BM17-BM18 -> 0.35701225
C10: AD | D10: Digestión Anaerobica | E10: 0 | F10: 0 | G10: 0 | H10: 0 | I10: 0 | J10: 0 | K10: 0 | L10: 0 | M10: 0 | N10: 0 | O10: 0 | P10: 0 | Q10: 0 | R10: 0 | S10: 0 | T10: 0 | U10: 0 | V10: 0 | W10: 0 | X10: 0 | Y10: 0 | Z10: 0 | AA10: 0 | AB10: 0 | AC10: 0 | AD10: 0 | AE10: 0 | AF10: 0 | AG10: 0 | AH10: 0 | AI10: 0 | AJ10: 0 | AK10: 0 | AL10: 0 | AM10: 0 | AN10: 0 | AO10: 0 | AP10: 0 | AQ10: 0 | AR10: 0 | AS10: 0 | AT10: 0 | AU10: 0 | AV10: 0 | AW10: 0 | AX10: 0 | AY10: 0 | AZ10: 0 | BA10: 0 | BB10: 0 | BC10: 0 | BD10: 0 | BE10: 0 | BF10: 0 | BG10: 0 | BH10: 0 | BI10: 0 | BJ10: 0 | BK10: 0 | BL10: 0 | BM10: 0
C11: COMPOST | D11: Compostaje | E11: =E44/E83 -> 0.0013522664 | F11: =F44/F83 -> 0.0015179384 | G11: =G44/G83 -> 0.0016788497 | H11: =H44/H83 -> 0.0044726924 | I11: =I44/I83 -> 0.0066135233 | J11: =J44/J83 -> 0.0060786705 | K11: =K44/K83 -> 0.0053787473 | L11: =L44/L83 -> 0.0060496501 | ... AD11: =AD44/AD83 -> 0.0066828611 | AE11: 0.0066828611 | AF11: 0.0066828611 | AG11: 0.0066828611 | AH11: 0.0066828611 | AI11: 0.0066828611 | AJ11: 0.0066828611 | AK11: 0.0066828611 | AL11: 0.0066828611 | AM11: 0.0066828611 | AN11: 0.0066828611 | AO11: 0.0066828611 | AP11: 0.0066828611 | AQ11: 0.0066828611 | AR11: 0.0066828611 | AS11: 0.0066828611 | AT11: 0.0066828611 | AU11: 0.0066828611 | AV11: 0.0066828611 | AW11: 0.0066828611 | AX11: 0.0066828611 | AY11: 0.0066828611 | AZ11: 0.0066828611 | BA11: 0.0066828611 | BB11: 0.0066828611 | BC11: 0.0066828611 | BD11: 0.0066828611 | BE11: 0.0066828611 | BF11: 0.0066828611 | BG11: 0.0066828611 | BH11: 0.0066828611 | BI11: 0.0066828611 | BJ11: 0.0066828611 | BK11: 0.0066828611 | BL11: 0.0066828611 | BM11: 0.0066828611
C12: LANDFILL_BG | D12: Relleno sanitario con quema biogas | E12: 0 | F12: 0 | G12: 0 | H12: 0 | I12: 0 | J12: 0 | K12: 0.00733391 | L12: 0.012651526 | M12: 0.012651526 | N12: 0.012651526 | O12: 0.012651526 | P12: 0.012651526 | Q12: 0.012651526 | R12: 0.012651526 | S12: 0.012651526 | T12: 0.012651526 | U12: 0.012651526 | V12: 0.012651526 | W12: 0.012651526 | X12: 0.012651526 | Y12: 0.012651526 | Z12: 0.012651526 | AA12: 0.012651526 | AB12: 0.012651526 | AC12: 0.012651526 | AD12: 0.012651526 | AE12: 0.012651526 | AF12: 0.012651526 | AG12: 0.012651526 | AH12: 0.012651526 | AI12: 0.012651526 | AJ12: 0.012651526 | AK12: 0.012651526 | AL12: 0.012651526 | AM12: 0.012651526 | AN12: 0.012651526 | AO12: 0.012651526 | AP12: 0.012651526 | AQ12: 0.012651526 | AR12: 0.012651526 | AS12: 0.012651526 | AT12: 0.012651526 | AU12: 0.012651526 | AV12: 0.012651526 | AW12: 0.012651526 | AX12: 0.012651526 | AY12: 0.012651526 | AZ12: 0.012651526 | BA12: 0.012651526 | BB12: 0.012651526 | BC12: 0.012651526 | BD12: 0.012651526 | BE12: 0.012651526 | BF12: 0.012651526 | BG12: 0.012651526 | BH12: 0.012651526 | BI12: 0.012651526 | BJ12: 0.012651526 | BK12: 0.012651526 | BL12: 0.012651526 | BM12: 0.012651526
C13: LANDFILL | D13: Sitios gestionados | E13: =E45/E83 -> 0.30664485 | F13: =F45/F83 -> 0.32113885 | G13: =G45/G83 -> 0.33305618 | H13: =H45/H83 -> 0.3172388 | I13: =I45/I83 -> 0.30415096 | J13: =J45/J83 -> 0.3769342 | K13: =K45/K83 -> 0.4386052 | L13: =L45/L83 -> 0.46566438 | ... AD13: =AD45/AD83 -> 0.54545973 | AE13: 0.54545973 | AF13: 0.54545973 | AG13: 0.54545973 | AH13: 0.54545973 | AI13: 0.54545973 | AJ13: 0.54545973 | AK13: 0.54545973 | AL13: 0.54545973 | AM13: 0.54545973 | AN13: 0.54545973 | AO13: 0.54545973 | AP13: 0.54545973 | AQ13: 0.54545973 | AR13: 0.54545973 | AS13: 0.54545973 | AT13: 0.54545973 | AU13: 0.54545973 | AV13: 0.54545973 | AW13: 0.54545973 | AX13: 0.54545973 | AY13: 0.54545973 | AZ13: 0.54545973 | BA13: 0.54545973 | BB13: 0.54545973 | BC13: 0.54545973 | BD13: 0.54545973 | BE13: 0.54545973 | BF13: 0.54545973 | BG13: 0.54545973 | BH13: 0.54545973 | BI13: 0.54545973 | BJ13: 0.54545973 | BK13: 0.54545973 | BL13: 0.54545973 | BM13: 0.54545973
C14: NO_CONTR_OD | D14: Sitios no gestionados | E14: =E46/E83 -> 0.27701792 | F14: =F46/F83 -> 0.26229501 | G14: =G46/G83 -> 0.25012561 | H14: =H46/H83 -> 0.26336502 | I14: =I46/I83 -> 0.274479 | J14: =J46/J83 -> 0.203088 | K14: =K46/K83 -> 0.14105369 | L14: =L46/L83 -> 0.11411028 | ... AD14: =AD46/AD83 -> 0.076325309 | AE14: 0.076325309 | AF14: 0.076325309 | AG14: 0.076325309 | AH14: 0.076325309 | AI14: 0.076325309 | AJ14: 0.076325309 | AK14: 0.076325309 | AL14: 0.076325309 | AM14: 0.076325309 | AN14: 0.076325309 | AO14: 0.076325309 | AP14: 0.076325309 | AQ14: 0.076325309 | AR14: 0.076325309 | AS14: 0.076325309 | AT14: 0.076325309 | AU14: 0.076325309 | AV14: 0.076325309 | AW14: 0.076325309 | AX14: 0.076325309 | AY14: 0.076325309 | AZ14: 0.076325309 | BA14: 0.076325309 | BB14: 0.076325309 | BC14: 0.076325309 | BD14: 0.076325309 | BE14: 0.076325309 | BF14: 0.076325309 | BG14: 0.076325309 | BH14: 0.076325309 | BI14: 0.076325309 | BJ14: 0.076325309 | BK14: 0.076325309 | BL14: 0.076325309 | BM14: 0.076325309
C15: COPROC | D15: Coprocesamiento | E15: 0 | F15: 0 | G15: 0 | H15: 0 | I15: 0 | J15: 0 | K15: 0 | L15: 0 | M15: 0 | N15: 0 | O15: 0 | P15: 0 | Q15: 0 | R15: 0 | S15: 0 | T15: 0 | U15: 0 | V15: 0 | W15: 0 | X15: 0 | Y15: 0 | Z15: 0 | AA15: 0 | AB15: 0 | AC15: 0 | AD15: 0 | AE15: 0 | AF15: 0 | AG15: 0 | AH15: 0 | AI15: 0 | AJ15: 0 | AK15: 0 | AL15: 0 | AM15: 0 | AN15: 0 | AO15: 0 | AP15: 0 | AQ15: 0 | AR15: 0 | AS15: 0 | AT15: 0 | AU15: 0 | AV15: 0 | AW15: 0 | AX15: 0 | AY15: 0 | AZ15: 0 | BA15: 0 | BB15: 0 | BC15: 0 | BD15: 0 | BE15: 0 | BF15: 0 | BG15: 0 | BH15: 0 | BI15: 0 | BJ15: 0 | BK15: 0 | BL15: 0 | BM15: 0
C16: INCIN | D16: Incineranción contralada | E16: =E47/E83 -> 0.0022373862 | F16: =F47/F83 -> 0.0023006254 | G16: =G47/G83 -> 0.0023917859 | H16: =H47/H83 -> 0.0021759044 | I16: =I47/I83 -> 0.0020089466 | J16: =J47/J83 -> 0.0021143202 | K16: =K47/K83 -> 0.0022147783 | L16: =L47/L83 -> 0.0022611807 | ... BM16: =BM47/BM83 -> 0.001868321
C17: OPEN_BURN | D17: Quema a cielo abierto | E17: 0 | F17: 0 | G17: 0 | H17: 0 | I17: 0 | J17: 0 | K17: 0 | L17: 0 | M17: 0 | N17: 0 | O17: 0 | P17: 0 | Q17: 0 | R17: 0 | S17: 0 | T17: 0 | U17: 0 | V17: 0 | W17: 0 | X17: 0 | Y17: 0 | Z17: 0 | AA17: 0 | AB17: 0 | AC17: 0 | AD17: 0 | AE17: 0 | AF17: 0 | AG17: 0 | AH17: 0 | AI17: 0 | AJ17: 0 | AK17: 0 | AL17: 0 | AM17: 0 | AN17: 0 | AO17: 0 | AP17: 0 | AQ17: 0 | AR17: 0 | AS17: 0 | AT17: 0 | AU17: 0 | AV17: 0 | AW17: 0 | AX17: 0 | AY17: 0 | AZ17: 0 | BA17: 0 | BB17: 0 | BC17: 0 | BD17: 0 | BE17: 0 | BF17: 0 | BG17: 0 | BH17: 0 | BI17: 0 | BJ17: 0 | BK17: 0 | BL17: 0 | BM17: 0
C18: SIT_CLAN | D18: Disposición en sitios clandestinos | E18: 0 | F18: 0 | G18: 0 | H18: 0 | I18: 0 | J18: 0 | K18: 0 | L18: 0 | M18: 0 | N18: 0 | O18: 0 | P18: 0 | Q18: 0 | R18: 0 | S18: 0 | T18: 0 | U18: 0 | V18: 0 | W18: 0 | X18: 0 | Y18: 0 | Z18: 0 | AA18: 0 | AB18: 0 | AC18: 0 | AD18: 0 | AE18: 0 | AF18: 0 | AG18: 0 | AH18: 0 | AI18: 0 | AJ18: 0 | AK18: 0 | AL18: 0 | AM18: 0 | AN18: 0 | AO18: 0 | AP18: 0 | AQ18: 0 | AR18: 0 | AS18: 0 | AT18: 0 | AU18: 0 | AV18: 0 | AW18: 0 | AX18: 0 | AY18: 0 | AZ18: 0 | BA18: 0 | BB18: 0 | BC18: 0 | BD18: 0 | BE18: 0 | BF18: 0 | BG18: 0 | BH18: 0 | BI18: 0 | BJ18: 0 | BK18: 0 | BL18: 0 | BM18: 0
E19: =SUM(E9:E18) -> 1 | F19: =SUM(F9:F18) -> 1 | G19: =SUM(G9:G18) -> 1 | H19: =SUM(H9:H18) -> 1 | I19: =SUM(I9:I18) -> 1 | J19: =SUM(J9:J18) -> 1 | K19: =SUM(K9:K18) -> 1 | L19: =SUM(L9:L18) -> 1 | ... BM19: =SUM(BM9:BM18) -> 1
D21: Relleno sanitario | E21: 0.15345822 | F21: 0.17844801 | G21: 0.18257969 | H21: 0.2533691 | I21: 0.29152718 | J21: 0.31758447 | K21: 0.34105926 | L21: 0.28420064 | M21: 0.29868552 | N21: 0.30029408 | O21: 0.33361839 | P21: 0.42025908 | Q21: 0.46132695 | R21: 0.51146955 | S21: 0.52365633
D22: Reciclaje de residuos inorgánicos separados en sitio de disposición final | E22: 0.024154045 | F22: 0.025147903 | G22: 0.025940634 | H22: 0.028244366 | I22: 0.027714 | J22: 0.02772 | K22: 0.027354 | L22: 0.038622 | M22: 0.0402084 | N22: 0.037584 | O22: 0.0382752 | P22: 0.0385392 | Q22: 0.04021848 | R22: 0.0423756 | S22: 0.0423756 | T22: 0.04091826 | U22: 0.039460921 | V22: 0.038003581 | W22: 0.036546241 | X22: 0.035088902 | Y22: 0.033631562 | Z22: 0.03368361 | AA22: 0.033735658 | AB22: 0.033787705 | AC22: 0.033839753 | AD22: 0.033891801 | AE22: 0.033943849 | AF22: 0.033995897 | AG22: 0.034047945 | AH22: 0.034099992 | AI22: 0.03415204 | AJ22: 0.034204088 | AK22: 0.034256136 | AL22: 0.034308184 | AM22: 0.034360232 | AN22: 0.03441228 | AO22: 0.034464327 | AP22: 0.034516375 | AQ22: 0.034568423 | AR22: 0.034620471 | AS22: 0.034672519 | AT22: 0.034672519 | AU22: 0.034672519 | AV22: 0.034672519 | AW22: 0.034672519 | AX22: 0.034672519 | AY22: 0.034672519 | AZ22: 0.034672519 | BA22: 0.034672519 | BB22: 0.034672519 | BC22: 0.034672519 | BD22: 0.034672519 | BE22: 0.034672519 | BF22: 0.034672519 | BG22: 0.034672519 | BH22: 0.034672519 | BI22: 0.034672519 | BJ22: 0.034672519 | BK22: 0.034672519 | BL22: 0.034672519 | BM22: 0.034507701
C24: Etapa 3: Separación en el sitio de disposición final
C25: OSS_INORG | D25: Separación de residuos inorgánicos en sitio de disposición final | E25: 0.024154045 | F25: 0.025147903 | G25: 0.025940634 | H25: 0.028244366 | I25: 0.027714 | J25: 0.02772 | K25: 0.027354 | L25: 0.038622 | M25: 0.0402084 | N25: 0.037584 | O25: 0.0382752 | P25: 0.0385392 | Q25: 0.04021848 | R25: 0.0423756 | S25: 0.0423756 | T25: =$H$92+$H$91*T1 -> 0.04091826 | U25: =$H$92+$H$91*U1 -> 0.039460921 | V25: =$H$92+$H$91*V1 -> 0.038003581 | W25: =$H$92+$H$91*W1 -> 0.036546241 | X25: =$H$92+$H$91*X1 -> 0.035088902 | Y25: =AVERAGE(E25:S25) -> 0.033631562 | Z25: =$I$92+$I$91*Z1 -> 0.03368361 | AA25: =$I$92+$I$91*AA1 -> 0.033735658 | AB25: =$I$92+$I$91*AB1 -> 0.033787705 | AC25: =$I$92+$I$91*AC1 -> 0.033839753 | AD25: =$I$92+$I$91*AD1 -> 0.033891801 | AE25: =$I$92+$I$91*AE1 -> 0.033943849 | AF25: =$I$92+$I$91*AF1 -> 0.033995897 | AG25: =$I$92+$I$91*AG1 -> 0.034047945 | ... AR25: =$I$92+$I$91*AR1 -> 0.034620471 | AS25: =AVERAGE(E25:Y25) -> 0.034672519 | AT25: 0.034672519 | AU25: 0.034672519 | AV25: 0.034672519 | AW25: 0.034672519 | AX25: 0.034672519 | AY25: 0.034672519 | AZ25: 0.034672519 | BA25: 0.034672519 | BB25: 0.034672519 | BC25: 0.034672519 | BD25: 0.034672519 | BE25: 0.034672519 | BF25: 0.034672519 | BG25: 0.034672519 | BH25: 0.034672519 | BI25: 0.034672519 | BJ25: 0.034672519 | BK25: 0.034672519 | BL25: 0.034672519 | BM25: =AVERAGE(E25:BL25) -> 0.034507701
C26: OSS_ORG | D26: Separación de residuos orgánicos en sitio de disposición final | E26: 0.023762538 | F26: 0.025779778 | G26: 0.027964623 | H26: 0.028890301 | I26: 0.026905 | J26: 0.0319 | K26: 0.025705 | L26: 0.044745 | M26: 0.042993 | N26: 0.04068 | O26: 0.040104 | P26: 0.041884 | Q26: 0.0494846 | R26: 0.043687 | S26: 0.043687 | T26: =$H$94+$H$93*T1 -> 0.04238552 | U26: =$H$94+$H$93*U1 -> 0.041084041 | V26: =$H$94+$H$93*V1 -> 0.039782561 | W26: =$H$94+$H$93*W1 -> 0.038481082 | X26: =$H$94+$H$93*X1 -> 0.037179602 | Y26: =AVERAGE(E26:S26) -> 0.035878123 | Z26: =$I$94+$I$93*Z1 -> 0.035924604 | AA26: =$I$94+$I$93*AA1 -> 0.035971086 | AB26: =$I$94+$I$93*AB1 -> 0.036017567 | AC26: =$I$94+$I$93*AC1 -> 0.036064048 | AD26: =$I$94+$I$93*AD1 -> 0.03611053 | AE26: =$I$94+$I$93*AE1 -> 0.036157011 | AF26: =$I$94+$I$93*AF1 -> 0.036203493 | AG26: =$I$94+$I$93*AG1 -> 0.036249974 | ... AR26: =$I$94+$I$93*AR1 -> 0.03676127 | AS26: =AVERAGE(E26:Y26) -> 0.036807751 | AT26: 0.036807751 | AU26: 0.036807751 | AV26: 0.036807751 | AW26: 0.036807751 | AX26: 0.036807751 | AY26: 0.036807751 | AZ26: 0.036807751 | BA26: 0.036807751 | BB26: 0.036807751 | BC26: 0.036807751 | BD26: 0.036807751 | BE26: 0.036807751 | BF26: 0.036807751 | BG26: 0.036807751 | BH26: 0.036807751 | BI26: 0.036807751 | BJ26: 0.036807751 | BK26: 0.036807751 | BL26: 0.036807751 | BM26: =AVERAGE(E26:BL26) -> 0.03666056
C27: NO_OSS_BLEND | D27: No separación de residuos mezclados en sitio de disposición final | E27: 0.95208342 | F27: 0.94907232 | G27: 0.94609474 | H27: 0.94286533 | I27: 0.945381 | J27: 0.94038 | K27: 0.946941 | L27: 0.896633 | M27: 0.9167986 | N27: 0.921736 | O27: 0.9216208 | P27: 0.9195768 | Q27: 0.91029692 | R27: 0.9139374 | S27: 0.91847658 | T27: =1-T26-T25 -> 0.91669622 | U27: =1-U26-U25 -> 0.91945504 | V27: =1-V26-V25 -> 0.92221386 | W27: =1-W26-W25 -> 0.92497268 | X27: =1-X26-X25 -> 0.9277315 | Y27: =1-Y26-Y25 -> 0.93049032 | Z27: =1-Z26-Z25 -> 0.93039179 | AA27: =1-AA26-AA25 -> 0.93029326 | ... BM27: =1-BM26-BM25 -> 0.92883174
C28: NO_OSS_NO_COLL | D28: No separación de residuos mezclados no recolectados | E28: 0.0022373862 | F28: 0.0022373862 | G28: 0.0022373862 | H28: 0.0022373862 | I28: 0.0022373862 | J28: 0.0022373862 | K28: 0.0022373862 | L28: 0.0022373862 | M28: 0.0022373862 | N28: 0.0022373862 | O28: 0.0022373862 | P28: 0.0022373862 | Q28: 0.0022373862 | R28: 0.0022373862 | S28: 0.0022373862 | T28: 0.0022373862 | U28: 0.0022373862 | V28: 0.0022373862 | W28: 0.0022373862 | X28: 0.0022373862 | Y28: 0.0022373862 | Z28: 0.0022373862 | AA28: 0.0022373862 | AB28: 0.0022373862 | AC28: 0.0022373862 | AD28: 0.0022373862 | AE28: 0.0022373862 | AF28: 0.0022373862 | AG28: 0.0022373862 | AH28: 0.0022373862 | AI28: 0.0022373862 | AJ28: 0.0022373862 | AK28: 0.0022373862 | AL28: 0.0022373862 | AM28: 0.0022373862 | AN28: 0.0022373862 | AO28: 0.0022373862 | AP28: 0.0022373862 | AQ28: 0.0022373862 | AR28: 0.0022373862 | AS28: 0.0022373862 | AT28: 0.0022373862 | AU28: 0.0022373862 | AV28: 0.0022373862 | AW28: 0.0022373862 | AX28: 0.0022373862 | AY28: 0.0022373862 | AZ28: 0.0022373862 | BA28: 0.0022373862 | BB28: 0.0022373862 | BC28: 0.0022373862 | BD28: 0.0022373862 | BE28: 0.0022373862 | BF28: 0.0022373862 | BG28: 0.0022373862 | BH28: 0.0022373862 | BI28: 0.0022373862 | BJ28: 0.0022373862 | BK28: 0.0022373862 | BL28: 0.0022373862 | BM28: 0.0022373862
E29: =E25+E26+E27 -> 1 | F29: =F25+F26+F27 -> 1 | G29: =G25+G26+G27 -> 1 | H29: =H25+H26+H27 -> 1 | I29: =I25+I26+I27 -> 1 | J29: =J25+J26+J27 -> 1 | K29: =K25+K26+K27 -> 1 | L29: =L25+L26+L27 -> 0.98 | ... BM29: =BM25+BM26+BM27 -> 1
C30: Etapa 2: Recolección
C31: INORG_DCOLL | D31: Recolección diferenciada de residuos inorgánicos | E31: 0.047525076 | F31: 0.051559556 | G31: 0.055929246 | H31: 0.057780602 | I31: 0.05381 | J31: 0.0638 | K31: 0.05141 | L31: 0.08949 | M31: 0.085986 | N31: 0.08136 | O31: 0.080208 | P31: 0.083768 | Q31: 0.0989692 | R31: 0.087374 | S31: 0.087374 | T31: 0.087374 | U31: 0.087374 | V31: 0.087374 | W31: 0.087374 | X31: 0.087374 | Y31: 0.087374 | Z31: 0.087374 | AA31: 0.087374 | AB31: 0.087374 | AC31: 0.087374 | AD31: 0.087374 | AE31: 0.087374 | AF31: 0.087374 | AG31: 0.087374 | AH31: 0.087374 | AI31: 0.087374 | AJ31: 0.087374 | AK31: 0.087374 | AL31: 0.087374 | AM31: 0.087374 | AN31: 0.087374 | AO31: 0.087374 | AP31: 0.087374 | AQ31: 0.087374 | AR31: 0.087374 | AS31: 0.087374 | AT31: 0.087374 | AU31: 0.087374 | AV31: 0.087374 | AW31: 0.087374 | AX31: 0.087374 | AY31: 0.087374 | AZ31: 0.087374 | BA31: 0.087374 | BB31: 0.087374 | BC31: 0.087374 | BD31: 0.087374 | BE31: 0.087374 | BF31: 0.087374 | BG31: 0.087374 | BH31: 0.087374 | BI31: 0.087374 | BJ31: 0.087374 | BK31: 0.087374 | BL31: 0.087374 | BM31: 0.087374
C32: ORG_DCOLL | D32: Recolección diferenciada de residuos orgánicos | E32: 0.040256742 | F32: 0.041913171 | G32: 0.04323439 | H32: 0.047073943 | I32: 0.04619 | J32: 0.0462 | K32: 0.04559 | L32: 0.06437 | M32: 0.067014 | N32: 0.06264 | O32: 0.063792 | P32: 0.064232 | Q32: 0.0670308 | R32: 0.070626 | S32: 0.070626 | T32: 0.070626 | U32: 0.070626 | V32: 0.070626 | W32: 0.070626 | X32: 0.070626 | Y32: 0.070626 | Z32: 0.070626 | AA32: 0.070626 | AB32: 0.070626 | AC32: 0.070626 | AD32: 0.070626 | AE32: 0.070626 | AF32: 0.070626 | AG32: 0.070626 | AH32: 0.070626 | AI32: 0.070626 | AJ32: 0.070626 | AK32: 0.070626 | AL32: 0.070626 | AM32: 0.070626 | AN32: 0.070626 | AO32: 0.070626 | AP32: 0.070626 | AQ32: 0.070626 | AR32: 0.070626 | AS32: 0.070626 | AT32: 0.070626 | AU32: 0.070626 | AV32: 0.070626 | AW32: 0.070626 | AX32: 0.070626 | AY32: 0.070626 | AZ32: 0.070626 | BA32: 0.070626 | BB32: 0.070626 | BC32: 0.070626 | BD32: 0.070626 | BE32: 0.070626 | BF32: 0.070626 | BG32: 0.070626 | BH32: 0.070626 | BI32: 0.070626 | BJ32: 0.070626 | BK32: 0.070626 | BL32: 0.070626 | BM32: 0.070626
C33: BLEND_NO_DCOLL | D33: Recolección no diferenciada de residuos mezclados | E33: 0.91221818 | F33: 0.90652727 | G33: 0.90083636 | H33: 0.89514545 | I33: 0.9 | J33: 0.89 | K33: 0.903 | L33: 0.843 | M33: 0.847 | N33: 0.856 | O33: 0.856 | P33: 0.85 | Q33: 0.834 | R33: 0.842 | S33: 0.84 | T33: 0.84 | U33: 0.84 | V33: 0.84 | W33: 0.84 | X33: 0.84 | Y33: 0.84 | Z33: 0.84 | AA33: 0.84 | AB33: 0.84 | AC33: 0.84 | AD33: 0.84 | AE33: 0.84 | AF33: 0.84 | AG33: 0.84 | AH33: 0.84 | AI33: 0.84 | AJ33: 0.84 | AK33: 0.84 | AL33: 0.84 | AM33: 0.84 | AN33: 0.84 | AO33: 0.84 | AP33: 0.84 | AQ33: 0.84 | AR33: 0.84 | AS33: 0.84 | AT33: 0.84 | AU33: 0.84 | AV33: 0.84 | AW33: 0.84 | AX33: 0.84 | AY33: 0.84 | AZ33: 0.84 | BA33: 0.84 | BB33: 0.84 | BC33: 0.84 | BD33: 0.84 | BE33: 0.84 | BF33: 0.84 | BG33: 0.84 | BH33: 0.84 | BI33: 0.84 | BJ33: 0.84 | BK33: 0.84 | BL33: 0.84 | BM33: 0.84
C34: BLEND_NO_COLL | D34: No recolección de residuos | E34: 0 | F34: 0 | G34: 0 | H34: 0 | I34: 0 | J34: 0 | K34: 0 | L34: 0 | M34: 0 | N34: 0 | O34: 0 | P34: 0 | Q34: 0 | R34: 0 | S34: 0 | T34: 0 | U34: 0 | V34: 0 | W34: 0 | X34: 0 | Y34: 0 | Z34: 0 | AA34: 0 | AB34: 0 | AC34: 0 | AD34: 0 | AE34: 0 | AF34: 0 | AG34: 0 | AH34: 0 | AI34: 0 | AJ34: 0 | AK34: 0 | AL34: 0 | AM34: 0 | AN34: 0 | AO34: 0 | AP34: 0 | AQ34: 0 | AR34: 0 | AS34: 0 | AT34: 0 | AU34: 0 | AV34: 0 | AW34: 0 | AX34: 0 | AY34: 0 | AZ34: 0 | BA34: 0 | BB34: 0 | BC34: 0 | BD34: 0 | BE34: 0 | BF34: 0 | BG34: 0 | BH34: 0 | BI34: 0 | BJ34: 0 | BK34: 0 | BL34: 0 | BM34: 0
E35: =SUM(E31:E34) -> 1 | F35: =SUM(F31:F34) -> 1 | G35: =SUM(G31:G34) -> 1 | H35: =SUM(H31:H34) -> 1 | I35: =SUM(I31:I34) -> 1 | J35: =SUM(J31:J34) -> 1 | K35: =SUM(K31:K34) -> 1 | L35: =SUM(L31:L34) -> 0.99686 | ... BM35: =SUM(BM31:BM34) -> 0.998
C36: Etapa 1: Separación en la fuente
C38: ORG_SS | D38: Separación de residuos orgánicos en la fuente | E38: =E32 -> 0.040256742 | F38: =F32 -> 0.041913171 | G38: =G32 -> 0.04323439 | H38: =H32 -> 0.047073943 | I38: =I32 -> 0.04619 | J38: =J32 -> 0.0462 | K38: =K32 -> 0.04559 | L38: =L32 -> 0.06437 | ... P38: =P32 -> 0.064232 | Q38: =Q31 -> 0.0989692 | R38: =R31 -> 0.087374 | S38: =S31 -> 0.087374 | T38: 0.087374 | U38: 0.087374 | V38: 0.087374 | W38: 0.087374 | X38: 0.087374 | Y38: 0.087374 | Z38: 0.087374 | AA38: 0.087374 | AB38: 0.087374 | AC38: 0.087374 | AD38: 0.087374 | AE38: 0.087374 | AF38: 0.087374 | AG38: 0.087374 | AH38: 0.087374 | AI38: 0.087374 | AJ38: 0.087374 | AK38: 0.087374 | AL38: 0.087374 | AM38: 0.087374 | AN38: 0.087374 | AO38: 0.087374 | AP38: 0.087374 | AQ38: 0.087374 | AR38: 0.087374 | AS38: 0.087374 | AT38: 0.087374 | AU38: 0.087374 | AV38: 0.087374 | AW38: 0.087374 | AX38: 0.087374 | AY38: 0.087374 | AZ38: 0.087374 | BA38: 0.087374 | BB38: 0.087374 | BC38: 0.087374 | BD38: 0.087374 | BE38: 0.087374 | BF38: 0.087374 | BG38: 0.087374 | BH38: 0.087374 | BI38: 0.087374 | BJ38: 0.087374 | BK38: 0.087374 | BL38: 0.087374 | BM38: 0.087374
C39: INORG_SS | D39: Separación de residuos inorgánicos en la fuente | E39: =E31 -> 0.047525076 | F39: =F31 -> 0.051559556 | G39: =G31 -> 0.055929246 | H39: =H31 -> 0.057780602 | I39: =I31 -> 0.05381 | J39: =J31 -> 0.0638 | K39: =K31 -> 0.05141 | L39: =L31 -> 0.08949 | ... P39: =P31 -> 0.083768 | Q39: =Q32 -> 0.0670308 | R39: =R32 -> 0.070626 | S39: =S32 -> 0.070626 | T39: 0.070626 | U39: 0.070626 | V39: 0.070626 | W39: 0.070626 | X39: 0.070626 | Y39: 0.070626 | Z39: 0.070626 | AA39: 0.070626 | AB39: 0.070626 | AC39: 0.070626 | AD39: 0.070626 | AE39: 0.070626 | AF39: 0.070626 | AG39: 0.070626 | AH39: 0.070626 | AI39: 0.070626 | AJ39: 0.070626 | AK39: 0.070626 | AL39: 0.070626 | AM39: 0.070626 | AN39: 0.070626 | AO39: 0.070626 | AP39: 0.070626 | AQ39: 0.070626 | AR39: 0.070626 | AS39: 0.070626 | AT39: 0.070626 | AU39: 0.070626 | AV39: 0.070626 | AW39: 0.070626 | AX39: 0.070626 | AY39: 0.070626 | AZ39: 0.070626 | BA39: 0.070626 | BB39: 0.070626 | BC39: 0.070626 | BD39: 0.070626 | BE39: 0.070626 | BF39: 0.070626 | BG39: 0.070626 | BH39: 0.070626 | BI39: 0.070626 | BJ39: 0.070626 | BK39: 0.070626 | BL39: 0.070626 | BM39: 0.070626
C40: NO_SS | D40: No separación de residuos en la fuente | E40: =E33 -> 0.91221818 | F40: =F33 -> 0.90652727 | G40: =G33 -> 0.90083636 | H40: =H33 -> 0.89514545 | I40: =I33 -> 0.9 | J40: =J33 -> 0.89 | K40: =K33 -> 0.903 | L40: =L33 -> 0.843 | ... S40: =S33 -> 0.84 | T40: 0.84 | U40: 0.84 | V40: 0.84 | W40: 0.84 | X40: 0.84 | Y40: 0.84 | Z40: 0.84 | AA40: 0.84 | AB40: 0.84 | AC40: 0.84 | AD40: 0.84 | AE40: 0.84 | AF40: 0.84 | AG40: 0.84 | AH40: 0.84 | AI40: 0.84 | AJ40: 0.84 | AK40: 0.84 | AL40: 0.84 | AM40: 0.84 | AN40: 0.84 | AO40: 0.84 | AP40: 0.84 | AQ40: 0.84 | AR40: 0.84 | AS40: 0.84 | AT40: 0.84 | AU40: 0.84 | AV40: 0.84 | AW40: 0.84 | AX40: 0.84 | AY40: 0.84 | AZ40: 0.84 | BA40: 0.84 | BB40: 0.84 | BC40: 0.84 | BD40: 0.84 | BE40: 0.84 | BF40: 0.84 | BG40: 0.84 | BH40: 0.84 | BI40: 0.84 | BJ40: 0.84 | BK40: 0.84 | BL40: 0.84 | BM40: 0.84
E41: =SUM(E38:E40) -> 1 | F41: =SUM(F38:F40) -> 1 | G41: =SUM(G38:G40) -> 1 | H41: =SUM(H38:H40) -> 1 | I41: =SUM(I38:I40) -> 1 | J41: =SUM(J38:J40) -> 1 | K41: =SUM(K38:K40) -> 1 | L41: =SUM(L38:L40) -> 0.99686 | ... BM41: =SUM(BM38:BM40) -> 0.998
D43: Inorgánicos u otros sin emisiones
D44: Compostaje | E44: 0.0055 | F44: 0.0064 | G44: 0.0073 | H44: 0.0222 | I44: 0.0372 | J44: 0.0322 | K44: 0.0272 | L44: 0.0305 | M44: 0.0338 | N44: 0.0353 | O44: 0.0368 | P44: 0.0385 | Q44: 0.0337 | R44: 0.0356 | S44: 0.0376 | T44: 0.0396 | U44: 0.0417 | V44: 0.0437 | W44: 0.0459 | X44: 0.048 | Y44: 0.0502 | Z44: 0.0512 | AA44: 0.0521 | AB44: 0.0531 | AC44: 0.0541 | AD44: 0.0551
D45: Sitios gestionados | E45: 1.2472 | F45: 1.354 | G45: 1.4482 | H45: 1.5746 | I45: 1.7108 | J45: 1.9967 | K45: 2.218 | L45: 2.3477 | M45: 2.4618 | N45: 2.4778 | O45: 2.4921 | P45: 2.6399 | Q45: 2.7492 | R45: 2.9082 | S45: 3.0701 | T45: 3.2348 | U45: 3.4022 | V45: 3.5721 | W45: 3.7446 | X45: 3.9197 | Y45: 4.097 | Z45: 4.177 | AA45: 4.2571 | AB45: 4.3372 | AC45: 4.4173 | AD45: 4.4973
D46: Sitios no gestionados | E46: 1.1267 | F46: 1.1059 | G46: 1.0876 | H46: 1.3072 | I46: 1.5439 | J46: 1.0758 | K46: 0.7133 | L46: 0.5753 | M46: 0.4538 | N46: 0.4447 | O46: 0.4366 | P46: 0.3745 | Q46: 0.3847 | R46: 0.4069 | S46: 0.4296 | T46: 0.4526 | U46: 0.476 | V46: 0.4998 | W46: 0.5239 | X46: 0.5484 | Y46: 0.5733 | Z46: 0.5844 | AA46: 0.5957 | AB46: 0.6069 | AC46: 0.6181 | AD46: 0.6293
D47: Incineranción contralada | E47: 0.0091 | F47: 0.0097 | G47: 0.0104 | H47: 0.0108 | I47: 0.0113 | J47: 0.0112 | K47: 0.0112 | L47: 0.0114 | M47: 0.0116 | N47: 0.0151 | O47: 0.0193 | P47: 0.0091 | Q47: 0.0137 | R47: 0.014492478 | S47: 0.015299452 | T47: 0.016119906 | U47: 0.016954093 | V47: 0.017800997 | W47: 0.018660617 | X47: 0.019532953 | Y47: 0.020416479 | Z47: 0.020815261 | AA47: 0.021214552 | AB47: 0.021613589 | AC47: 0.022012625 | AD47: 0.022411408 | AE47: 0.022411408 | AF47: 0.022411408 | AG47: 0.022411408 | AH47: 0.022411408 | AI47: 0.022411408 | AJ47: 0.022411408 | AK47: 0.022411408 | AL47: 0.022411408 | AM47: 0.022411408 | AN47: 0.022411408 | AO47: 0.022411408 | AP47: 0.022411408 | AQ47: 0.022411408 | AR47: 0.022411408 | AS47: 0.022411408 | AT47: 0.022411408 | AU47: 0.022411408 | AV47: 0.022411408 | AW47: 0.022411408 | AX47: 0.022411408 | AY47: 0.022411408 | AZ47: 0.022411408 | BA47: 0.022411408 | BB47: 0.022411408 | BC47: 0.022411408 | BD47: 0.022411408 | BE47: 0.022411408 | BF47: 0.022411408 | BG47: 0.022411408 | BH47: 0.022411408 | BI47: 0.022411408 | BJ47: 0.022411408 | BK47: 0.022411408 | BL47: 0.022411408 | BM47: 0.022411408
D49: Residuos sólidos (Mt)
C51: Códificación OSeMOSYS | D51: BAU
C53: Etapa 4: Disposición final
C54: INORG_RCY_OS | D54: Reciclaje de residuos inorgánicos separados en sitio de disposición final | E54: =E9*$E$83 -> 1.6787459 | F54: =F9*$E$83 -> 1.6787459 | G54: =G9*$E$83 -> 1.6787459 | H54: =H9*$E$83 -> 1.6787459 | I54: =I9*$E$83 -> 1.6787459 | J54: =J9*$E$83 -> 1.6748301 | K54: =K9*$E$83 -> 1.6489171 | L54: =L9*$E$83 -> 1.6239007 | ... BM54: =BM9*$E$83 -> 1.4520566
C55: AD | D55: Digestión Anaerobica | E55: =E10*$E$83 -> 0 | F55: =F10*$E$83 -> 0 | G55: =G10*$E$83 -> 0 | H55: =H10*$E$83 -> 0 | I55: =I10*$E$83 -> 0 | J55: =J10*$E$83 -> 0 | K55: =K10*$E$83 -> 0 | L55: =L10*$E$83 -> 0 | ... BM55: =BM10*$E$83 -> 0
C56: COMPOST | D56: Compostaje | E56: =E11*$E$83 -> 0.0055 | F56: =F11*$E$83 -> 0.0061738288 | G56: =G11*$E$83 -> 0.0068282945 | H56: =H11*$E$83 -> 0.01819154 | I56: =I11*$E$83 -> 0.026898825 | J56: =J11*$E$83 -> 0.024723447 | K56: =K11*$E$83 -> 0.021876688 | L56: =L11*$E$83 -> 0.024605414 | ... BM56: =BM11*$E$83 -> 0.027180839
C57: LANDFILL_BG | D57: Relleno sanitario con quema biogas | E57: =E12*$E$83 -> 0 | F57: =F12*$E$83 -> 0 | G57: =G12*$E$83 -> 0 | H57: =H12*$E$83 -> 0 | I57: =I12*$E$83 -> 0 | J57: =J12*$E$83 -> 0 | K57: =K12*$E$83 -> 0.029828815 | L57: =L12*$E$83 -> 0.051456867 | ... BM57: =BM12*$E$83 -> 0.051456867
C58: LANDFILL | D58: Relleno sanitario | E58: =E13*$E$83 -> 1.2472 | F58: =F13*$E$83 -> 1.3061506 | G58: =G13*$E$83 -> 1.3546214 | H58: =H13*$E$83 -> 1.2902882 | I58: =I13*$E$83 -> 1.2370567 | J58: =J13*$E$83 -> 1.5330841 | K58: =K13*$E$83 -> 1.7839152 | L58: =L13*$E$83 -> 1.8939715 | ... BM58: =BM13*$E$83 -> 2.2185189
C59: NO_CONTR_OD | D59: Botadero a cielo abierto | E59: =E14*$E$83 -> 1.1267 | F59: =F14*$E$83 -> 1.0668183 | G59: =G14*$E$83 -> 1.0173223 | H59: =H14*$E$83 -> 1.0711703 | I59: =I14*$E$83 -> 1.1163736 | J59: =J14*$E$83 -> 0.82600884 | K59: =K14*$E$83 -> 0.57370005 | L59: =L14*$E$83 -> 0.46411458 | ... BM59: =BM14*$E$83 -> 0.3104338
C60: COPROC | D60: Coprocesamiento | E60: =E15*$E$83 -> 0 | F60: =F15*$E$83 -> 0 | G60: =G15*$E$83 -> 0 | H60: =H15*$E$83 -> 0 | I60: =I15*$E$83 -> 0 | J60: =J15*$E$83 -> 0 | K60: =K15*$E$83 -> 0 | L60: =L15*$E$83 -> 0 | ... BM60: =BM15*$E$83 -> 0
C61: INCIN | D61: Incineranción contralada | E61: 0.0091 | F61: 0.0097 | G61: 0.0104 | H61: 0.0108 | I61: 0.0113 | J61: 0.0112 | K61: 0.0112 | L61: 0.0114 | M61: 0.0116 | N61: 0.0151 | O61: 0.0193 | P61: 0.0091 | Q61: 0.0137 | R61: 0.014492478 | S61: 0.015299452 | T61: 0.016119906 | U61: 0.016954093 | V61: 0.017800997 | W61: 0.018660617 | X61: 0.019532953 | Y61: 0.020416479 | Z61: 0.020815261 | AA61: 0.021214552 | AB61: 0.021613589 | AC61: 0.022012625 | AD61: 0.022411408 | AE61: =AE16*$E$83 -> 0.010890403 | AF61: =AF16*$E$83 -> 0.010730288 | AG61: =AG16*$E$83 -> 0.010575236 | AH61: =AH16*$E$83 -> 0.010425277 | AI61: =AI16*$E$83 -> 0.010280331 | AJ61: =AJ16*$E$83 -> 0.01014035 | AK61: =AK16*$E$83 -> 0.010005276 | AL61: =AL16*$E$83 -> 0.0098750124 | ... BM61: =BM16*$E$83 -> 0.0075989211
C62: OPEN_BURN | D62: Quema a cielo abierto | E62: =E17*$E$83 -> 0 | F62: =F17*$E$83 -> 0 | G62: =G17*$E$83 -> 0 | H62: =H17*$E$83 -> 0 | I62: =I17*$E$83 -> 0 | J62: =J17*$E$83 -> 0 | K62: =K17*$E$83 -> 0 | L62: =L17*$E$83 -> 0 | ... BM62: =BM17*$E$83 -> 0
C63: SIT_CLAN | D63: Disposición en sitios clandestinos | E63: =E18*$E$83 -> 0 | F63: =F18*$E$83 -> 0 | G63: =G18*$E$83 -> 0 | H63: =H18*$E$83 -> 0 | I63: =I18*$E$83 -> 0 | J63: =J18*$E$83 -> 0 | K63: =K18*$E$83 -> 0 | L63: =L18*$E$83 -> 0 | ... BM63: =BM18*$E$83 -> 0
E64: =E19*E83 -> 4.0672459 | F64: =F19*F83 -> 4.2162448 | G64: =G19*G83 -> 4.3482153 | H64: =H19*H83 -> 4.9634533 | I64: =I19*I83 -> 5.6248384 | J64: =J19*J83 -> 5.297211 | K64: =K19*K83 -> 5.0569395 | L64: =L19*L83 -> 5.0416139 | ... BM64: =BM19*BM83 -> 11.99548
C65: Etapa 3: Separación en el sitio de disposición final
C66: OSS_INORG | D66: Separación de residuos inorgánicos en sitio de disposición final | E66: =E25*$E$83 -> 0.09824044 | F66: =F25*$E$83 -> 0.1022827 | G66: =G25*$E$83 -> 0.10550694 | H66: =H25*$E$83 -> 0.11487678 | I66: =I25*$E$83 -> 0.11271965 | J66: =J25*$E$83 -> 0.11274406 | K66: =K25*$E$83 -> 0.11125544 | L66: =L25*$E$83 -> 0.15708517 | ... BM66: =BM25*$E$83 -> 0.1403513
C67: OSS_ORG | D67: Separación de residuos orgánicos en sitio de disposición final | E67: =E26*$E$83 -> 0.096648085 | F67: =F26*$E$83 -> 0.1048527 | G67: =G26*$E$83 -> 0.113739 | H67: =H26*$E$83 -> 0.11750396 | I67: =I26*$E$83 -> 0.10942925 | J67: =J26*$E$83 -> 0.12974514 | K67: =K26*$E$83 -> 0.10454856 | L67: =L26*$E$83 -> 0.18198892 | ... BM67: =BM26*$E$83 -> 0.14910751
C68: NO_OSS_BLEND | D68: No separación de residuos mezclados en sitio de disposición final | E68: =E27*$E$83 -> 3.8723574 | F68: =F27*$E$83 -> 3.8601105 | G68: =G27*$E$83 -> 3.8479999 | H68: =H27*$E$83 -> 3.8348651 | I68: =I27*$E$83 -> 3.845097 | J68: =J27*$E$83 -> 3.8247567 | K68: =K27*$E$83 -> 3.8514419 | L68: =L27*$E$83 -> 3.6468269 | ... BM68: =BM27*$E$83 -> 3.7777871
C69: NO_OSS_NO_COLL | D69: No separación de residuos mezclados no recolectados | E69: =E28*$E$83 -> 0.0091 | F69: =F28*$E$83 -> 0.0091 | G69: =G28*$E$83 -> 0.0091 | H69: =H28*$E$83 -> 0.0091 | I69: =I28*$E$83 -> 0.0091 | J69: =J28*$E$83 -> 0.0091 | K69: =K28*$E$83 -> 0.0091 | L69: =L28*$E$83 -> 0.0091 | ... BM69: =BM28*$E$83 -> 0.0091
E70: =E29*E83 -> 4.0672459 | F70: =F29*F83 -> 4.2162448 | G70: =G29*G83 -> 4.3482153 | H70: =H29*H83 -> 4.9634533 | I70: =I29*I83 -> 5.6248384 | J70: =J29*J83 -> 5.297211 | K70: =K29*K83 -> 5.0569395 | L70: =L29*L83 -> 4.9407816 | ... BM70: =BM29*BM83 -> 11.99548
C71: Etapa 2: Recolección
C72: INORG_DCOLL | D72: Recolección diferenciada de residuos inorgánicos | E72: =E31*$E$83 -> 0.19329617 | F72: =F31*$E$83 -> 0.20970539 | G72: =G31*$E$83 -> 0.227478 | H72: =H31*$E$83 -> 0.23500792 | I72: =I31*$E$83 -> 0.2188585 | J72: =J31*$E$83 -> 0.25949029 | K72: =K31*$E$83 -> 0.20909711 | L72: =L31*$E$83 -> 0.36397783 | ... BM72: =BM31*$E$83 -> 0.35537154
C73: ORG_DCOLL | D73: Recolección diferenciada de residuos orgánicos | E73: =E32*$E$83 -> 0.16373407 | F73: =F32*$E$83 -> 0.17047117 | G73: =G32*$E$83 -> 0.17584489 | H73: =H32*$E$83 -> 0.1914613 | I73: =I32*$E$83 -> 0.18786609 | J73: =J32*$E$83 -> 0.18790676 | K73: =K32*$E$83 -> 0.18542574 | L73: =L32*$E$83 -> 0.26180862 | ... BM73: =BM32*$E$83 -> 0.28725331
C74: BLEND_NO_DCOLL | D74: Recolección no diferenciada de residuos mezclados | E74: =E33*$E$83 -> 3.7102156 | F74: =F33*$E$83 -> 3.6870693 | G74: =G33*$E$83 -> 3.663923 | H74: =H33*$E$83 -> 3.6407767 | I74: =I33*$E$83 -> 3.6605213 | J74: =J33*$E$83 -> 3.6198488 | K74: =K33*$E$83 -> 3.672723 | L74: =L33*$E$83 -> 3.4286883 | ... BM74: =BM33*$E$83 -> 3.4164865
C75: BLEND_NO_COLL | D75: No recolección de residuos | E75: =E34*$E$83 -> 0 | F75: =F34*$E$83 -> 0 | G75: =G34*$E$83 -> 0 | H75: =H34*$E$83 -> 0 | I75: =I34*$E$83 -> 0 | J75: =J34*$E$83 -> 0 | K75: =K34*$E$83 -> 0 | L75: =L34*$E$83 -> 0 | ... BM75: =BM34*$E$83 -> 0
E76: =E35*E83 -> 4.0672459 | F76: =F35*F83 -> 4.2162448 | G76: =G35*G83 -> 4.3482153 | H76: =H35*H83 -> 4.9634533 | I76: =I35*I83 -> 5.6248384 | J76: =J35*J83 -> 5.297211 | K76: =K35*K83 -> 5.0569395 | L76: =L35*L83 -> 5.0257833 | ... BM76: =BM35*BM83 -> 11.971489
C77: Etapa 1: Separación en la fuente
C78: ORG_SS | D78: Separación de residuos orgánicos en la fuente | E78: =E38*E83 -> 0.16373407 | F78: =F38*F83 -> 0.17671619 | G78: =G38*G83 -> 0.18799244 | H78: =H38*H83 -> 0.23364932 | I78: =I38*I83 -> 0.25981129 | J78: =J38*J83 -> 0.24473115 | K78: =K38*K83 -> 0.23054587 | L78: =L38*L83 -> 0.32452869 | ... BM78: =BM38*BM83 -> 1.0480931
C79: INORG_SS | D79: Separación de residuos inorgánicos en la fuente | E79: =E39*E83 -> 0.19329617 | F79: =F39*F83 -> 0.21738771 | G79: =G39*G83 -> 0.24319241 | H79: =H39*H83 -> 0.28679132 | I79: =I39*I83 -> 0.30267256 | J79: =J39*J83 -> 0.33796206 | K79: =K39*K83 -> 0.25997726 | L79: =L39*L83 -> 0.45117403 | ... BM79: =BM39*BM83 -> 0.84719276
C80: NO_SS | D80: No separación de residuos en la fuente | E80: =E40*E83 -> 3.7102156 | F80: =F40*F83 -> 3.8221409 | G80: =G40*G83 -> 3.9170305 | H80: =H40*H83 -> 4.4430127 | I80: =I40*I83 -> 5.0623546 | J80: =J40*J83 -> 4.7145178 | K80: =K40*K83 -> 4.5664164 | L80: =L40*L83 -> 4.2500805 | ... BM80: =BM40*BM83 -> 10.076203
E81: =E41*E83 -> 4.0672459 | F81: =F41*F83 -> 4.2162448 | G81: =G41*G83 -> 4.3482153 | H81: =H41*H83 -> 4.9634533 | I81: =I41*I83 -> 5.6248384 | J81: =J41*J83 -> 5.297211 | K81: =K41*K83 -> 5.0569395 | L81: =L41*L83 -> 5.0257833 | ... BM81: =BM41*BM83 -> 11.971489
C83: TSW | D83: Producción de residuos sólidos | E83: 4.0672459 | F83: 4.2162448 | G83: 4.3482153 | H83: 4.9634533 | I83: 5.6248384 | J83: 5.297211 | K83: 5.0569395 | L83: 5.0416139 | M83: 5.0421248 | N83: 5.0625589 | O83: 5.0826525 | P83: 5.0809549 | Q83: 5.024 | R83: 5.1685634 | S83: 5.3182251 | T83: 5.4711369 | U83: 5.6266966 | V83: 5.7846258 | W83: 5.9446358 | X83: 6.1064841 | Y83: 6.2700132 | Z83: 7.7465395 | AA83: 7.8706084 | AB83: 7.99513 | AC83: 8.119959 | AD83: 8.2449716 | AE83: 8.370003 | AF83: 8.4948986 | AG83: 8.6194485 | AH83: 8.7434327 | AI83: 8.8667093 | AJ83: 8.9891084 | AK83: 9.1104639 | AL83: 9.2306421 | AM83: 9.3495143 | AN83: 9.4669604 | AO83: 9.582871 | AP83: 9.6971381 | AQ83: 9.8096582 | AR83: 9.9203392 | AS83: 10.031842 | AT83: 10.171669 | AU83: 10.308131 | AV83: 10.441039 | AW83: 10.57021 | AX83: 10.69546 | AY83: 10.816612 | AZ83: 10.933493 | BA83: 11.045934 | BB83: 11.153771 | BC83: 11.256846 | BD83: 11.355005 | BE83: 11.448104 | BF83: 11.536002 | BG83: 11.618566 | BH83: 11.695672 | BI83: 11.767202 | BJ83: 11.833044 | BK83: 11.893099 | BL83: 11.947273 | BM83: 11.99548
H90: 2030 | I90: 2050 | J90: 2070
E91: OSS_INORG | G91: m OSS_INORG | H91: =(Y25-S25)/($Y$1-$S$1) -> -0.0014573397 | I91: =(AS25-Y25)/($AS$1-$Y$1) -> 5.2047846e-05 | J91: =(BM25-AS25)/($BM$1-$AS$1) -> -8.240909e-06
E92: OSS_ORG | G92: b OSS_INORG | H92: =S25-H91*$S$1 -> 2.9920311 | I92: =Y25-I91*$Y$1 -> -0.072025566 | J92: =Y25-J91*$Y$1 -> 0.050360607
G93: m OSS_ORG | H93: =(Y26-S26)/($Y$1-$S$1) -> -0.0013014795 | I93: =(AS26-Y26)/($AS$1-$Y$1) -> 4.6481412e-05 | J93: =(BM26-AS26)/($BM$1-$AS$1) -> -7.359557e-06 | M93: |
G94: B OSS_ORG | H94: =S26-H93*$S$1 -> 2.6778816 | I94: =Y26-I93*$Y$1 -> -0.058479144 | J94: =AS26-J93*$AS$1 -> 0.051894843

Sheet ParticipacionTechsSolidosTN (
D1: Ecuador | E1: 2010 | F1: 2011 | G1: 2012 | H1: 2013 | I1: 2014 | J1: 2015 | K1: 2016 | L1: 2017 | M1: 2018 | N1: 2019 | O1: 2020 | P1: 2021 | Q1: 2022 | R1: 2023 | S1: 2024 | T1: 2025 | U1: 2026 | V1: 2027 | W1: 2028 | X1: 2029 | Y1: 2030 | Z1: 2031 | AA1: 2032 | AB1: 2033 | AC1: 2034 | AD1: 2035
D4: Residuos sólidos (PORCENTAJES)
C6: Códificación OSeMOSYS | D6: Tendencial Nacional
C8: Etapa 4: Disposición final
C9: INORG_RCY_OS | D9: Reciclaje de residuos inorgánicos separados en sitio de disposición final | E9: =E19-E15 -> 0.0084026138 | F9: =F19-F15 -> 0.0083393746 | G9: =G19-G15 -> 0.0082482141 | H9: =H19-H15 -> 0.0084640956 | I9: =I19-I15 -> 0.0086310534 | J9: =J19-J15 -> 0.0085256798 | K9: =K19-K15 -> 0.0084252217 | L9: =L19-L15 -> 0.0083788193 | ... AD9: =AD19-AD15 -> 0.008111047
C10: AD | D10: Digestión Anaerobica | E10: 0 | F10: 0 | G10: 0 | H10: 0 | I10: 0 | J10: 0 | K10: 0 | L10: 0 | M10: 0 | N10: 0 | O10: 0 | P10: 0 | Q10: 0 | R10: 0 | S10: 0 | T10: 0 | U10: 0 | V10: 0 | W10: 0 | X10: 0 | Y10: 0 | Z10: 0 | AA10: 0 | AB10: 0 | AC10: 0 | AD10: 0
C11: COMPOST | D11: Compostaje | E11: 0.016331389 | F11: 0.018335775 | G11: 0.020436365 | H11: 0.0236 | I11: 0.0236 | J11: 0.0236 | K11: 0.0236 | L11: 0.0236 | M11: 0.0236 | N11: 0.0236 | O11: 0.0236 | P11: 0.0236 | Q11: 0.035046692 | R11: 0.035175404 | S11: 0.035175404 | T11: 0.035175404 | U11: 0.035175404 | V11: 0.035175404 | W11: 0.035175404 | X11: 0.035175404 | Y11: 0.035175404 | Z11: 0.035175404 | AA11: 0.035175404 | AB11: 0.035175404 | AC11: 0.035175404 | AD11: 0.035175404
C12: LANDFILL | D12: Relleno sanitario | E12: 0.33186663 | F12: 0.33972032 | G12: 0.34750426 | H12: 0.35486065 | I12: 0.3681148 | J12: 0.40640579 | K12: 0.41951566 | L12: 0.44091141 | M12: 0.43362624 | N12: 0.46549632 | O12: 0.48722158 | P12: 0.49783433 | Q12: 0.52010075 | R12: 0.5288252 | S12: 0.5288252 | T12: 0.5288252 | U12: 0.5288252 | V12: 0.5288252 | W12: 0.5288252 | X12: 0.5288252 | Y12: 0.5288252 | Z12: 0.5288252 | AA12: 0.5288252 | AB12: 0.5288252 | AC12: 0.5288252 | AD12: 0.5288252
C13: NO_CONTR_OD | D13: Botadero a cielo abierto | E13: 0.64116198 | F13: 0.63130391 | G13: 0.62141938 | H13: 0.61089935 | I13: 0.5976452 | J13: 0.55935421 | K13: 0.54624434 | L13: 0.52484859 | M13: 0.53213376 | N13: 0.50026368 | O13: 0.47853842 | P13: 0.46792567 | Q13: 0.43421255 | R13: 0.4253594 | S13: 0.4253594 | T13: 0.4253594 | U13: 0.4253594 | V13: 0.4253594 | W13: 0.4253594 | X13: 0.4253594 | Y13: 0.4253594 | Z13: 0.4253594 | AA13: 0.4253594 | AB13: 0.4253594 | AC13: 0.4253594 | AD13: 0.4253594
C14: COPROC | D14: Coprocesamiento | E14: 0 | F14: 0 | G14: 0 | H14: 0 | I14: 0 | J14: 0 | K14: 0 | L14: 0 | M14: 0 | N14: 0 | O14: 0 | P14: 0 | Q14: 0 | R14: 0 | S14: 0 | T14: 0 | U14: 0 | V14: 0 | W14: 0 | X14: 0 | Y14: 0 | Z14: 0 | AA14: 0 | AB14: 0 | AC14: 0 | AD14: 0
C15: INCIN | D15: Incineranción contralada | E15: =E42/E77 -> 0.0022373862 | F15: =F42/F77 -> 0.0023006254 | G15: =G42/G77 -> 0.0023917859 | H15: =H42/H77 -> 0.0021759044 | I15: =I42/I77 -> 0.0020089466 | J15: =J42/J77 -> 0.0021143202 | K15: =K42/K77 -> 0.0022147783 | L15: =L42/L77 -> 0.0022611807 | ... AD15: =AD42/AD77 -> 0.002528953
C16: OPEN_BURN | D16: Quema a cielo abierto | E16: 0 | F16: 0 | G16: 0 | H16: 0 | I16: 0 | J16: 0 | K16: 0 | L16: 0 | M16: 0 | N16: 0 | O16: 0 | P16: 0 | Q16: 0 | R16: 0 | S16: 0 | T16: 0 | U16: 0 | V16: 0 | W16: 0 | X16: 0 | Y16: 0 | Z16: 0 | AA16: 0 | AB16: 0 | AC16: 0 | AD16: 0
C17: SIT_CLAN | D17: Disposición en sitios clandestinos | E17: 0 | F17: 0 | G17: 0 | H17: 0 | I17: 0 | J17: 0 | K17: 0 | L17: 0 | M17: 0 | N17: 0 | O17: 0 | P17: 0 | Q17: 0 | R17: 0 | S17: 0 | T17: 0 | U17: 0 | V17: 0 | W17: 0 | X17: 0 | Y17: 0 | Z17: 0 | AA17: 0 | AB17: 0 | AC17: 0 | AD17: 0
E18: =SUM(E9:E17) -> 1 | F18: =SUM(F9:F17) -> 1 | G18: =SUM(G9:G17) -> 1 | H18: =SUM(H9:H17) -> 1 | I18: =SUM(I9:I17) -> 1 | J18: =SUM(J9:J17) -> 1 | K18: =SUM(K9:K17) -> 1 | L18: =SUM(L9:L17) -> 1 | ... AD18: =SUM(AD9:AD17) -> 1
D19: Reciclaje de residuos inorgánicos separados en sitio de disposición final | E19: 0.01064 | F19: 0.01064 | G19: 0.01064 | H19: 0.01064 | I19: 0.01064 | J19: 0.01064 | K19: 0.01064 | L19: 0.01064 | M19: 0.01064 | N19: 0.01064 | O19: 0.01064 | P19: 0.01064 | Q19: 0.01064 | R19: 0.01064 | S19: 0.01064 | T19: 0.01064 | U19: 0.01064 | V19: 0.01064 | W19: 0.01064 | X19: 0.01064 | Y19: 0.01064 | Z19: 0.01064 | AA19: 0.01064 | AB19: 0.01064 | AC19: 0.01064 | AD19: 0.01064
C21: Etapa 3: Separación en el sitio de disposición final
C22: OSS_INORG | D22: Separación de residuos inorgánicos en sitio de disposición final | E22: =E9 -> 0.0084026138 | F22: =F9 -> 0.0083393746 | G22: =G9 -> 0.0082482141 | H22: =H9 -> 0.0084640956 | I22: =I9 -> 0.0086310534 | J22: =J9 -> 0.0085256798 | K22: =K9 -> 0.0084252217 | L22: =L9 -> 0.0083788193 | ... AD22: =AD9 -> 0.008111047
C23: OSS_ORG | D23: Separación de residuos orgánicos en sitio de disposición final | E23: =E11 -> 0.016331389 | F23: =F11 -> 0.018335775 | G23: =G11 -> 0.020436365 | H23: =H11 -> 0.0236 | I23: =I11 -> 0.0236 | J23: =J11 -> 0.0236 | K23: =K11 -> 0.0236 | L23: =L11 -> 0.0236 | ... AD23: =AD11 -> 0.035175404
C24: NO_OSS_BLEND | D24: No separación de residuos mezclados en sitio de disposición final | E24: =1-E23-E22 -> 0.975266 | F24: =1-F23-F22 -> 0.97332485 | G24: =1-G23-G22 -> 0.97131542 | H24: =1-H23-H22 -> 0.9679359 | I24: =1-I23-I22 -> 0.96776895 | J24: =1-J23-J22 -> 0.96787432 | K24: =1-K23-K22 -> 0.96797478 | L24: =1-L23-L22 -> 0.96802118 | ... AD24: =1-AD23-AD22 -> 0.95671355
C25: NO_OSS_NO_COLL | D25: No separación de residuos mezclados no recolectados | E25: 0 | F25: 0 | G25: 0 | H25: 0 | I25: 0 | J25: 0 | K25: 0 | L25: 0 | M25: 0 | N25: 0 | O25: 0 | P25: 0 | Q25: 0 | R25: 0 | S25: 0 | T25: 0 | U25: 0 | V25: 0 | W25: 0 | X25: 0 | Y25: 0 | Z25: 0 | AA25: 0 | AB25: 0 | AC25: 0 | AD25: 0
E26: =E22+E23+E24 -> 1 | F26: =F22+F23+F24 -> 1 | G26: =G22+G23+G24 -> 1 | H26: =H22+H23+H24 -> 1 | I26: =I22+I23+I24 -> 1 | J26: =J22+J23+J24 -> 1 | K26: =K22+K23+K24 -> 1 | L26: =L22+L23+L24 -> 1 | ... AD26: =AD22+AD23+AD24 -> 1
C27: Etapa 2: Recolección
C28: INORG_DCOLL | D28: Recolección diferenciada de residuos inorgánicos | E28: =E22 -> 0.0084026138 | F28: =F22 -> 0.0083393746 | G28: =G22 -> 0.0082482141 | H28: =H22 -> 0.0084640956 | I28: =I22 -> 0.0086310534 | J28: =J22 -> 0.0085256798 | K28: =K22 -> 0.0084252217 | L28: =L22 -> 0.0083788193 | ... AD28: =AD22 -> 0.008111047
C29: ORG_DCOLL | D29: Recolección diferenciada de residuos orgánicos | E29: =E23 -> 0.016331389 | F29: =F23 -> 0.018335775 | G29: =G23 -> 0.020436365 | H29: =H23 -> 0.0236 | I29: =I23 -> 0.0236 | J29: =J23 -> 0.0236 | K29: =K23 -> 0.0236 | L29: =L23 -> 0.0236 | ... AD29: =AD23 -> 0.035175404
C30: BLEND_NO_DCOLL | D30: Recolección no diferenciada de residuos mezclados | E30: =1-E29-E28 -> 0.975266 | F30: =1-F29-F28 -> 0.97332485 | G30: =1-G29-G28 -> 0.97131542 | H30: =1-H29-H28 -> 0.9679359 | I30: =1-I29-I28 -> 0.96776895 | J30: =1-J29-J28 -> 0.96787432 | K30: =1-K29-K28 -> 0.96797478 | L30: =1-L29-L28 -> 0.96802118 | ... AD30: =1-AD29-AD28 -> 0.95671355
C31: BLEND_NO_COLL | D31: No recolección de residuos | E31: 0 | F31: 0 | G31: 0 | H31: 0 | I31: 0 | J31: 0 | K31: 0 | L31: 0 | M31: 0 | N31: 0 | O31: 0 | P31: 0 | Q31: 0 | R31: 0 | S31: 0 | T31: 0 | U31: 0 | V31: 0 | W31: 0 | X31: 0 | Y31: 0 | Z31: 0 | AA31: 0 | AB31: 0 | AC31: 0 | AD31: 0
E32: =SUM(E28:E31) -> 1 | F32: =SUM(F28:F31) -> 1 | G32: =SUM(G28:G31) -> 1 | H32: =SUM(H28:H31) -> 1 | I32: =SUM(I28:I31) -> 1 | J32: =SUM(J28:J31) -> 1 | K32: =SUM(K28:K31) -> 1 | L32: =SUM(L28:L31) -> 1 | ... AD32: =SUM(AD28:AD31) -> 1
C33: Etapa 1: Separación en la fuente
C35: ORG_SS | D35: Separación de residuos orgánicos en la fuente | E35: =E29 -> 0.016331389 | F35: =F29 -> 0.018335775 | G35: =G29 -> 0.020436365 | H35: =H29 -> 0.0236 | I35: =I29 -> 0.0236 | J35: =J29 -> 0.0236 | K35: =K29 -> 0.0236 | L35: =L29 -> 0.0236 | ... AD35: =AD29 -> 0.035175404
C36: INORG_SS | D36: Separación de residuos inorgánicos en la fuente | E36: =E28 -> 0.0084026138 | F36: =F28 -> 0.0083393746 | G36: =G28 -> 0.0082482141 | H36: =H28 -> 0.0084640956 | I36: =I28 -> 0.0086310534 | J36: =J28 -> 0.0085256798 | K36: =K28 -> 0.0084252217 | L36: =L28 -> 0.0083788193 | ... AD36: =AD28 -> 0.008111047
C37: NO_SS | D37: No separación de residuos en la fuente | E37: =E30 -> 0.975266 | F37: =F30 -> 0.97332485 | G37: =G30 -> 0.97131542 | H37: =H30 -> 0.9679359 | I37: =I30 -> 0.96776895 | J37: =J30 -> 0.96787432 | K37: =K30 -> 0.96797478 | L37: =L30 -> 0.96802118 | ... AD37: =AD30 -> 0.95671355
E38: =SUM(E35:E37) -> 1 | F38: =SUM(F35:F37) -> 1 | G38: =SUM(G35:G37) -> 1 | H38: =SUM(H35:H37) -> 1 | I38: =SUM(I35:I37) -> 1 | J38: =SUM(J35:J37) -> 1 | K38: =SUM(K35:K37) -> 1 | L38: =SUM(L35:L37) -> 1 | ... AD38: =SUM(AD35:AD37) -> 1
D42: Incineranción contralada | E42: 0.0091 | F42: 0.0097 | G42: 0.0104 | H42: 0.0108 | I42: 0.0113 | J42: 0.0112 | K42: 0.0112 | L42: 0.0114 | M42: 0.0116 | N42: 0.0151 | O42: 0.0193 | P42: 0.0091 | Q42: 0.0137 | R42: 0.014492478 | S42: 0.015299452 | T42: 0.016119906 | U42: 0.016954093 | V42: 0.017800997 | W42: 0.018660617 | X42: 0.019532953 | Y42: 0.020416479 | Z42: 0.020815261 | AA42: 0.021214552 | AB42: 0.021613589 | AC42: 0.022012625 | AD42: 0.022411408
D44: Residuos sólidos (Mt)
C46: Códificación OSeMOSYS | D46: Tendencial Nacional
C48: Etapa 4: Disposición final
C49: INORG_RCY_OS | D49: Reciclaje de residuos inorgánicos separados en sitio de disposición final | E49: =E9*E77 -> 0.034175496 | F49: =F9*F77 -> 0.035160845 | G49: =G9*G77 -> 0.035865011 | H49: =H9*H77 -> 0.042011143 | I49: =I9*I77 -> 0.048548281 | J49: =J9*J77 -> 0.045162325 | K49: =K9*K77 -> 0.042605837 | L49: =L9*L77 -> 0.042242772 | ... AD49: =AD9*AD77 -> 0.07187954
C50: AD | D50: Digestión Anaerobica | E50: =E10*E77 -> 0 | F50: =F10*F77 -> 0 | G50: =G10*G77 -> 0 | H50: =H10*H77 -> 0 | I50: =I10*I77 -> 0 | J50: =J10*J77 -> 0 | K50: =K10*K77 -> 0 | L50: =L10*L77 -> 0 | ... AD50: =AD10*AD77 -> 0
C51: COMPOST | D51: Compostaje | E51: =E11*E77 -> 0.066423773 | F51: =F11*F77 -> 0.077308115 | G51: =G11*G77 -> 0.088861717 | H51: =H11*H77 -> 0.1171375 | I51: =I11*I77 -> 0.13274619 | J51: =J11*J77 -> 0.12501418 | K51: =K11*K77 -> 0.11934377 | L51: =L11*L77 -> 0.11898209 | ... AD51: =AD11*AD77 -> 0.31172201
C52: LANDFILL | D52: Relleno sanitario | E52: =E12*E77 -> 1.3497832 | F52: =F12*F77 -> 1.432344 | G52: =G12*G77 -> 1.5110233 | H52: =H12*H77 -> 1.7613343 | I52: =I12*I77 -> 2.0705863 | J52: =J12*J77 -> 2.1528172 | K52: =K12*K77 -> 2.1214653 | L52: =L12*L77 -> 2.2229051 | ... AD52: =AD12*AD77 -> 4.6864125
C53: NO_CONTR_OD | D53: Botadero a cielo abierto | E53: =E13*E77 -> 2.6077634 | F53: =F13*F77 -> 2.6617318 | G53: =G13*G77 -> 2.7020653 | H53: =H13*H77 -> 3.0321704 | I53: =I13*I77 -> 3.3616577 | J53: =J13*J77 -> 2.9630173 | K53: =K13*K77 -> 2.7623246 | L53: =L13*L77 -> 2.646084 | ... AD53: =AD13*AD77 -> 3.7695057
C54: COPROC | D54: Coprocesamiento | E54: =E14*E77 -> 0 | F54: =F14*F77 -> 0 | G54: =G14*G77 -> 0 | H54: =H14*H77 -> 0 | I54: =I14*I77 -> 0 | J54: =J14*J77 -> 0 | K54: =K14*K77 -> 0 | L54: =L14*L77 -> 0 | ... AD54: =AD14*AD77 -> 0
C55: INCIN | D55: Incineranción contralada | E55: =E15*E77 -> 0.0091 | F55: =F15*F77 -> 0.0097 | G55: =G15*G77 -> 0.0104 | H55: =H15*H77 -> 0.0108 | I55: =I15*I77 -> 0.0113 | J55: =J15*J77 -> 0.0112 | K55: =K15*K77 -> 0.0112 | L55: =L15*L77 -> 0.0114 | ... AD55: =AD15*AD77 -> 0.022411408
C56: OPEN_BURN | D56: Quema a cielo abierto | E56: =E17*E77 -> 0 | F56: =F17*F77 -> 0 | G56: =G17*G77 -> 0 | H56: =H17*H77 -> 0 | I56: =I17*I77 -> 0 | J56: =J17*J77 -> 0 | K56: =K17*K77 -> 0 | L56: =L17*L77 -> 0 | ... AD56: =AD17*AD77 -> 0
C57: SIT_CLAN | D57: Disposición en sitios clandestinos | E57: =E17*E77 -> 0 | F57: =F17*F77 -> 0 | G57: =G17*G77 -> 0 | H57: =H17*H77 -> 0 | I57: =I17*I77 -> 0 | J57: =J17*J77 -> 0 | K57: =K17*K77 -> 0 | L57: =L17*L77 -> 0 | ... AD57: =AD17*AD77 -> 0
E58: =SUM(E49:E57) -> 4.0672459 | F58: =SUM(F49:F57) -> 4.2162448 | G58: =SUM(G49:G57) -> 4.3482153 | H58: =SUM(H49:H57) -> 4.9634533 | I58: =SUM(I49:I57) -> 5.6248384 | J58: =SUM(J49:J57) -> 5.297211 | K58: =SUM(K49:K57) -> 5.0569395 | L58: =SUM(L49:L57) -> 5.0416139 | ... AD58: =SUM(AD49:AD57) -> 8.8619312
C59: Etapa 3: Separación en el sitio de disposición final
C60: OSS_INORG | D60: Separación de residuos inorgánicos en sitio de disposición final | E60: =E22*E77 -> 0.034175496 | F60: =F22*F77 -> 0.035160845 | G60: =G22*G77 -> 0.035865011 | H60: =H22*H77 -> 0.042011143 | I60: =I22*I77 -> 0.048548281 | J60: =J22*J77 -> 0.045162325 | K60: =K22*K77 -> 0.042605837 | L60: =L22*L77 -> 0.042242772 | ... AD60: =AD22*AD77 -> 0.07187954
C61: OSS_ORG | D61: Separación de residuos orgánicos en sitio de disposición final | E61: =E23*E77 -> 0.066423773 | F61: =F23*F77 -> 0.077308115 | G61: =G23*G77 -> 0.088861717 | H61: =H23*H77 -> 0.1171375 | I61: =I23*I77 -> 0.13274619 | J61: =J23*J77 -> 0.12501418 | K61: =K23*K77 -> 0.11934377 | L61: =L23*L77 -> 0.11898209 | ... AD61: =AD23*AD77 -> 0.31172201
C62: NO_OSS_BLEND | D62: No separación de residuos mezclados en sitio de disposición final | E62: =E24*E77 -> 3.9666466 | F62: =F24*F77 -> 4.1037759 | G62: =G24*G77 -> 4.2234886 | H62: =H24*H77 -> 4.8043047 | I62: =I24*I77 -> 5.443544 | J62: =J24*J77 -> 5.1270345 | K62: =K24*K77 -> 4.8949899 | L62: =L24*L77 -> 4.8803891 | ... AD62: =AD24*AD77 -> 8.4783296
C63: NO_OSS_NO_COLL | D63: No separación de residuos mezclados no recolectados | E63: =E25*E77 -> 0 | F63: =F25*F77 -> 0 | G63: =G25*G77 -> 0 | H63: =H25*H77 -> 0 | I63: =I25*I77 -> 0 | J63: =J25*J77 -> 0 | K63: =K25*K77 -> 0 | L63: =L25*L77 -> 0 | ... AD63: =AD25*AD77 -> 0
E64: =SUM(E60:E63) -> 4.0672459 | F64: =SUM(F60:F63) -> 4.2162448 | G64: =SUM(G60:G63) -> 4.3482153 | H64: =SUM(H60:H63) -> 4.9634533 | I64: =SUM(I60:I63) -> 5.6248384 | J64: =SUM(J60:J63) -> 5.297211 | K64: =SUM(K60:K63) -> 5.0569395 | L64: =SUM(L60:L63) -> 5.0416139 | ... AD64: =SUM(AD60:AD63) -> 8.8619312
C65: Etapa 2: Recolección
C66: INORG_DCOLL | D66: Recolección diferenciada de residuos inorgánicos | E66: =E28*E77 -> 0.034175496 | F66: =F28*F77 -> 0.035160845 | G66: =G28*G77 -> 0.035865011 | H66: =H28*H77 -> 0.042011143 | I66: =I28*I77 -> 0.048548281 | J66: =J28*J77 -> 0.045162325 | K66: =K28*K77 -> 0.042605837 | L66: =L28*L77 -> 0.042242772 | ... AD66: =AD28*AD77 -> 0.07187954
C67: ORG_DCOLL | D67: Recolección diferenciada de residuos orgánicos | E67: =E29*E77 -> 0.066423773 | F67: =F29*F77 -> 0.077308115 | G67: =G29*G77 -> 0.088861717 | H67: =H29*H77 -> 0.1171375 | I67: =I29*I77 -> 0.13274619 | J67: =J29*J77 -> 0.12501418 | K67: =K29*K77 -> 0.11934377 | L67: =L29*L77 -> 0.11898209 | ... AD67: =AD29*AD77 -> 0.31172201
C68: BLEND_NO_DCOLL | D68: Recolección no diferenciada de residuos mezclados | E68: =E30*E77 -> 3.9666466 | F68: =F30*F77 -> 4.1037759 | G68: =G30*G77 -> 4.2234886 | H68: =H30*H77 -> 4.8043047 | I68: =I30*I77 -> 5.443544 | J68: =J30*J77 -> 5.1270345 | K68: =K30*K77 -> 4.8949899 | L68: =L30*L77 -> 4.8803891 | ... AD68: =AD30*AD77 -> 8.4783296
C69: BLEND_NO_COLL | D69: No recolección de residuos | E69: =E31*E77 -> 0 | F69: =F31*F77 -> 0 | G69: =G31*G77 -> 0 | H69: =H31*H77 -> 0 | I69: =I31*I77 -> 0 | J69: =J31*J77 -> 0 | K69: =K31*K77 -> 0 | L69: =L31*L77 -> 0 | ... AD69: =AD31*AD77 -> 0
E70: =SUM(E66:E69) -> 4.0672459 | F70: =SUM(F66:F69) -> 4.2162448 | G70: =SUM(G66:G69) -> 4.3482153 | H70: =SUM(H66:H69) -> 4.9634533 | I70: =SUM(I66:I69) -> 5.6248384 | J70: =SUM(J66:J69) -> 5.297211 | K70: =SUM(K66:K69) -> 5.0569395 | L70: =SUM(L66:L69) -> 5.0416139 | ... AD70: =SUM(AD66:AD69) -> 8.8619312
C71: Etapa 1: Separación en la fuente
C72: ORG_SS | D72: Separación de residuos orgánicos en la fuente | E72: =E35*E77 -> 0.066423773 | F72: =F35*F77 -> 0.077308115 | G72: =G35*G77 -> 0.088861717 | H72: =H35*H77 -> 0.1171375 | I72: =I35*I77 -> 0.13274619 | J72: =J35*J77 -> 0.12501418 | K72: =K35*K77 -> 0.11934377 | L72: =L35*L77 -> 0.11898209 | ... AD72: =AD35*AD77 -> 0.31172201
C73: INORG_SS | D73: Separación de residuos inorgánicos en la fuente | E73: =E36*E77 -> 0.034175496 | F73: =F36*F77 -> 0.035160845 | G73: =G36*G77 -> 0.035865011 | H73: =H36*H77 -> 0.042011143 | I73: =I36*I77 -> 0.048548281 | J73: =J36*J77 -> 0.045162325 | K73: =K36*K77 -> 0.042605837 | L73: =L36*L77 -> 0.042242772 | ... AD73: =AD36*AD77 -> 0.07187954
C74: NO_SS | D74: No separación de residuos en la fuente | E74: =E37*E77 -> 3.9666466 | F74: =F37*F77 -> 4.1037759 | G74: =G37*G77 -> 4.2234886 | H74: =H37*H77 -> 4.8043047 | I74: =I37*I77 -> 5.443544 | J74: =J37*J77 -> 5.1270345 | K74: =K37*K77 -> 4.8949899 | L74: =L37*L77 -> 4.8803891 | ... AD74: =AD37*AD77 -> 8.4783296
E75: =E38*E77 -> 4.0672459 | F75: =F38*F77 -> 4.2162448 | G75: =G38*G77 -> 4.3482153 | H75: =H38*H77 -> 4.9634533 | I75: =I38*I77 -> 5.6248384 | J75: =J38*J77 -> 5.297211 | K75: =K38*K77 -> 5.0569395 | L75: =L38*L77 -> 5.0416139 | ... AD75: =AD38*AD77 -> 8.8619312
C77: TSW | D77: Producción de residuos sólidos | E77: =ProduccionResiduosSolidos!D12 -> 4.0672459 | F77: =ProduccionResiduosSolidos!E12 -> 4.2162448 | G77: =ProduccionResiduosSolidos!F12 -> 4.3482153 | H77: =ProduccionResiduosSolidos!G12 -> 4.9634533 | I77: =ProduccionResiduosSolidos!H12 -> 5.6248384 | J77: =ProduccionResiduosSolidos!I12 -> 5.297211 | K77: =ProduccionResiduosSolidos!J12 -> 5.0569395 | L77: =ProduccionResiduosSolidos!K12 -> 5.0416139 | ... AD77: =ProduccionResiduosSolidos!AC12 -> 8.8619312
P81: Reciclaje de residuos inorgánicos separados en sitio de disposición final | Q81: Compostaje | R81: Relleno sanitario | S81: botadero
E82: kg/hab/día | F82: ton/año | J82: % | K82: % | L82: % | M82: % | N82: % | O82: % | P82: kg/dia | Q82: kg/dia | R82: kg/dia | S82: kg/dia
B83: Fuente | C83: Año | D83: hab | E83: PPC | F83: Generacion | G83: % Botadero | H83: % Celda Emergente | I83: % Relleno Sanitario | J83: Recolección NO diferencidada | K83: Recolección diferencidada | L83: %Orgánicos | M83: %Inorgánicos | N83: Recolección diferenciada de residuos sólidos organico | O83: Recolección diferenciada de residuos sólidos inorganico | P83: RISDF | Q83: RODA | R83: RRS: Residuos sólidos totales a RS | S83: RROB: Residuos sólidos totales a Bot y cel
B84: Reporte de la Gestión, Gasto e Inversión en Protección Ambiental de los Municipios y Consejos Provinciales 2010 | C84: 2010 | D84: 14883661 | E84: 0.74868269 | F84: 4067245.9 | G84: 0.65893435 | H84: 0 | I84: 0.34106565 | J84: 0.91941818 | K84: 0.080581818 | L84: 0.58742857 | M84: 0.41257143 | N84: 0.5414 | O84: 0.4586 | P84: 0.01064 | Q84: 0.016331389 | R84: 0.33186663 | S84: 0.64116198
B85: Reporte de la Gestión, Gasto e Inversión en Protección Ambiental de los Municipios y Consejos Provinciales 2011 | C85: 2011 | D85: 15160587 | E85: 0.76193328 | F85: 4216244.8 | G85: 0.65014228 | H85: 0 | I85: 0.34985772 | J85: 0.91274545 | K85: 0.087254545 | L85: 0.58471429 | M85: 0.41528571 | N85: 0.5516 | O85: 0.4484 | P85: 0.01064 | Q85: 0.018335775 | R85: 0.33972032 | S85: 0.63130391
B86: Reporte de la Gestión, Gasto e Inversión en Protección Ambiental de los Municipios y Consejos Provinciales 2012 | C86: 2012 | D86: 15440550 | E86: 0.77153461 | F86: 4348215.3 | G86: 0.64135021 | H86: 0 | I86: 0.35864979 | J86: 0.90607273 | K86: 0.093927273 | L86: 0.582 | M86: 0.418 | N86: 0.56400964 | O86: 0.43599036 | P86: 0.01064 | Q86: 0.020436365 | R86: 0.34750426 | S86: 0.62141938
B87: Reporte de la Gestión, Gasto e Inversión en Protección Ambiental de los Municipios y Consejos Provinciales 2014 | C87: 2013 | D87: 15717514 | E87: 0.8651815 | F87: 4963453.3 | G87: 0.63255814 | H87: 0 | I87: 0.36744186 | J87: 0.8994 | K87: 0.1006 | L87: 0.57928571 | M87: 0.42071429 | N87: 0.55105482 | O87: 0.44894518 | P87: 0.01064 | Q87: 0.0236 | R87: 0.35486065 | S87: 0.61089935
B88: Reporte de la Gestión, Gasto e Inversión en Protección Ambiental de los Municipios y Consejos Provinciales 2014 | C88: 2014 | D88: 15994366 | E88: 0.96349654 | F88: 5624838.4 | G88: 0.49545455 | H88: 0.13181818 | I88: 0.38636364 | J88: 0.9 | K88: 0.1 | L88: 0.57657143 | M88: 0.42342857 | N88: 0.5381 | O88: 0.4619 | P88: 0.01064 | Q88: 0.0236 | R88: 0.3681148 | S88: 0.5976452
B89: Información Ambiental Económica en Gobiernos Autónomos Descentraliza 2015 | C89: 2015 | D89: 16269171 | E89: 0.89204956 | F89: 5297211 | G89: 0.40723982 | H89: 0.1719457 | I89: 0.42081448 | J89: 0.89 | K89: 0.11 | L89: 0.57385714 | M89: 0.42614286 | N89: 0.58 | O89: 0.42 | P89: 0.01064 | Q89: 0.0236 | R89: 0.40640579 | S89: 0.55935421
B90: Información Ambiental Económica en Gobiernos Autónomos Descentraliza 2016 | C90: 2016 | D90: 16532265 | E90: 0.83803574 | F90: 5056939.5 | G90: 0.35746606 | H90: 0.2081448 | I90: 0.43438914 | J90: 0.903 | K90: 0.097 | L90: 0.57114286 | M90: 0.42885714 | N90: 0.53 | O90: 0.47 | P90: 0.01064 | Q90: 0.0236 | R90: 0.41951566 | S90: 0.54624434
B91: Información Ambiental Económica en Gobiernos Autónomos Descentraliza 2017 | C91: 2017 | D91: 16792803 | E91: 0.82253337 | F91: 5041613.9 | G91: 0.288 | H91: 0.256 | I91: 0.457 | J91: 0.843 | K91: 0.157 | L91: 0.57 | M91: 0.43 | N91: 0.665 | O91: 0.335 | P91: 0.01064 | Q91: 0.0236 | R91: 0.44091141 | S91: 0.52484859
B92: Información Ambiental Económica en Gobiernos Autónomos Descentraliza 2018 | C92: 2018 | D92: 17023408 | E92: 0.80888483 | F92: 5026041.4 | G92: 0.204 | H92: 0.347 | I92: 0.449 | J92: 0.847 | K92: 0.153 | L92: 0.562 | M92: 0.438 | N92: 0.669 | O92: 0.331 | P92: 0.01064 | Q92: 0.0236 | R92: 0.43362624 | S92: 0.53213376
B93: Información Ambiental Económica en Gobiernos Autónomos Descentraliza 2019 | C93: 2019 | D93: 17267986 | E93: 0.79910816 | F93: 5036630.8 | G93: 0.191 | H93: 0.327 | I93: 0.482 | J93: 0.856 | K93: 0.144 | L93: 0.565 | M93: 0.434 | N93: 0.645 | O93: 0.355 | P93: 0.01064 | Q93: 0.0236 | R93: 0.46549632 | S93: 0.50026368
B94: Información Ambiental Económica en Gobiernos Autónomos Descentraliza 2020 | C94: 2020 | D94: 17510643 | E94: 0.79451751 | F94: 5078067 | G94: 0.182 | H94: 0.314 | I94: 0.505 | J94: 0.856 | K94: 0.144 | L94: 0.557 | M94: 0.443 | N94: 0.605 | O94: 0.395 | P94: 0.01064 | Q94: 0.0236 | R94: 0.48722158 | S94: 0.47853842
B95: Información Ambiental Económica en Gobiernos Autónomos Descentraliza 2021 | C95: 2021 | D95: 17751277 | E95: 0.81099793 | F95: 5254630.9 | G95: 0.186 | H95: 0.299 | I95: 0.516 | J95: 0.856 | K95: 0.144 | L95: 0.566 | M95: 0.434 | N95: 0.605 | O95: 0.395 | P95: 0.01064 | Q95: 0.0236 | R95: 0.49783433 | S95: 0.46792567
... B97: Información Ambiental Económica en Gobiernos Autónomos Descentraliza 2023 | C97: 2023 | D97: 18226512 | E97: 0.8803189 | F97: 5856477.2 | G97: 0.172 | H97: 0.272 | I97: 0.552 | J97: 0.842 | K97: 0.158 | L97: 0.553 | M97: 0.447 | N97: 0.504 | O97: 0.496 | P97: 0.01064 | Q97: 0.035175404 | R97: 0.5288252 | S97: 0.4253594
B99: La construcción del modelo del sector Residuos se basó en un enfoque mixto (NDC–PLANMICC), integrando las bases metodológicas, tecnológicas y de datos de ambos ejercicios. Para su desarrollo se consideraron las proyecciones poblacionales del INEC (2024), los parámetros de generación y caracterización de residuos del modelo NDC, y la estructura tecnológica del PLANMICC (Proyecto CZZ 2739). El proceso de calibración, supuestos e incertidumbre se encuentra descrito en la sección 3.7 “Modelamiento del sector Residuos” del Producto 2: Establecimiento de escenarios de emisiones elaborado por el Consorcio USFQ–UCR.
B100: Para más información del proceso se recomienda revisar la sección de Producto 2: Establecimiento de escenarios de emisiones. Informe que detalla el proceso de calibración, supuestos e incertidumbre, del proyecto “Financiamiento de actividades de modelado para el desarrollo de una estrategia nacional de descarbonización en Ecuador para 2050 (PLANMICC) - CZZ 2739”, presentado por el consorcio USFQ–UCR al FIAS, MAATE y AFD, sección 3.7 Modelamiento del sector residuos: calibración, supuestos e incertidumbre

Sheet ParticipacionTechsSolidosPA
D1: Ecuador | E1: 2010 | F1: 2011 | G1: 2012 | H1: 2013 | I1: 2014 | J1: 2015 | K1: 2016 | L1: 2017 | M1: 2018 | N1: 2019 | O1: 2020 | P1: 2021 | Q1: 2022 | R1: 2023 | S1: 2024 | T1: 2025 | U1: 2026 | V1: 2027 | W1: 2028 | X1: 2029 | Y1: 2030 | Z1: 2031 | AA1: 2032 | AB1: 2033 | AC1: 2034 | AD1: 2035
D4: Residuos sólidos (PORCENTAJES)
C6: Códificación OSeMOSYS | D6: Plan de acción
C8: Etapa 4: Disposición final
C9: INORG_RCY_OS | D9: Reciclaje de residuos inorgánicos separados en sitio de disposición final | E9: 0.0084026138 | F9: 0.0083393746 | G9: 0.0082482141 | H9: 0.0084640956 | I9: 0.0086310534 | J9: 0.0085256798 | K9: 0.0084252217 | L9: 0.0083788193 | M9: 0.0083320206 | N9: 0.0076419641 | O9: 0.0070018194 | P9: 0.0088393707 | Q9: 0.0081496508 | R9: 0.0081653933 | S9: 0.008111047 | T9: 0.008111047 | U9: 0.008111047 | V9: 0.008111047 | W9: 0.008111047 | X9: 0.008111047 | Y9: 0.008111047 | Z9: 0.008111047 | AA9: 0.008111047 | AB9: 0.008111047 | AC9: 0.008111047 | AD9: 0.008111047
C10: AD | D10: Digestión Anaerobica | E10: 0 | F10: 0 | G10: 0 | H10: 0 | I10: 0 | J10: 0 | K10: 0 | L10: 0 | M10: 0 | N10: 0 | O10: 0 | P10: 0 | Q10: 0 | R10: 0 | S10: 0 | T10: 0 | U10: 0 | V10: 0 | W10: 0 | X10: 0 | Y10: 0 | Z10: 0 | AA10: 0 | AB10: 0 | AC10: 0 | AD10: 0
C11: COMPOST | D11: Compostaje | E11: 0.0163 | F11: 0.018357763 | G11: 0.020445242 | H11: 0.023632517 | I11: 0.023574172 | J11: 0.02361625 | K11: 0.023591528 | L11: 0.023603618 | M11: 0.023597294 | N11: 0.023607195 | O11: 0.023601267 | P11: 0.023605999 | Q11: 0.035046899 | R11: 0.035174592 | S11: 0.035175298 | T11: 0.035173593 | U11: 0.036800573 | V11: 0.038247872 | W11: 0.03961832 | X11: 0.040880015 | Y11: 0.04197381 | Z11: 0.043151742 | AA11: 0.044272479 | AB11: 0.045340699 | AC11: 0.046358757 | AD11: 0.047318576
C12: LANDFILL | D12: Relleno sanitario | E12: 0.33187087 | F12: 0.33971006 | G12: 0.34749785 | H12: 0.35485413 | I12: 0.36811751 | J12: 0.40640176 | K12: 0.41952313 | L12: 0.4409106 | M12: 0.43362082 | N12: 0.46548911 | O12: 0.48721411 | P12: 0.49782481 | Q12: 0.52010133 | R12: 0.52883332 | S12: 0.5288182 | T12: 0.50453205 | U12: 0.48799289 | V12: 0.49061879 | W12: 0.4930386 | X12: 0.5108242 | Y12: 0.51327406 | Z12: 0.51309814 | AA12: 0.51302428 | AB12: 0.51301267 | AC12: 0.51305696 | AD12: 0.51316528
C13: NO_CONTR_OD | D13: Botadero a cielo abierto | E13: 0.64118913 | F13: 0.63129218 | G13: 0.62141691 | H13: 0.61087335 | I13: 0.59766832 | J13: 0.55934199 | K13: 0.54624534 | L13: 0.52484578 | M13: 0.53214188 | N13: 0.50026369 | O13: 0.47854462 | P13: 0.46792919 | Q13: 0.43421177 | R13: 0.42535209 | S13: 0.4253665 | T13: 0.44965436 | U13: 0.46456653 | V13: 0.46049334 | W13: 0.45670308 | X13: 0.43765578 | Y13: 0.43411213 | Z13: 0.43311012 | AA13: 0.43206324 | AB13: 0.43100663 | AC13: 0.42994428 | AD13: 0.42887615
C14: COPROC | D14: Coprocesamiento | E14: 0 | F14: 0 | G14: 0 | H14: 0 | I14: 0 | J14: 0 | K14: 0 | L14: 0 | M14: 0 | N14: 0 | O14: 0 | P14: 0 | Q14: 0 | R14: 0 | S14: 0 | T14: 0 | U14: 0 | V14: 0 | W14: 0 | X14: 0 | Y14: 0 | Z14: 0 | AA14: 0 | AB14: 0 | AC14: 0 | AD14: 0
C15: INCIN | D15: Incineranción contralada | E15: 0.0022373862 | F15: 0.0023006254 | G15: 0.0023917859 | H15: 0.0021759044 | I15: 0.0020089466 | J15: 0.0021143202 | K15: 0.0022147783 | L15: 0.0022611807 | M15: 0.0023079794 | N15: 0.0029980359 | O15: 0.0036381806 | P15: 0.0018006293 | Q15: 0.0024903492 | R15: 0.0024746067 | S15: 0.002528953 | T15: 0.002528953 | U15: 0.002528953 | V15: 0.002528953 | W15: 0.002528953 | X15: 0.002528953 | Y15: 0.002528953 | Z15: 0.002528953 | AA15: 0.002528953 | AB15: 0.002528953 | AC15: 0.002528953 | AD15: 0.002528953
C16: OPEN_BURN | D16: Quema a cielo abierto | E16: 0 | F16: 0 | G16: 0 | H16: 0 | I16: 0 | J16: 0 | K16: 0 | L16: 0 | M16: 0 | N16: 0 | O16: 0 | P16: 0 | Q16: 0 | R16: 0 | S16: 0 | T16: 0 | U16: 0 | V16: 0 | W16: 0 | X16: 0 | Y16: 0 | Z16: 0 | AA16: 0 | AB16: 0 | AC16: 0 | AD16: 0
C17: SIT_CLAN | D17: Disposición en sitios clandestinos | E17: 0 | F17: 0 | G17: 0 | H17: 0 | I17: 0 | J17: 0 | K17: 0 | L17: 0 | M17: 0 | N17: 0 | O17: 0 | P17: 0 | Q17: 0 | R17: 0 | S17: 0 | T17: 0 | U17: 0 | V17: 0 | W17: 0 | X17: 0 | Y17: 0 | Z17: 0 | AA17: 0 | AB17: 0 | AC17: 0 | AD17: 0
E18: 1 | F18: 1 | G18: 1 | H18: 1 | I18: 1 | J18: 1 | K18: 1 | L18: 1 | M18: 1 | N18: 1 | O18: 1 | P18: 1 | Q18: 1 | R18: 1 | S18: 1 | T18: 1 | U18: 1 | V18: 1 | W18: 1 | X18: 1 | Y18: 1 | Z18: 1 | AA18: 1 | AB18: 1 | AC18: 1 | AD18: 1
C22: Etapa 3: Separación en el sitio de disposición final
C23: OSS_INORG | D23: Separación de residuos inorgánicos en sitio de disposición final | E23: =E10-E16 -> 0 | F23: =F10-F16 -> 0 | G23: =G10-G16 -> 0 | H23: =H10-H16 -> 0 | I23: =I10-I16 -> 0 | J23: =J10-J16 -> 0 | K23: =K10-K16 -> 0 | L23: =L10-L16 -> 0 | ... AD23: =AD10-AD16 -> 0
C24: OSS_ORG | D24: Separación de residuos orgánicos en sitio de disposición final | E24: =E12 -> 0.33187087 | F24: =F12 -> 0.33971006 | G24: =G12 -> 0.34749785 | H24: =H12 -> 0.35485413 | I24: =I12 -> 0.36811751 | J24: =J12 -> 0.40640176 | K24: =K12 -> 0.41952313 | L24: =L12 -> 0.4409106 | ... AD24: =AD12 -> 0.51316528
C25: NO_OSS_BLEND | D25: No separación de residuos mezclados en sitio de disposición final | E25: =1-E24-E23 -> 0.66812913 | F25: =1-F24-F23 -> 0.66028994 | G25: =1-G24-G23 -> 0.65250215 | H25: =1-H24-H23 -> 0.64514587 | I25: =1-I24-I23 -> 0.63188249 | J25: =1-J24-J23 -> 0.59359824 | K25: =1-K24-K23 -> 0.58047687 | L25: =1-L24-L23 -> 0.5590894 | ... AD25: =1-AD24-AD23 -> 0.48683472
C26: NO_OSS_NO_COLL | D26: No separación de residuos mezclados no recolectados | E26: 0 | F26: 0 | G26: 0 | H26: 0 | I26: 0 | J26: 0 | K26: 0 | L26: 0 | M26: 0 | N26: 0 | O26: 0 | P26: 0 | Q26: 0 | R26: 0 | S26: 0 | T26: 0 | U26: 0 | V26: 0 | W26: 0 | X26: 0 | Y26: 0 | Z26: 0 | AA26: 0 | AB26: 0 | AC26: 0 | AD26: 0
E27: =E23+E24+E25 -> 1 | F27: =F23+F24+F25 -> 1 | G27: =G23+G24+G25 -> 1 | H27: =H23+H24+H25 -> 1 | I27: =I23+I24+I25 -> 1 | J27: =J23+J24+J25 -> 1 | K27: =K23+K24+K25 -> 1 | L27: =L23+L24+L25 -> 1 | ... AD27: =AD23+AD24+AD25 -> 1
C28: Etapa 2: Recolección
C29: INORG_DCOLL | D29: Recolección diferenciada de residuos inorgánicos | E29: =E23 -> 0 | F29: =F23 -> 0 | G29: =G23 -> 0 | H29: =H23 -> 0 | I29: =I23 -> 0 | J29: =J23 -> 0 | K29: =K23 -> 0 | L29: =L23 -> 0 | ... AD29: =AD23 -> 0
C30: ORG_DCOLL | D30: Recolección diferenciada de residuos orgánicos | E30: =E24 -> 0.33187087 | F30: =F24 -> 0.33971006 | G30: =G24 -> 0.34749785 | H30: =H24 -> 0.35485413 | I30: =I24 -> 0.36811751 | J30: =J24 -> 0.40640176 | K30: =K24 -> 0.41952313 | L30: =L24 -> 0.4409106 | ... AD30: =AD24 -> 0.51316528
C31: BLEND_NO_DCOLL | D31: Recolección no diferenciada de residuos mezclados | E31: =1-E30-E29 -> 0.66812913 | F31: =1-F30-F29 -> 0.66028994 | G31: =1-G30-G29 -> 0.65250215 | H31: =1-H30-H29 -> 0.64514587 | I31: =1-I30-I29 -> 0.63188249 | J31: =1-J30-J29 -> 0.59359824 | K31: =1-K30-K29 -> 0.58047687 | L31: =1-L30-L29 -> 0.5590894 | ... AD31: =1-AD30-AD29 -> 0.48683472
C32: BLEND_NO_COLL | D32: No recolección de residuos | E32: 0 | F32: 0 | G32: 0 | H32: 0 | I32: 0 | J32: 0 | K32: 0 | L32: 0 | M32: 0 | N32: 0 | O32: 0 | P32: 0 | Q32: 0 | R32: 0 | S32: 0 | T32: 0 | U32: 0 | V32: 0 | W32: 0 | X32: 0 | Y32: 0 | Z32: 0 | AA32: 0 | AB32: 0 | AC32: 0 | AD32: 0
E33: =SUM(E29:E32) -> 1 | F33: =SUM(F29:F32) -> 1 | G33: =SUM(G29:G32) -> 1 | H33: =SUM(H29:H32) -> 1 | I33: =SUM(I29:I32) -> 1 | J33: =SUM(J29:J32) -> 1 | K33: =SUM(K29:K32) -> 1 | L33: =SUM(L29:L32) -> 1 | ... AD33: =SUM(AD29:AD32) -> 1
C34: Etapa 1: Separación en la fuente
C36: ORG_SS | D36: Separación de residuos orgánicos en la fuente | E36: =E30 -> 0.33187087 | F36: =F30 -> 0.33971006 | G36: =G30 -> 0.34749785 | H36: =H30 -> 0.35485413 | I36: =I30 -> 0.36811751 | J36: =J30 -> 0.40640176 | K36: =K30 -> 0.41952313 | L36: =L30 -> 0.4409106 | ... AD36: =AD30 -> 0.51316528
C37: INORG_SS | D37: Separación de residuos inorgánicos en la fuente | E37: =E29 -> 0 | F37: =F29 -> 0 | G37: =G29 -> 0 | H37: =H29 -> 0 | I37: =I29 -> 0 | J37: =J29 -> 0 | K37: =K29 -> 0 | L37: =L29 -> 0 | ... AD37: =AD29 -> 0
C38: NO_SS | D38: No separación de residuos en la fuente | E38: =E31 -> 0.66812913 | F38: =F31 -> 0.66028994 | G38: =G31 -> 0.65250215 | H38: =H31 -> 0.64514587 | I38: =I31 -> 0.63188249 | J38: =J31 -> 0.59359824 | K38: =K31 -> 0.58047687 | L38: =L31 -> 0.5590894 | ... AD38: =AD31 -> 0.48683472
E39: =SUM(E36:E38) -> 1 | F39: =SUM(F36:F38) -> 1 | G39: =SUM(G36:G38) -> 1 | H39: =SUM(H36:H38) -> 1 | I39: =SUM(I36:I38) -> 1 | J39: =SUM(J36:J38) -> 1 | K39: =SUM(K36:K38) -> 1 | L39: =SUM(L36:L38) -> 1 | ... AD39: =SUM(AD36:AD38) -> 1

Sheet ParticipacionTechsSolidosBAU
D1: Ecuador | E1: 2010 | F1: 2011 | G1: 2012 | H1: 2013 | I1: 2014 | J1: 2015 | K1: 2016 | L1: 2017 | M1: 2018 | N1: 2019 | O1: 2020 | P1: 2021 | Q1: 2022 | R1: 2023 | S1: 2024 | T1: 2025 | U1: 2026 | V1: 2027 | W1: 2028 | X1: 2029 | Y1: 2030 | Z1: 2031 | AA1: 2032 | AB1: 2033 | AC1: 2034 | AD1: 2035 | AE1: 2036 | AF1: 2037 | AG1: 2038 | AH1: 2039 | AI1: 2040 | AJ1: 2041 | AK1: 2042 | AL1: 2043 | AM1: 2044 | AN1: 2045 | AO1: 2046 | AP1: 2047 | AQ1: 2048 | AR1: 2049 | AS1: 2050 | AT1: 2051 | AU1: 2052 | AV1: 2053 | AW1: 2054 | AX1: 2055 | AY1: 2056 | AZ1: 2057 | BA1: 2058 | BB1: 2059 | BC1: 2060 | BD1: 2061 | BE1: 2062 | BF1: 2063 | BG1: 2064 | BH1: 2065 | BI1: 2066 | BJ1: 2067 | BK1: 2068 | BL1: 2069 | BM1: 2070
D4: Residuos sólidos (PORCENTAJES)
C6: Códificación OSeMOSYS | D6: BAU
C8: Etapa 4: Disposición final
C9: INORG_RCY_OS | D9: Reciclaje de residuos inorgánicos separados en sitio de disposición final | E9: =E22-E16 -> 0.021916659 | F9: =F22-F16 -> 0.022847277 | G9: =G22-G16 -> 0.023548848 | H9: =H22-H16 -> 0.026068461 | I9: =I22-I16 -> 0.025705053 | J9: =J22-J16 -> 0.02560568 | K9: =K22-K16 -> 0.025139222 | L9: =L22-L16 -> 0.036360819 | ... BM9: =BM22-BM16 -> 0.03263938
C10: AD | D10: Digestión Anaerobica | E10: 0 | F10: 0 | G10: 0 | H10: 0 | I10: 0 | J10: 0 | K10: 0 | L10: 0 | M10: 0 | N10: 0 | O10: 0 | P10: 0 | Q10: 0 | R10: 0 | S10: 0 | T10: 0 | U10: 0 | V10: 0 | W10: 0 | X10: 0 | Y10: 0 | Z10: 0 | AA10: 0 | AB10: 0 | AC10: 0 | AD10: 0 | AE10: 0 | AF10: 0 | AG10: 0 | AH10: 0 | AI10: 0 | AJ10: 0 | AK10: 0 | AL10: 0 | AM10: 0 | AN10: 0 | AO10: 0 | AP10: 0 | AQ10: 0 | AR10: 0 | AS10: 0 | AT10: 0 | AU10: 0 | AV10: 0 | AW10: 0 | AX10: 0 | AY10: 0 | AZ10: 0 | BA10: 0 | BB10: 0 | BC10: 0 | BD10: 0 | BE10: 0 | BF10: 0 | BG10: 0 | BH10: 0 | BI10: 0 | BJ10: 0 | BK10: 0 | BL10: 0 | BM10: 0
C11: COMPOST | D11: Compostaje | E11: 0.023762538 | F11: 0.025779778 | G11: 0.027964623 | H11: 0.028890301 | I11: 0.026905 | J11: 0.0319 | K11: 0.025705 | L11: 0.044745 | M11: 0.042993 | N11: 0.04068 | O11: 0.040104 | P11: 0.041884 | Q11: 0.0494846 | R11: 0.043687 | S11: 0.043687 | T11: =T26 -> 0.04238552 | U11: =U26 -> 0.041084041 | V11: =V26 -> 0.039782561 | W11: =W26 -> 0.038481082 | X11: =X26 -> 0.037179602 | Y11: =Y26 -> 0.035878123 | Z11: =Z26 -> 0.035924604 | AA11: =AA26 -> 0.035971086 | ... BM11: =BM26 -> 0.03666056
C12: LANDFILL_BG | D12: Relleno sanitario con quema biogas | E12: 0 | F12: 0 | G12: 0 | H12: 0 | I12: 0 | J12: 0 | K12: 0.00733391 | L12: 0.012651526 | M12: 0.012651526 | N12: 0.012651526 | O12: 0.012651526 | P12: 0.012651526 | Q12: 0.012651526 | R12: 0.012651526 | S12: 0.012651526 | T12: 0.012651526 | U12: 0.012651526 | V12: 0.012651526 | W12: 0.012651526 | X12: 0.012651526 | Y12: 0.012651526 | Z12: 0.012651526 | AA12: 0.012651526 | AB12: 0.012651526 | AC12: 0.012651526 | AD12: 0.012651526 | AE12: 0.012651526 | AF12: 0.012651526 | AG12: 0.012651526 | AH12: 0.012651526 | AI12: 0.012651526 | AJ12: 0.012651526 | AK12: 0.012651526 | AL12: 0.012651526 | AM12: 0.012651526 | AN12: 0.012651526 | AO12: 0.012651526 | AP12: 0.012651526 | AQ12: 0.012651526 | AR12: 0.012651526 | AS12: 0.012651526 | AT12: 0.012651526 | AU12: 0.012651526 | AV12: 0.012651526 | AW12: 0.012651526 | AX12: 0.012651526 | AY12: 0.012651526 | AZ12: 0.012651526 | BA12: 0.012651526 | BB12: 0.012651526 | BC12: 0.012651526 | BD12: 0.012651526 | BE12: 0.012651526 | BF12: 0.012651526 | BG12: 0.012651526 | BH12: 0.012651526 | BI12: 0.012651526 | BJ12: 0.012651526 | BK12: 0.012651526 | BL12: 0.012651526 | BM12: 0.012651526
C13: LANDFILL | D13: Relleno sanitario | E13: =E21-E12 -> 0.15345822 | F13: =F21-F12 -> 0.17844801 | G13: =G21-G12 -> 0.18257969 | H13: =H21-H12 -> 0.2533691 | I13: =I21-I12 -> 0.29152718 | J13: =J21-J12 -> 0.31758447 | K13: =K21-K12 -> 0.33372535 | L13: =L21-L12 -> 0.29154911 | ... R13: =R21-R12 -> 0.49881803 | S13: 1-% | T13: =1-T9-T11-T12-T14 -> 0.5121708 | U13: =1-U9-U11-U12-U14 -> 0.51499642 | V13: =1-V9-V11-V12-V14 -> 0.51781938 | W13: =1-W9-W11-W12-W14 -> 0.52063997 | X13: =1-X9-X11-X12-X14 -> 0.52345845 | Y13: =1-Y9-Y11-Y12-Y14 -> 0.52627475 | Z13: =1-Z9-Z11-Z12-Z14 -> 0.52560705 | AA13: =1-AA9-AA11-AA12-AA14 -> 0.5255169 | ... BM13: =1-BM9-BM11-BM12-BM14 -> 0.52322829
C14: NO_CONTR_OD | D14: Botadero a cielo abierto | E14: 0.7986252 | F14: 0.77062431 | G14: 0.76351506 | H14: 0.68949623 | I14: 0.65385382 | J14: 0.62279553 | K14: 0.60588174 | L14: 0.61243236 | M14: 0.61811308 | N14: 0.62144192 | O14: 0.58800241 | P14: 0.49931772 | Q14: 0.44896997 | R14: 0.40246785 | S14: 0.39482025 | T14: 0.39482025 | U14: 0.39482025 | V14: 0.39482025 | W14: 0.39482025 | X14: 0.39482025 | Y14: 0.39482025 | Z14: 0.39482025 | AA14: 0.39482025 | AB14: 0.39482025 | AC14: 0.39482025 | AD14: 0.39482025 | AE14: 0.39482025 | AF14: 0.39482025 | AG14: 0.39482025 | AH14: 0.39482025 | AI14: 0.39482025 | AJ14: 0.39482025 | AK14: 0.39482025 | AL14: 0.39482025 | AM14: 0.39482025 | AN14: 0.39482025 | AO14: 0.39482025 | AP14: 0.39482025 | AQ14: 0.39482025 | AR14: 0.39482025 | AS14: 0.39482025 | AT14: 0.39482025 | AU14: 0.39482025 | AV14: 0.39482025 | AW14: 0.39482025 | AX14: 0.39482025 | AY14: 0.39482025 | AZ14: 0.39482025 | BA14: 0.39482025 | BB14: 0.39482025 | BC14: 0.39482025 | BD14: 0.39482025 | BE14: 0.39482025 | BF14: 0.39482025 | BG14: 0.39482025 | BH14: 0.39482025 | BI14: 0.39482025 | BJ14: 0.39482025 | BK14: 0.39482025 | BL14: 0.39482025 | BM14: 0.39482025
C15: COPROC | D15: Coprocesamiento | E15: 0 | F15: 0 | G15: 0 | H15: 0 | I15: 0 | J15: 0 | K15: 0 | L15: 0 | M15: 0 | N15: 0 | O15: 0 | P15: 0 | Q15: 0 | R15: 0 | S15: 0 | T15: 0 | U15: 0 | V15: 0 | W15: 0 | X15: 0 | Y15: 0 | Z15: 0 | AA15: 0 | AB15: 0 | AC15: 0 | AD15: 0 | AE15: 0 | AF15: 0 | AG15: 0 | AH15: 0 | AI15: 0 | AJ15: 0 | AK15: 0 | AL15: 0 | AM15: 0 | AN15: 0 | AO15: 0 | AP15: 0 | AQ15: 0 | AR15: 0 | AS15: 0 | AT15: 0 | AU15: 0 | AV15: 0 | AW15: 0 | AX15: 0 | AY15: 0 | AZ15: 0 | BA15: 0 | BB15: 0 | BC15: 0 | BD15: 0 | BE15: 0 | BF15: 0 | BG15: 0 | BH15: 0 | BI15: 0 | BJ15: 0 | BK15: 0 | BL15: 0 | BM15: 0
C16: INCIN | D16: Incineranción contralada | E16: =E45/E81 -> 0.0022373862 | F16: =F45/F81 -> 0.0023006254 | G16: =G45/G81 -> 0.0023917859 | H16: =H45/H81 -> 0.0021759044 | I16: =I45/I81 -> 0.0020089466 | J16: =J45/J81 -> 0.0021143202 | K16: =K45/K81 -> 0.0022147783 | L16: =L45/L81 -> 0.0022611807 | ... BM16: =BM45/BM81 -> 0.001868321
C17: OPEN_BURN | D17: Quema a cielo abierto | E17: 0 | F17: 0 | G17: 0 | H17: 0 | I17: 0 | J17: 0 | K17: 0 | L17: 0 | M17: 0 | N17: 0 | O17: 0 | P17: 0 | Q17: 0 | R17: 0 | S17: 0 | T17: 0 | U17: 0 | V17: 0 | W17: 0 | X17: 0 | Y17: 0 | Z17: 0 | AA17: 0 | AB17: 0 | AC17: 0 | AD17: 0 | AE17: 0 | AF17: 0 | AG17: 0 | AH17: 0 | AI17: 0 | AJ17: 0 | AK17: 0 | AL17: 0 | AM17: 0 | AN17: 0 | AO17: 0 | AP17: 0 | AQ17: 0 | AR17: 0 | AS17: 0 | AT17: 0 | AU17: 0 | AV17: 0 | AW17: 0 | AX17: 0 | AY17: 0 | AZ17: 0 | BA17: 0 | BB17: 0 | BC17: 0 | BD17: 0 | BE17: 0 | BF17: 0 | BG17: 0 | BH17: 0 | BI17: 0 | BJ17: 0 | BK17: 0 | BL17: 0 | BM17: 0
C18: SIT_CLAN | D18: Disposición en sitios clandestinos | E18: 0 | F18: 0 | G18: 0 | H18: 0 | I18: 0 | J18: 0 | K18: 0 | L18: 0 | M18: 0 | N18: 0 | O18: 0 | P18: 0 | Q18: 0 | R18: 0 | S18: 0 | T18: 0 | U18: 0 | V18: 0 | W18: 0 | X18: 0 | Y18: 0 | Z18: 0 | AA18: 0 | AB18: 0 | AC18: 0 | AD18: 0 | AE18: 0 | AF18: 0 | AG18: 0 | AH18: 0 | AI18: 0 | AJ18: 0 | AK18: 0 | AL18: 0 | AM18: 0 | AN18: 0 | AO18: 0 | AP18: 0 | AQ18: 0 | AR18: 0 | AS18: 0 | AT18: 0 | AU18: 0 | AV18: 0 | AW18: 0 | AX18: 0 | AY18: 0 | AZ18: 0 | BA18: 0 | BB18: 0 | BC18: 0 | BD18: 0 | BE18: 0 | BF18: 0 | BG18: 0 | BH18: 0 | BI18: 0 | BJ18: 0 | BK18: 0 | BL18: 0 | BM18: 0
E19: =SUM(E9:E18) -> 1 | F19: =SUM(F9:F18) -> 1 | G19: =SUM(G9:G18) -> 1 | H19: =SUM(H9:H18) -> 1 | I19: =SUM(I9:I18) -> 1 | J19: =SUM(J9:J18) -> 1 | K19: =SUM(K9:K18) -> 1 | L19: =SUM(L9:L18) -> 1 | ... BM19: =SUM(BM9:BM18) -> 1.0018683
D21: Relleno sanitario | E21: 0.15345822 | F21: 0.17844801 | G21: 0.18257969 | H21: 0.2533691 | I21: 0.29152718 | J21: 0.31758447 | K21: 0.34105926 | L21: 0.30420064 | M21: 0.29868552 | N21: 0.30029408 | O21: 0.33361839 | P21: 0.42025908 | Q21: 0.46132695 | R21: 0.51146955 | S21: 0.52365633
D22: Reciclaje de residuos inorgánicos separados en sitio de disposición final | E22: 0.024154045 | F22: 0.025147903 | G22: 0.025940634 | H22: 0.028244366 | I22: 0.027714 | J22: 0.02772 | K22: 0.027354 | L22: 0.038622 | M22: 0.0402084 | N22: 0.037584 | O22: 0.0382752 | P22: 0.0385392 | Q22: 0.04021848 | R22: 0.0423756 | S22: 0.0423756 | T22: 0.04091826 | U22: 0.039460921 | V22: 0.038003581 | W22: 0.036546241 | X22: 0.035088902 | Y22: 0.033631562 | Z22: 0.03368361 | AA22: 0.033735658 | AB22: 0.033787705 | AC22: 0.033839753 | AD22: 0.033891801 | AE22: 0.033943849 | AF22: 0.033995897 | AG22: 0.034047945 | AH22: 0.034099992 | AI22: 0.03415204 | AJ22: 0.034204088 | AK22: 0.034256136 | AL22: 0.034308184 | AM22: 0.034360232 | AN22: 0.03441228 | AO22: 0.034464327 | AP22: 0.034516375 | AQ22: 0.034568423 | AR22: 0.034620471 | AS22: 0.034672519 | AT22: 0.034672519 | AU22: 0.034672519 | AV22: 0.034672519 | AW22: 0.034672519 | AX22: 0.034672519 | AY22: 0.034672519 | AZ22: 0.034672519 | BA22: 0.034672519 | BB22: 0.034672519 | BC22: 0.034672519 | BD22: 0.034672519 | BE22: 0.034672519 | BF22: 0.034672519 | BG22: 0.034672519 | BH22: 0.034672519 | BI22: 0.034672519 | BJ22: 0.034672519 | BK22: 0.034672519 | BL22: 0.034672519 | BM22: 0.034507701
C24: Etapa 3: Separación en el sitio de disposición final
C25: OSS_INORG | D25: Separación de residuos inorgánicos en sitio de disposición final | E25: 0.024154045 | F25: 0.025147903 | G25: 0.025940634 | H25: 0.028244366 | I25: 0.027714 | J25: 0.02772 | K25: 0.027354 | L25: 0.038622 | M25: 0.0402084 | N25: 0.037584 | O25: 0.0382752 | P25: 0.0385392 | Q25: 0.04021848 | R25: 0.0423756 | S25: 0.0423756 | T25: =$H$90+$H$89*T1 -> 0.04091826 | U25: =$H$90+$H$89*U1 -> 0.039460921 | V25: =$H$90+$H$89*V1 -> 0.038003581 | W25: =$H$90+$H$89*W1 -> 0.036546241 | X25: =$H$90+$H$89*X1 -> 0.035088902 | Y25: =AVERAGE(E25:S25) -> 0.033631562 | Z25: =$I$90+$I$89*Z1 -> 0.03368361 | AA25: =$I$90+$I$89*AA1 -> 0.033735658 | AB25: =$I$90+$I$89*AB1 -> 0.033787705 | AC25: =$I$90+$I$89*AC1 -> 0.033839753 | AD25: =$I$90+$I$89*AD1 -> 0.033891801 | AE25: =$I$90+$I$89*AE1 -> 0.033943849 | AF25: =$I$90+$I$89*AF1 -> 0.033995897 | AG25: =$I$90+$I$89*AG1 -> 0.034047945 | ... AR25: =$I$90+$I$89*AR1 -> 0.034620471 | AS25: =AVERAGE(E25:Y25) -> 0.034672519 | AT25: 0.034672519 | AU25: 0.034672519 | AV25: 0.034672519 | AW25: 0.034672519 | AX25: 0.034672519 | AY25: 0.034672519 | AZ25: 0.034672519 | BA25: 0.034672519 | BB25: 0.034672519 | BC25: 0.034672519 | BD25: 0.034672519 | BE25: 0.034672519 | BF25: 0.034672519 | BG25: 0.034672519 | BH25: 0.034672519 | BI25: 0.034672519 | BJ25: 0.034672519 | BK25: 0.034672519 | BL25: 0.034672519 | BM25: =AVERAGE(E25:BL25) -> 0.034507701
C26: OSS_ORG | D26: Separación de residuos orgánicos en sitio de disposición final | E26: 0.023762538 | F26: 0.025779778 | G26: 0.027964623 | H26: 0.028890301 | I26: 0.026905 | J26: 0.0319 | K26: 0.025705 | L26: 0.044745 | M26: 0.042993 | N26: 0.04068 | O26: 0.040104 | P26: 0.041884 | Q26: 0.0494846 | R26: 0.043687 | S26: 0.043687 | T26: =$H$92+$H$91*T1 -> 0.04238552 | U26: =$H$92+$H$91*U1 -> 0.041084041 | V26: =$H$92+$H$91*V1 -> 0.039782561 | W26: =$H$92+$H$91*W1 -> 0.038481082 | X26: =$H$92+$H$91*X1 -> 0.037179602 | Y26: =AVERAGE(E26:S26) -> 0.035878123 | Z26: =$I$92+$I$91*Z1 -> 0.035924604 | AA26: =$I$92+$I$91*AA1 -> 0.035971086 | AB26: =$I$92+$I$91*AB1 -> 0.036017567 | AC26: =$I$92+$I$91*AC1 -> 0.036064048 | AD26: =$I$92+$I$91*AD1 -> 0.03611053 | AE26: =$I$92+$I$91*AE1 -> 0.036157011 | AF26: =$I$92+$I$91*AF1 -> 0.036203493 | AG26: =$I$92+$I$91*AG1 -> 0.036249974 | ... AR26: =$I$92+$I$91*AR1 -> 0.03676127 | AS26: =AVERAGE(E26:Y26) -> 0.036807751 | AT26: 0.036807751 | AU26: 0.036807751 | AV26: 0.036807751 | AW26: 0.036807751 | AX26: 0.036807751 | AY26: 0.036807751 | AZ26: 0.036807751 | BA26: 0.036807751 | BB26: 0.036807751 | BC26: 0.036807751 | BD26: 0.036807751 | BE26: 0.036807751 | BF26: 0.036807751 | BG26: 0.036807751 | BH26: 0.036807751 | BI26: 0.036807751 | BJ26: 0.036807751 | BK26: 0.036807751 | BL26: 0.036807751 | BM26: =AVERAGE(E26:BL26) -> 0.03666056
C27: NO_OSS_BLEND | D27: No separación de residuos mezclados en sitio de disposición final | E27: 0.95208342 | F27: 0.94907232 | G27: 0.94609474 | H27: 0.94286533 | I27: 0.945381 | J27: 0.94038 | K27: 0.946941 | L27: 0.916633 | M27: 0.9167986 | N27: 0.921736 | O27: 0.9216208 | P27: 0.9195768 | Q27: 0.91029692 | R27: 0.9139374 | S27: 0.91847658 | T27: =1-T26-T25 -> 0.91669622 | U27: =1-U26-U25 -> 0.91945504 | V27: =1-V26-V25 -> 0.92221386 | W27: =1-W26-W25 -> 0.92497268 | X27: =1-X26-X25 -> 0.9277315 | Y27: =1-Y26-Y25 -> 0.93049032 | Z27: =1-Z26-Z25 -> 0.93039179 | AA27: =1-AA26-AA25 -> 0.93029326 | ... BM27: =1-BM26-BM25 -> 0.92883174
C28: NO_OSS_NO_COLL | D28: No separación de residuos mezclados no recolectados | E28: 0.0022373862 | F28: 0.0022373862 | G28: 0.0022373862 | H28: 0.0022373862 | I28: 0.0022373862 | J28: 0.0022373862 | K28: 0.0022373862 | L28: 0.0022373862 | M28: 0.0022373862 | N28: 0.0022373862 | O28: 0.0022373862 | P28: 0.0022373862 | Q28: 0.0022373862 | R28: 0.0022373862 | S28: 0.0022373862 | T28: 0.0022373862 | U28: 0.0022373862 | V28: 0.0022373862 | W28: 0.0022373862 | X28: 0.0022373862 | Y28: 0.0022373862 | Z28: 0.0022373862 | AA28: 0.0022373862 | AB28: 0.0022373862 | AC28: 0.0022373862 | AD28: 0.0022373862 | AE28: 0.0022373862 | AF28: 0.0022373862 | AG28: 0.0022373862 | AH28: 0.0022373862 | AI28: 0.0022373862 | AJ28: 0.0022373862 | AK28: 0.0022373862 | AL28: 0.0022373862 | AM28: 0.0022373862 | AN28: 0.0022373862 | AO28: 0.0022373862 | AP28: 0.0022373862 | AQ28: 0.0022373862 | AR28: 0.0022373862 | AS28: 0.0022373862 | AT28: 0.0022373862 | AU28: 0.0022373862 | AV28: 0.0022373862 | AW28: 0.0022373862 | AX28: 0.0022373862 | AY28: 0.0022373862 | AZ28: 0.0022373862 | BA28: 0.0022373862 | BB28: 0.0022373862 | BC28: 0.0022373862 | BD28: 0.0022373862 | BE28: 0.0022373862 | BF28: 0.0022373862 | BG28: 0.0022373862 | BH28: 0.0022373862 | BI28: 0.0022373862 | BJ28: 0.0022373862 | BK28: 0.0022373862 | BL28: 0.0022373862 | BM28: 0.0022373862
E29: =E25+E26+E27 -> 1 | F29: =F25+F26+F27 -> 1 | G29: =G25+G26+G27 -> 1 | H29: =H25+H26+H27 -> 1 | I29: =I25+I26+I27 -> 1 | J29: =J25+J26+J27 -> 1 | K29: =K25+K26+K27 -> 1 | L29: =L25+L26+L27 -> 1 | ... BM29: =BM25+BM26+BM27 -> 1
C30: Etapa 2: Recolección
C31: INORG_DCOLL | D31: Recolección diferenciada de residuos inorgánicos | E31: 0.047525076 | F31: 0.051559556 | G31: 0.055929246 | H31: 0.057780602 | I31: 0.05381 | J31: 0.0638 | K31: 0.05141 | L31: 0.08949 | M31: 0.085986 | N31: 0.08136 | O31: 0.080208 | P31: 0.083768 | Q31: 0.0989692 | R31: 0.087374 | S31: 0.087374 | T31: 0.087374 | U31: 0.087374 | V31: 0.087374 | W31: 0.087374 | X31: 0.087374 | Y31: 0.087374 | Z31: 0.087374 | AA31: 0.087374 | AB31: 0.087374 | AC31: 0.087374 | AD31: 0.087374 | AE31: 0.087374 | AF31: 0.087374 | AG31: 0.087374 | AH31: 0.087374 | AI31: 0.087374 | AJ31: 0.087374 | AK31: 0.087374 | AL31: 0.087374 | AM31: 0.087374 | AN31: 0.087374 | AO31: 0.087374 | AP31: 0.087374 | AQ31: 0.087374 | AR31: 0.087374 | AS31: 0.087374 | AT31: 0.087374 | AU31: 0.087374 | AV31: 0.087374 | AW31: 0.087374 | AX31: 0.087374 | AY31: 0.087374 | AZ31: 0.087374 | BA31: 0.087374 | BB31: 0.087374 | BC31: 0.087374 | BD31: 0.087374 | BE31: 0.087374 | BF31: 0.087374 | BG31: 0.087374 | BH31: 0.087374 | BI31: 0.087374 | BJ31: 0.087374 | BK31: 0.087374 | BL31: 0.087374 | BM31: 0.087374
C32: ORG_DCOLL | D32: Recolección diferenciada de residuos orgánicos | E32: 0.040256742 | F32: 0.041913171 | G32: 0.04323439 | H32: 0.047073943 | I32: 0.04619 | J32: 0.0462 | K32: 0.04559 | L32: 0.06437 | M32: 0.067014 | N32: 0.06264 | O32: 0.063792 | P32: 0.064232 | Q32: 0.0670308 | R32: 0.070626 | S32: 0.070626 | T32: 0.070626 | U32: 0.070626 | V32: 0.070626 | W32: 0.070626 | X32: 0.070626 | Y32: 0.070626 | Z32: 0.070626 | AA32: 0.070626 | AB32: 0.070626 | AC32: 0.070626 | AD32: 0.070626 | AE32: 0.070626 | AF32: 0.070626 | AG32: 0.070626 | AH32: 0.070626 | AI32: 0.070626 | AJ32: 0.070626 | AK32: 0.070626 | AL32: 0.070626 | AM32: 0.070626 | AN32: 0.070626 | AO32: 0.070626 | AP32: 0.070626 | AQ32: 0.070626 | AR32: 0.070626 | AS32: 0.070626 | AT32: 0.070626 | AU32: 0.070626 | AV32: 0.070626 | AW32: 0.070626 | AX32: 0.070626 | AY32: 0.070626 | AZ32: 0.070626 | BA32: 0.070626 | BB32: 0.070626 | BC32: 0.070626 | BD32: 0.070626 | BE32: 0.070626 | BF32: 0.070626 | BG32: 0.070626 | BH32: 0.070626 | BI32: 0.070626 | BJ32: 0.070626 | BK32: 0.070626 | BL32: 0.070626 | BM32: 0.070626
C33: BLEND_NO_DCOLL | D33: Recolección no diferenciada de residuos mezclados | E33: 0.91221818 | F33: 0.90652727 | G33: 0.90083636 | H33: 0.89514545 | I33: 0.9 | J33: 0.89 | K33: 0.903 | L33: 0.843 | M33: 0.847 | N33: 0.856 | O33: 0.856 | P33: 0.85 | Q33: 0.834 | R33: 0.842 | S33: 0.84 | T33: 0.84 | U33: 0.84 | V33: 0.84 | W33: 0.84 | X33: 0.84 | Y33: 0.84 | Z33: 0.84 | AA33: 0.84 | AB33: 0.84 | AC33: 0.84 | AD33: 0.84 | AE33: 0.84 | AF33: 0.84 | AG33: 0.84 | AH33: 0.84 | AI33: 0.84 | AJ33: 0.84 | AK33: 0.84 | AL33: 0.84 | AM33: 0.84 | AN33: 0.84 | AO33: 0.84 | AP33: 0.84 | AQ33: 0.84 | AR33: 0.84 | AS33: 0.84 | AT33: 0.84 | AU33: 0.84 | AV33: 0.84 | AW33: 0.84 | AX33: 0.84 | AY33: 0.84 | AZ33: 0.84 | BA33: 0.84 | BB33: 0.84 | BC33: 0.84 | BD33: 0.84 | BE33: 0.84 | BF33: 0.84 | BG33: 0.84 | BH33: 0.84 | BI33: 0.84 | BJ33: 0.84 | BK33: 0.84 | BL33: 0.84 | BM33: 0.84
C34: BLEND_NO_COLL | D34: No recolección de residuos | E34: 0 | F34: 0 | G34: 0 | H34: 0 | I34: 0 | J34: 0 | K34: 0 | L34: 0 | M34: 0 | N34: 0 | O34: 0 | P34: 0 | Q34: 0 | R34: 0 | S34: 0 | T34: 0 | U34: 0 | V34: 0 | W34: 0 | X34: 0 | Y34: 0 | Z34: 0 | AA34: 0 | AB34: 0 | AC34: 0 | AD34: 0 | AE34: 0 | AF34: 0 | AG34: 0 | AH34: 0 | AI34: 0 | AJ34: 0 | AK34: 0 | AL34: 0 | AM34: 0 | AN34: 0 | AO34: 0 | AP34: 0 | AQ34: 0 | AR34: 0 | AS34: 0 | AT34: 0 | AU34: 0 | AV34: 0 | AW34: 0 | AX34: 0 | AY34: 0 | AZ34: 0 | BA34: 0 | BB34: 0 | BC34: 0 | BD34: 0 | BE34: 0 | BF34: 0 | BG34: 0 | BH34: 0 | BI34: 0 | BJ34: 0 | BK34: 0 | BL34: 0 | BM34: 0
E35: =SUM(E31:E34) -> 1 | F35: =SUM(F31:F34) -> 1 | G35: =SUM(G31:G34) -> 1 | H35: =SUM(H31:H34) -> 1 | I35: =SUM(I31:I34) -> 1 | J35: =SUM(J31:J34) -> 1 | K35: =SUM(K31:K34) -> 1 | L35: =SUM(L31:L34) -> 0.99686 | ... BM35: =SUM(BM31:BM34) -> 0.998
C36: Etapa 1: Separación en la fuente
C38: ORG_SS | D38: Separación de residuos orgánicos en la fuente | E38: =E32 -> 0.040256742 | F38: =F32 -> 0.041913171 | G38: =G32 -> 0.04323439 | H38: =H32 -> 0.047073943 | I38: =I32 -> 0.04619 | J38: =J32 -> 0.0462 | K38: =K32 -> 0.04559 | L38: =L32 -> 0.06437 | ... P38: =P32 -> 0.064232 | Q38: =Q31 -> 0.0989692 | R38: =R31 -> 0.087374 | S38: =S31 -> 0.087374 | T38: 0.087374 | U38: 0.087374 | V38: 0.087374 | W38: 0.087374 | X38: 0.087374 | Y38: 0.087374 | Z38: 0.087374 | AA38: 0.087374 | AB38: 0.087374 | AC38: 0.087374 | AD38: 0.087374 | AE38: 0.087374 | AF38: 0.087374 | AG38: 0.087374 | AH38: 0.087374 | AI38: 0.087374 | AJ38: 0.087374 | AK38: 0.087374 | AL38: 0.087374 | AM38: 0.087374 | AN38: 0.087374 | AO38: 0.087374 | AP38: 0.087374 | AQ38: 0.087374 | AR38: 0.087374 | AS38: 0.087374 | AT38: 0.087374 | AU38: 0.087374 | AV38: 0.087374 | AW38: 0.087374 | AX38: 0.087374 | AY38: 0.087374 | AZ38: 0.087374 | BA38: 0.087374 | BB38: 0.087374 | BC38: 0.087374 | BD38: 0.087374 | BE38: 0.087374 | BF38: 0.087374 | BG38: 0.087374 | BH38: 0.087374 | BI38: 0.087374 | BJ38: 0.087374 | BK38: 0.087374 | BL38: 0.087374 | BM38: 0.087374
C39: INORG_SS | D39: Separación de residuos inorgánicos en la fuente | E39: =E31 -> 0.047525076 | F39: =F31 -> 0.051559556 | G39: =G31 -> 0.055929246 | H39: =H31 -> 0.057780602 | I39: =I31 -> 0.05381 | J39: =J31 -> 0.0638 | K39: =K31 -> 0.05141 | L39: =L31 -> 0.08949 | ... P39: =P31 -> 0.083768 | Q39: =Q32 -> 0.0670308 | R39: =R32 -> 0.070626 | S39: =S32 -> 0.070626 | T39: 0.070626 | U39: 0.070626 | V39: 0.070626 | W39: 0.070626 | X39: 0.070626 | Y39: 0.070626 | Z39: 0.070626 | AA39: 0.070626 | AB39: 0.070626 | AC39: 0.070626 | AD39: 0.070626 | AE39: 0.070626 | AF39: 0.070626 | AG39: 0.070626 | AH39: 0.070626 | AI39: 0.070626 | AJ39: 0.070626 | AK39: 0.070626 | AL39: 0.070626 | AM39: 0.070626 | AN39: 0.070626 | AO39: 0.070626 | AP39: 0.070626 | AQ39: 0.070626 | AR39: 0.070626 | AS39: 0.070626 | AT39: 0.070626 | AU39: 0.070626 | AV39: 0.070626 | AW39: 0.070626 | AX39: 0.070626 | AY39: 0.070626 | AZ39: 0.070626 | BA39: 0.070626 | BB39: 0.070626 | BC39: 0.070626 | BD39: 0.070626 | BE39: 0.070626 | BF39: 0.070626 | BG39: 0.070626 | BH39: 0.070626 | BI39: 0.070626 | BJ39: 0.070626 | BK39: 0.070626 | BL39: 0.070626 | BM39: 0.070626
C40: NO_SS | D40: No separación de residuos en la fuente | E40: =E33 -> 0.91221818 | F40: =F33 -> 0.90652727 | G40: =G33 -> 0.90083636 | H40: =H33 -> 0.89514545 | I40: =I33 -> 0.9 | J40: =J33 -> 0.89 | K40: =K33 -> 0.903 | L40: =L33 -> 0.843 | ... S40: =S33 -> 0.84 | T40: 0.84 | U40: 0.84 | V40: 0.84 | W40: 0.84 | X40: 0.84 | Y40: 0.84 | Z40: 0.84 | AA40: 0.84 | AB40: 0.84 | AC40: 0.84 | AD40: 0.84 | AE40: 0.84 | AF40: 0.84 | AG40: 0.84 | AH40: 0.84 | AI40: 0.84 | AJ40: 0.84 | AK40: 0.84 | AL40: 0.84 | AM40: 0.84 | AN40: 0.84 | AO40: 0.84 | AP40: 0.84 | AQ40: 0.84 | AR40: 0.84 | AS40: 0.84 | AT40: 0.84 | AU40: 0.84 | AV40: 0.84 | AW40: 0.84 | AX40: 0.84 | AY40: 0.84 | AZ40: 0.84 | BA40: 0.84 | BB40: 0.84 | BC40: 0.84 | BD40: 0.84 | BE40: 0.84 | BF40: 0.84 | BG40: 0.84 | BH40: 0.84 | BI40: 0.84 | BJ40: 0.84 | BK40: 0.84 | BL40: 0.84 | BM40: 0.84
E41: =SUM(E38:E40) -> 1 | F41: =SUM(F38:F40) -> 1 | G41: =SUM(G38:G40) -> 1 | H41: =SUM(H38:H40) -> 1 | I41: =SUM(I38:I40) -> 1 | J41: =SUM(J38:J40) -> 1 | K41: =SUM(K38:K40) -> 1 | L41: =SUM(L38:L40) -> 0.99686 | ... BM41: =SUM(BM38:BM40) -> 0.998
E45: 0.0091 | F45: 0.0097 | G45: 0.0104 | H45: 0.0108 | I45: 0.0113 | J45: 0.0112 | K45: 0.0112 | L45: 0.0114 | M45: 0.0116 | N45: 0.0151 | O45: 0.0193 | P45: 0.0091 | Q45: 0.0137 | R45: 0.014492478 | S45: 0.015299452 | T45: 0.016119906 | U45: 0.016954093 | V45: 0.017800997 | W45: 0.018660617 | X45: 0.019532953 | Y45: 0.020416479 | Z45: 0.020815261 | AA45: 0.021214552 | AB45: 0.021613589 | AC45: 0.022012625 | AD45: 0.022411408 | AE45: 0.022411408 | AF45: 0.022411408 | AG45: 0.022411408 | AH45: 0.022411408 | AI45: 0.022411408 | AJ45: 0.022411408 | AK45: 0.022411408 | AL45: 0.022411408 | AM45: 0.022411408 | AN45: 0.022411408 | AO45: 0.022411408 | AP45: 0.022411408 | AQ45: 0.022411408 | AR45: 0.022411408 | AS45: 0.022411408 | AT45: 0.022411408 | AU45: 0.022411408 | AV45: 0.022411408 | AW45: 0.022411408 | AX45: 0.022411408 | AY45: 0.022411408 | AZ45: 0.022411408 | BA45: 0.022411408 | BB45: 0.022411408 | BC45: 0.022411408 | BD45: 0.022411408 | BE45: 0.022411408 | BF45: 0.022411408 | BG45: 0.022411408 | BH45: 0.022411408 | BI45: 0.022411408 | BJ45: 0.022411408 | BK45: 0.022411408 | BL45: 0.022411408 | BM45: 0.022411408
D47: Residuos sólidos (Mt)
C49: Códificación OSeMOSYS | D49: BAU
C51: Etapa 4: Disposición final
C52: INORG_RCY_OS | D52: Reciclaje de residuos inorgánicos separados en sitio de disposición final | E52: =E9*E81 -> 0.08914044 | F52: =F9*$E$81 -> 0.092925494 | G52: =G9*$E$81 -> 0.095778955 | H52: =H9*$E$81 -> 0.10602684 | I52: =I9*$E$81 -> 0.10454877 | J52: =J9*$E$81 -> 0.1041446 | K52: =K9*$E$81 -> 0.1022474 | L52: =L9*$E$81 -> 0.14788839 | M52: =M9*$E$81 -> 0.15418027 | ... BM52: =BM9*$E$81 -> 0.13275238
C53: AD | D53: Digestión Anaerobica | E53: =E10*$E$81 -> 0 | F53: =F10*$E$81 -> 0 | G53: =G10*$E$81 -> 0 | H53: =H10*$E$81 -> 0 | I53: =I10*$E$81 -> 0 | J53: =J10*$E$81 -> 0 | K53: =K10*$E$81 -> 0 | L53: =L10*$E$81 -> 0 | ... BM53: =BM10*$E$81 -> 0
C54: COMPOST | D54: Compostaje | E54: =E11*$E$81 -> 0.096648085 | F54: =F11*$E$81 -> 0.1048527 | G54: =G11*$E$81 -> 0.113739 | H54: =H11*$E$81 -> 0.11750396 | I54: =I11*$E$81 -> 0.10942925 | J54: =J11*$E$81 -> 0.12974514 | K54: =K11*$E$81 -> 0.10454856 | L54: =L11*$E$81 -> 0.18198892 | ... BM54: =BM11*$E$81 -> 0.14910751
C55: LANDFILL_BG | D55: Relleno sanitario con quema biogas | E55: =E12*$E$81 -> 0 | F55: =F12*$E$81 -> 0 | G55: =G12*$E$81 -> 0 | H55: =H12*$E$81 -> 0 | I55: =I12*$E$81 -> 0 | J55: =J12*$E$81 -> 0 | K55: =K12*$E$81 -> 0.029828815 | L55: =L12*$E$81 -> 0.051456867 | ... BM55: =BM12*$E$81 -> 0.051456867
C56: LANDFILL | D56: Relleno sanitario | E56: =E13*$E$81 -> 0.6241523 | F56: =F13*$E$81 -> 0.72579193 | G56: =G13*$E$81 -> 0.74259648 | H56: =H13*$E$81 -> 1.0305144 | I56: =I13*$E$81 -> 1.1857127 | J56: =J13*$E$81 -> 1.2916941 | K56: =K13*$E$81 -> 1.357343 | L56: =L13*$E$81 -> 1.1858019 | ... BM56: =BM13*$E$81 -> 2.1280981
C57: NO_CONTR_OD | D57: Botadero a cielo abierto | E57: =E14*E81 -> 3.2482051 | F57: =F14*F81 -> 3.2491408 | G57: =G14*G81 -> 3.3199279 | H57: =H14*H81 -> 3.4222824 | I57: =I14*I81 -> 3.6778221 | J57: =J14*J81 -> 3.2990793 | K57: =K14*K81 -> 3.0639073 | L57: =L14*L81 -> 3.0876475 | ... BM57: =BM14*BM81 -> 4.7360583
C58: COPROC | D58: Coprocesamiento | E58: =E15*E81 -> 0 | F58: =F15*F81 -> 0 | G58: =G15*G81 -> 0 | H58: =H15*H81 -> 0 | I58: =I15*I81 -> 0 | J58: =J15*J81 -> 0 | K58: =K15*K81 -> 0 | L58: =L15*L81 -> 0 | ... BQ58: =BQ15*BQ81 -> 0
C59: INCIN | D59: Incineranción contralada | E59: 0.0091 | F59: 1.0091 | G59: 2.0091 | H59: 3.0091 | I59: 4.0091 | J59: 5.0091 | K59: 6.0091 | L59: 7.0091 | M59: 8.0091 | N59: 9.0091 | O59: 10.0091 | P59: 11.0091 | Q59: 12.0091 | R59: 13.0091 | S59: 14.0091 | T59: 15.0091 | U59: 16.0091 | V59: 17.0091 | W59: 18.0091 | X59: 19.0091 | Y59: 20.0091 | Z59: 21.0091 | AA59: 22.0091 | AB59: 23.0091 | AC59: 24.0091 | AD59: 25.0091 | AE59: 26.0091 | AF59: 27.0091 | AG59: 28.0091 | AH59: 29.0091 | AI59: 30.0091 | AJ59: 31.0091 | AK59: 32.0091 | AL59: 33.0091 | AM59: 34.0091 | AN59: 35.0091 | AO59: 36.0091 | AP59: 37.0091 | AQ59: 38.0091 | AR59: 39.0091 | AS59: 40.0091 | AT59: 41.0091 | AU59: 42.0091 | AV59: 43.0091 | AW59: 44.0091 | AX59: 45.0091 | AY59: 46.0091 | AZ59: 47.0091 | BA59: 48.0091 | BB59: 49.0091 | BC59: 50.0091 | BD59: 51.0091 | BE59: 52.0091 | BF59: 53.0091 | BG59: 54.0091 | BH59: 55.0091 | BI59: 56.0091 | BJ59: 57.0091 | BK59: 58.0091 | BL59: 59.0091 | BM59: 60.0091 | BN59: 61.0091 | BO59: 62.0091 | BP59: 63.0091 | BQ59: 64.0091
C60: OPEN_BURN | D60: Quema a cielo abierto | E60: =E17*E81 -> 0 | F60: =F17*F81 -> 0 | G60: =G17*G81 -> 0 | H60: =H17*H81 -> 0 | I60: =I17*I81 -> 0 | J60: =J17*J81 -> 0 | K60: =K17*K81 -> 0 | L60: =L17*L81 -> 0 | ... BQ60: =BQ17*BQ81 -> 0
C61: SIT_CLAN | D61: Disposición en sitios clandestinos | E61: =E18*E81 -> 0 | F61: =F18*F81 -> 0 | G61: =G18*G81 -> 0 | H61: =H18*H81 -> 0 | I61: =I18*I81 -> 0 | J61: =J18*J81 -> 0 | K61: =K18*K81 -> 0 | L61: =L18*L81 -> 0 | ... BQ61: =BQ18*BQ81 -> 0
E62: =SUM(E52:E61) -> 4.0672459 | F62: =SUM(F52:F61) -> 5.1818109 | G62: =SUM(G52:G61) -> 6.2811423 | H62: =SUM(H52:H61) -> 7.6854276 | I62: =SUM(I52:I61) -> 9.0866128 | J62: =SUM(J52:J61) -> 9.8337632 | K62: =SUM(K52:K61) -> 10.666975 | L62: =SUM(L52:L61) -> 11.663884 | ... BI62: =SUM(BI52:BI61) -> 63.116444 | BJ62: =BJ19*BJ81 -> 11.855456 | BK62: =BK19*BK81 -> 11.915511 | BL62: =BL19*BL81 -> 11.969684 | BM62: =BM19*BM81 -> 12.017891
C63: Etapa 3: Separación en el sitio de disposición final
C64: OSS_INORG | D64: Separación de residuos inorgánicos en sitio de disposición final | E64: =E25*$E$81 -> 0.09824044 | F64: =F25*$E$81 -> 0.1022827 | G64: =G25*$E$81 -> 0.10550694 | H64: =H25*$E$81 -> 0.11487678 | I64: =I25*$E$81 -> 0.11271965 | J64: =J25*$E$81 -> 0.11274406 | K64: =K25*$E$81 -> 0.11125544 | L64: =L25*$E$81 -> 0.15708517 | ... BM64: =BM25*$E$81 -> 0.1403513
C65: OSS_ORG | D65: Separación de residuos orgánicos en sitio de disposición final | E65: =E26*$E$81 -> 0.096648085 | F65: =F26*$E$81 -> 0.1048527 | G65: =G26*$E$81 -> 0.113739 | H65: =H26*$E$81 -> 0.11750396 | I65: =I26*$E$81 -> 0.10942925 | J65: =J26*$E$81 -> 0.12974514 | K65: =K26*$E$81 -> 0.10454856 | L65: =L26*$E$81 -> 0.18198892 | ... BM65: =BM26*$E$81 -> 0.14910751
C66: NO_OSS_BLEND | D66: No separación de residuos mezclados en sitio de disposición final | E66: =E27*$E$81 -> 3.8723574 | F66: =F27*$E$81 -> 3.8601105 | G66: =G27*$E$81 -> 3.8479999 | H66: =H27*$E$81 -> 3.8348651 | I66: =I27*$E$81 -> 3.845097 | J66: =J27*$E$81 -> 3.8247567 | K66: =K27*$E$81 -> 3.8514419 | L66: =L27*$E$81 -> 3.7281718 | ... BM66: =BM27*$E$81 -> 3.7777871
C67: NO_OSS_NO_COLL | D67: No separación de residuos mezclados no recolectados | E67: =E28*$E$81 -> 0.0091 | F67: =F28*$E$81 -> 0.0091 | G67: =G28*$E$81 -> 0.0091 | H67: =H28*$E$81 -> 0.0091 | I67: =I28*$E$81 -> 0.0091 | J67: =J28*$E$81 -> 0.0091 | K67: =K28*$E$81 -> 0.0091 | L67: =L28*$E$81 -> 0.0091 | ... BM67: =BM28*$E$81 -> 0.0091
E68: =E29*E81 -> 4.0672459 | F68: =F29*F81 -> 4.2162448 | G68: =G29*G81 -> 4.3482153 | H68: =H29*H81 -> 4.9634533 | I68: =I29*I81 -> 5.6248384 | J68: =J29*J81 -> 5.297211 | K68: =K29*K81 -> 5.0569395 | L68: =L29*L81 -> 5.0416139 | ... BM68: =BM29*BM81 -> 11.99548
C69: Etapa 2: Recolección
C70: INORG_DCOLL | D70: Recolección diferenciada de residuos inorgánicos | E70: =E31*$E$81 -> 0.19329617 | F70: =F31*$E$81 -> 0.20970539 | G70: =G31*$E$81 -> 0.227478 | H70: =H31*$E$81 -> 0.23500792 | I70: =I31*$E$81 -> 0.2188585 | J70: =J31*$E$81 -> 0.25949029 | K70: =K31*$E$81 -> 0.20909711 | L70: =L31*$E$81 -> 0.36397783 | ... BM70: =BM31*$E$81 -> 0.35537154
C71: ORG_DCOLL | D71: Recolección diferenciada de residuos orgánicos | E71: =E32*$E$81 -> 0.16373407 | F71: =F32*$E$81 -> 0.17047117 | G71: =G32*$E$81 -> 0.17584489 | H71: =H32*$E$81 -> 0.1914613 | I71: =I32*$E$81 -> 0.18786609 | J71: =J32*$E$81 -> 0.18790676 | K71: =K32*$E$81 -> 0.18542574 | L71: =L32*$E$81 -> 0.26180862 | ... BM71: =BM32*$E$81 -> 0.28725331
C72: BLEND_NO_DCOLL | D72: Recolección no diferenciada de residuos mezclados | E72: =E33*$E$81 -> 3.7102156 | F72: =F33*$E$81 -> 3.6870693 | G72: =G33*$E$81 -> 3.663923 | H72: =H33*$E$81 -> 3.6407767 | I72: =I33*$E$81 -> 3.6605213 | J72: =J33*$E$81 -> 3.6198488 | K72: =K33*$E$81 -> 3.672723 | L72: =L33*$E$81 -> 3.4286883 | ... BM72: =BM33*$E$81 -> 3.4164865
C73: BLEND_NO_COLL | D73: No recolección de residuos | E73: =E34*$E$81 -> 0 | F73: =F34*$E$81 -> 0 | G73: =G34*$E$81 -> 0 | H73: =H34*$E$81 -> 0 | I73: =I34*$E$81 -> 0 | J73: =J34*$E$81 -> 0 | K73: =K34*$E$81 -> 0 | L73: =L34*$E$81 -> 0 | ... BM73: =BM34*$E$81 -> 0
E74: =E35*E81 -> 4.0672459 | F74: =F35*F81 -> 4.2162448 | G74: =G35*G81 -> 4.3482153 | H74: =H35*H81 -> 4.9634533 | I74: =I35*I81 -> 5.6248384 | J74: =J35*J81 -> 5.297211 | K74: =K35*K81 -> 5.0569395 | L74: =L35*L81 -> 5.0257833 | ... BM74: =BM35*BM81 -> 11.971489
C75: Etapa 1: Separación en la fuente
C76: ORG_SS | D76: Separación de residuos orgánicos en la fuente | E76: =E38*E81 -> 0.16373407 | F76: =F38*F81 -> 0.17671619 | G76: =G38*G81 -> 0.18799244 | H76: =H38*H81 -> 0.23364932 | I76: =I38*I81 -> 0.25981129 | J76: =J38*J81 -> 0.24473115 | K76: =K38*K81 -> 0.23054587 | L76: =L38*L81 -> 0.32452869 | ... BM76: =BM38*BM81 -> 1.0480931
C77: INORG_SS | D77: Separación de residuos inorgánicos en la fuente | E77: =E39*E81 -> 0.19329617 | F77: =F39*F81 -> 0.21738771 | G77: =G39*G81 -> 0.24319241 | H77: =H39*H81 -> 0.28679132 | I77: =I39*I81 -> 0.30267256 | J77: =J39*J81 -> 0.33796206 | K77: =K39*K81 -> 0.25997726 | L77: =L39*L81 -> 0.45117403 | ... BM77: =BM39*BM81 -> 0.84719276
C78: NO_SS | D78: No separación de residuos en la fuente | E78: =E40*E81 -> 3.7102156 | F78: =F40*F81 -> 3.8221409 | G78: =G40*G81 -> 3.9170305 | H78: =H40*H81 -> 4.4430127 | I78: =I40*I81 -> 5.0623546 | J78: =J40*J81 -> 4.7145178 | K78: =K40*K81 -> 4.5664164 | L78: =L40*L81 -> 4.2500805 | ... BM78: =BM40*BM81 -> 10.076203
E79: =E41*E81 -> 4.0672459 | F79: =F41*F81 -> 4.2162448 | G79: =G41*G81 -> 4.3482153 | H79: =H41*H81 -> 4.9634533 | I79: =I41*I81 -> 5.6248384 | J79: =J41*J81 -> 5.297211 | K79: =K41*K81 -> 5.0569395 | L79: =L41*L81 -> 5.0257833 | ... BM79: =BM41*BM81 -> 11.971489
C81: TSW | D81: Producción de residuos sólidos | E81: 4.0672459 | F81: 4.2162448 | G81: 4.3482153 | H81: 4.9634533 | I81: 5.6248384 | J81: 5.297211 | K81: 5.0569395 | L81: 5.0416139 | M81: 5.0421248 | N81: 5.0625589 | O81: 5.0826525 | P81: 5.0809549 | Q81: 5.024 | R81: 5.1685634 | S81: 5.3182251 | T81: 5.4711369 | U81: 5.6266966 | V81: 5.7846258 | W81: 5.9446358 | X81: 6.1064841 | Y81: 6.2700132 | Z81: 7.7465395 | AA81: 7.8706084 | AB81: 7.99513 | AC81: 8.119959 | AD81: 8.2449716 | AE81: 8.370003 | AF81: 8.4948986 | AG81: 8.6194485 | AH81: 8.7434327 | AI81: 8.8667093 | AJ81: 8.9891084 | AK81: 9.1104639 | AL81: 9.2306421 | AM81: 9.3495143 | AN81: 9.4669604 | AO81: 9.582871 | AP81: 9.6971381 | AQ81: 9.8096582 | AR81: 9.9203392 | AS81: 10.031842 | AT81: 10.171669 | AU81: 10.308131 | AV81: 10.441039 | AW81: 10.57021 | AX81: 10.69546 | AY81: 10.816612 | AZ81: 10.933493 | BA81: 11.045934 | BB81: 11.153771 | BC81: 11.256846 | BD81: 11.355005 | BE81: 11.448104 | BF81: 11.536002 | BG81: 11.618566 | BH81: 11.695672 | BI81: 11.767202 | BJ81: 11.833044 | BK81: 11.893099 | BL81: 11.947273 | BM81: 11.99548
H88: 2030 | I88: 2050 | J88: 2070
E89: OSS_INORG | G89: m OSS_INORG | H89: =(Y25-S25)/($Y$1-$S$1) -> -0.0014573397 | I89: =(AS25-Y25)/($AS$1-$Y$1) -> 5.2047846e-05 | J89: =(BM25-AS25)/($BM$1-$AS$1) -> -8.240909e-06
E90: OSS_ORG | G90: b OSS_INORG | H90: =S25-H89*$S$1 -> 2.9920311 | I90: =Y25-I89*$Y$1 -> -0.072025566 | J90: =Y25-J89*$Y$1 -> 0.050360607
G91: m OSS_ORG | H91: =(Y26-S26)/($Y$1-$S$1) -> -0.0013014795 | I91: =(AS26-Y26)/($AS$1-$Y$1) -> 4.6481412e-05 | J91: =(BM26-AS26)/($BM$1-$AS$1) -> -7.359557e-06 | M91: |
G92: B OSS_ORG | H92: =S26-H91*$S$1 -> 2.6778816 | I92: =Y26-I91*$Y$1 -> -0.058479144 | J92: =AS26-J91*$AS$1 -> 0.051894843

Sheet Iniciativas_Lanfill
A2: Tegnologia | B2: nombre | C2: unidad | D2: Fuente | E2: Observación | I2: Nombre | K2: Tegnologia | L2: unidad | M2: 2010 | N2: 2011 | O2: 2012 | P2: 2013 | Q2: 2014 | R2: 2015 | S2: 2016 | T2: 2017 | U2: 2018 | V2: 2019 | W2: 2020 | X2: 2021 | Y2: 2022 | Z2: 2023 | AA2: 2024 | AB2: 2025 | AC2: 2026 | AD2: 2027 | AE2: 2028 | AF2: 2029 | AG2: 2030 | AH2: 2031 | AI2: 2032 | AJ2: 2033 | AK2: 2034 | AL2: 2035
A3: TSW | B3: Producción de residuos sólidos | C3: Mt | D3: Escenario Tendencial modelo | E3: Poblacion y PPC de NDC | I3: Producción de residuos sólidos | K3: TSW | L3: Residuos sólidos (Mt) | M3: 4.0672459 | N3: 4.2162448 | O3: 4.3482153 | P3: 4.9634533 | Q3: 5.6248384 | R3: 5.297211 | S3: 5.0569395 | T3: 5.0416139 | U3: 5.0260414 | V3: 5.0366308 | W3: 5.3048493 | X3: 5.0537886 | Y3: 5.5012364 | Z3: 5.8564772 | AA3: 6.0497179 | AB3: 6.3741422 | AC3: 6.703997 | AD3: 7.03888 | AE3: 7.3787914 | AF3: 7.723731 | AG3: 8.0730955 | AH3: 8.2307822 | AI3: 8.38867 | AJ3: 8.5464572 | AK3: 8.7042445 | AL3: 8.8619312
A4: LANFILL | B4: Emisiones relleno sanitario | C4: % | D4: Escenario Tendencial modelo- OSEMOSYS | E4: Emisiones NDC- INGEI 5taCN | I4: Iniciativa identificada | K4: LANDFILL | L4: MtCO2eq | M4: 0 | N4: 0 | O4: 0 | P4: 0 | Q4: 0 | R4: 0 | S4: 0 | T4: 0 | U4: 0 | V4: 0 | W4: 0 | X4: 0 | Y4: 0 | Z4: 0 | AA4: 0 | AB4: 0.215107 | AC4: 0.398607 | AD4: 0.411107 | AE4: 0.423607 | AF4: 0.221 | AG4: 0.196 | AH4: 0.201 | AI4: 0.206 | AJ4: 0.211 | AK4: 0.216 | AL4: 0.221
A5: LANFILL; LANFILL_ELEC | B5: Potencial de reducción- PROYECTOS | C5: Mt CO2eq | D5: Matriz de iniciativas GCF Readiness Mitigación_Residuos&PI_factibilidad | E5: Sumatoria acumulado del potencial de mitigación al 2035 | I5: Iniciativa identificada | K5: LANDFILL | L5: MtCO2eq | M5: 0 | N5: 0 | O5: 0 | P5: 0 | Q5: 0 | R5: 0 | S5: 0 | T5: 0 | U5: 0 | V5: 0 | W5: 0 | X5: 0 | Y5: 0 | Z5: 0 | AA5: 0 | AB5: =[1]RESIDUOS!P23 -> 0 | AC5: =[1]RESIDUOS!Q23 -> 0 | AD5: =[1]RESIDUOS!R23 -> 0 | AE5: =[1]RESIDUOS!S23 -> 0 | AF5: 0.012857143 | AG5: 0.025714286 | AH5: 0.038571429 | AI5: 0.051428571 | AJ5: 0.064285714 | AK5: 0.077142857 | AL5: 0.09
B6: FE OSEMOSYS LANFILL_ELEC | C6: MtCO2e/Mt de residuos | D6: Escenario Tendencial modelo | E6: NDC- PLAN MICC usan el mismo del BAU | I6: Iniciativa identificada total | K6: LANDFILL+LANDFILL_ELEC | L6: MtCO2eq | M6: =M5+M4 -> 0 | N6: =N5+N4 -> 0 | O6: =O5+O4 -> 0 | P6: =P5+P4 -> 0 | Q6: =Q5+Q4 -> 0 | R6: =R5+R4 -> 0 | S6: =S5+S4 -> 0 | T6: =T5+T4 -> 0 | ... AL6: =AL5+AL4 -> 0.311
B7: % de fases GIRS | C7: % | D7: EscenarioTendencial modelo | E7: Calculado metodologia Plan Micc y adaptado a PAC | I7: Emisiones de Relleno Mt | K7: LANFILL | L7: MtCO2eq | M7: 0.892383 | N7: 1.0328 | O7: 1.17331 | P7: 1.22974 | Q7: 1.28636 | R7: 1.72014 | S7: 2.15416 | T7: 2.43503 | U7: 2.71607 | V7: 2.89799 | W7: 3.07969 | X7: 3.29902 | Y7: 3.4497 | Z7: 3.82725 | AA7: 4.23791 | AB7: 4.68269 | AC7: 5.16312 | AD7: 5.69101 | AE7: 6.25949 | AF7: 6.87044 | AG7: 7.53692 | AH7: 8.05819 | AI7: 8.618 | AJ7: 9.20531 | AK7: 9.83286 | AL7: 10.5021
I8: Emisiones de Relleno netas | K8: LANFILL | L8: MtCO2eq | M8: =M7-M6 -> 0.892383 | N8: =N7-N6 -> 1.0328 | O8: =O7-O6 -> 1.17331 | P8: =P7-P6 -> 1.22974 | Q8: =Q7-Q6 -> 1.28636 | R8: =R7-R6 -> 1.72014 | S8: =S7-S6 -> 2.15416 | T8: =T7-T6 -> 2.43503 | ... AL8: =AL7-AL6 -> 10.1911
I9: FE Osemosys Lanfill | L9: MtCO2e/Mt residuos sólidos | M9: 0.66112218 | N9: 0.7210776 | O9: 0.77651457 | P9: 0.69819944 | Q9: 0.62124942 | R9: 0.79902605 | S9: 1.0153933 | T9: 1.0954289 | U9: 1.2462488 | V9: 1.2360819 | W9: 1.191555 | X9: 1.3112676 | Y9: 1.2056828 | Z9: 1.2357527 | AA9: 1.3246776 | AB9: 1.3891915 | AC9: 1.4563683 | AD9: 1.5288969 | AE9: 1.6041332 | AF9: 1.6820772 | AG9: 1.7653757 | AH9: 1.8513498 | AI9: 1.9426964 | AJ9: 2.0367533 | AK9: 2.1361849 | AL9: 2.2409668
I10: RESIDUOS Relleno netas | K10: LANFILL | L10: Residuos sólidos (Mt) | M10: =M8/M9 -> 1.3498004 | N10: =N8/N9 -> 1.4323008 | O10: =O8/O9 -> 1.5109955 | P10: =P8/P9 -> 1.7613019 | Q10: =Q8/Q9 -> 2.0706015 | R10: =R8/R9 -> 2.1527959 | S10: =S8/S9 -> 2.1215031 | T10: =T8/T9 -> 2.222901 | ... AL10: =AL8/AL9 -> 4.5476354
I11: % Residuos en Relleno netas | K11: LANFILL | L11: Residuos sólidos (Mt) | M11: =M10/M3 -> 0.33187087 | N11: =N10/N3 -> 0.33971006 | O11: =O10/O3 -> 0.34749785 | P11: =P10/P3 -> 0.35485413 | Q11: =Q10/Q3 -> 0.36811751 | R11: =R10/R3 -> 0.40640176 | S11: =S10/S3 -> 0.41952313 | T11: =T10/T3 -> 0.4409106 | ... AL11: =AL10/AL3 -> 0.51316528

Sheet Ini_compost_Reduc
C1: Reducir la producción per cápita | K1: 2010 | L1: 2011 | M1: 2012 | N1: 2013 | O1: 2014 | P1: 2015 | Q1: 2016 | R1: 2017 | S1: 2018 | T1: 2019 | U1: 2020 | V1: 2021 | W1: 2022 | X1: 2023 | Y1: 2024 | Z1: 2025 | AA1: 2026 | AB1: 2027 | AC1: 2028 | AD1: 2029 | AE1: 2030 | AF1: 2031 | AG1: 2032 | AH1: 2033 | AI1: 2034 | AJ1: 2035
G2: Nombre | I2: Tegnologia | J2: unidad
G3: Producción de residuos sólidos MT | I3: TSW | J3: Residuos sólidos (Mt) | K3: 4.0672459 | L3: 4.2162448 | M3: 4.3482153 | N3: 4.9634533 | O3: 5.6248384 | P3: 5.297211 | Q3: 5.0569395 | R3: 5.0416139 | S3: 5.0260414 | T3: 5.0366308 | U3: 5.3048493 | V3: 5.0537886 | W3: 5.5012364 | X3: 5.8564772 | Y3: 6.0497179 | Z3: 6.3741422 | AA3: 6.703997 | AB3: 7.03888 | AC3: 7.3787914 | AD3: 7.723731 | AE3: 8.0730955 | AF3: 8.2307822 | AG3: 8.38867 | AH3: 8.5464572 | AI3: 8.7042445 | AJ3: 8.8619312
G4: Potencial de reduccion | I4: TSW | J4: Mt CO2eq | K4: 0 | L4: 0 | M4: 0 | N4: 0 | O4: 0 | P4: 0 | Q4: 0 | R4: 0 | S4: 0 | T4: 0 | U4: 0 | V4: 0 | W4: 0 | X4: 0 | Y4: 0 | Z4: 0 | AA4: =$B$11+$C$11+$D$11+Z4+$A$11 -> 0.4 | AB4: =$B$11+$C$11+$D$11+AA4+$A$11 -> 0.8 | AC4: =$B$11+$C$11+$D$11+AB4+$A$11 -> 1.2 | AD4: =$B$11+$C$11+$D$11+AC4+$A$11 -> 1.6 | AE4: =$B$11+$C$11+$D$11+AD4+$A$11 -> 2 | AF4: =$B$11+$C$11+$D$11+AE4+$A$11 -> 2.4 | AG4: =$B$11+$C$11+$D$11+AF4+$A$11 -> 2.8 | AH4: =$B$11+$C$11+$D$11+AG4+$A$11 -> 3.2 | ... AJ4: =$B$11+$C$11+$D$11+AI4+$A$11 -> 4
G5: Potencial de reduccion | I5: TSW | J5: Mt CO2eq | K5: =(K4/28)*1000 -> 0 | L5: =(L4/28)*1000 -> 0 | M5: =(M4/28)*1000 -> 0 | N5: =(N4/28)*1000 -> 0 | O5: =(O4/28)*1000 -> 0 | P5: =(P4/28)*1000 -> 0 | Q5: =(Q4/28)*1000 -> 0 | R5: =(R4/28)*1000 -> 0 | ... Z5: =(Z4/28)*1000 -> 0 | AA5: =$B$13+$C$13+$D$13+Z5+$A$13 -> 0.014285714 | AB5: =$B$13+$C$13+$D$13+AA5+$A$13 -> 0.028571429 | AC5: =$B$13+$C$13+$D$13+AB5+$A$13 -> 0.042857143 | AD5: =$B$13+$C$13+$D$13+AC5+$A$13 -> 0.057142857 | AE5: =$B$13+$C$13+$D$13+AD5+$A$13 -> 0.071428571 | AF5: =$B$13+$C$13+$D$13+AE5+$A$13 -> 0.085714286 | AG5: =$B$13+$C$13+$D$13+AF5+$A$13 -> 0.1 | AH5: =$B$13+$C$13+$D$13+AG5+$A$13 -> 0.11428571 | ... AJ5: =$B$13+$C$13+$D$13+AI5+$A$13 -> 0.14285714
G6: Potencial de reduccion en MT de residuos | I6: TSW | J6: Residuos sólidos (Mt) | K6: =(((K5*12)/(16*(1-$B$15)*($B$14*$B$16*$B$17*$B$18))))/1000 -> 0 | L6: =(((L5*12)/(16*(1-$B$15)*($B$14*$B$16*$B$17*$B$18))))/1000 -> 0 | M6: =(((M5*12)/(16*(1-$B$15)*($B$14*$B$16*$B$17*$B$18))))/1000 -> 0 | N6: =(((N5*12)/(16*(1-$B$15)*($B$14*$B$16*$B$17*$B$18))))/1000 -> 0 | O6: =(((O5*12)/(16*(1-$B$15)*($B$14*$B$16*$B$17*$B$18))))/1000 -> 0 | P6: =(((P5*12)/(16*(1-$B$15)*($B$14*$B$16*$B$17*$B$18))))/1000 -> 0 | Q6: =(((Q5*12)/(16*(1-$B$15)*($B$14*$B$16*$B$17*$B$18))))/1000 -> 0 | R6: =(((R5*12)/(16*(1-$B$15)*($B$14*$B$16*$B$17*$B$18))))/1000 -> 0 | ... AJ6: =(((AJ5*12)/(16*(1-$B$15)*($B$14*$B$16*$B$17*$B$18))))/1000 -> 0.0028571429
G7: Porcentaje de reducción | I7: TSW | J7: Residuos sólidos (Mt) | K7: =ROUND(K3-K6,4) -> 4.0672 | L7: =ROUND(L3-L6,4) -> 4.2162 | M7: =ROUND(M3-M6,4) -> 4.3482 | N7: =ROUND(N3-N6,4) -> 4.9635 | O7: =ROUND(O3-O6,4) -> 5.6248 | P7: =ROUND(P3-P6,4) -> 5.2972 | Q7: =ROUND(Q3-Q6,4) -> 5.0569 | R7: =ROUND(R3-R6,4) -> 5.0416 | ... AJ7: =ROUND(AJ3-AJ6,4) -> 8.8591
G8: Porcentaje de reducción | I8: TSW | J8: % | K8: =ROUND(1-(K7/K3),4) -> 0 | L8: =ROUND(1-(L7/L3),4) -> 0 | M8: =ROUND(1-(M7/M3),4) -> 0 | N8: =ROUND(1-(N7/N3),4) -> 0 | O8: =ROUND(1-(O7/O3),4) -> 0 | P8: =ROUND(1-(P7/P3),4) -> 0 | Q8: =ROUND(1-(Q7/Q3),4) -> 0 | R8: =ROUND(1-(R7/R3),4) -> 0 | ... AJ8: =ROUND(1-(AJ7/AJ3),4) -> 0.0003
B9: Reduc PPC
B10: 4 | C10: Kt CO2 eq
B11: =B10/10 -> 0.4
A12: CH4​evitado
A13: =A11/28 -> 0 | B13: =B11/28 -> 0.014285714 | C13: =C11/28 -> 0 | D13: =D11/28 -> 0 | E13: Gg CH4
A14: Doc | B14: 0.15 | D14: Gg de residuos | E14: =(((C13+B13+D13)*12)/(16*(1-$B$15)*($B$14*$B$16*$B$17*$B$18))) -> 0.28571429
A15: 0x | B15: 0
A16: DOCf | B16: 0.5
A17: MCF | B17: 1
A18: F | B18: 0.5
I19: ndc | K19: 4.0672 | L19: 4.2162 | M19: 4.3482 | N19: 4.9634 | O19: 5.6248 | P19: 5.2972 | Q19: 5.0569 | R19: 5.0416 | S19: 5.0421 | T19: 5.0625 | U19: 5.0826 | V19: 5.2141 | W19: 5.4172 | X19: 5.7307 | Y19: 6.0498 | Z19: 6.3742 | AA19: 6.7037 | AB19: 7.0384 | AC19: 7.3781 | AD19: 7.7229 | AE19: 8.072 | AF19: 8.2296 | AG19: 8.3873 | AH19: 8.545 | AI19: 8.7027 | AJ19: 8.8603
G21: Nombre | I21: Tegnologia | J21: unidad | K21: 2010 | L21: 2011 | M21: 2012 | N21: 2013 | O21: 2014 | P21: 2015 | Q21: 2016 | R21: 2017 | S21: 2018 | T21: 2019 | U21: 2020 | V21: 2021 | W21: 2022 | X21: 2023 | Y21: 2024 | Z21: 2025 | AA21: 2026 | AB21: 2027 | AC21: 2028 | AD21: 2029 | AE21: 2030 | AF21: 2031 | AG21: 2032 | AH21: 2033 | AI21: 2034 | AJ21: 2035
G22: Producción de residuos sólidos MT nuevo incluido reducción | I22: TSW | J22: Residuos sólidos (Mt) | K22: 4.0672459 | L22: 4.2162448 | M22: 4.3482153 | N22: 4.9634533 | O22: 5.6248384 | P22: 5.297211 | Q22: 5.0569395 | R22: 5.0416139 | S22: 5.0260414 | T22: 5.0366308 | U22: 5.3048493 | V22: 5.0537886 | W22: 5.5012364 | X22: 5.8564772 | Y22: 6.0497179 | Z22: 6.3741422 | AA22: 6.703997 | AB22: 7.03888 | AC22: 7.3787914 | AD22: 7.723731 | AE22: 8.0730955 | AF22: 8.2307822 | AG22: 8.38867 | AH22: 8.5464572 | AI22: 8.7042445 | AJ22: 8.8619312
G23: Potencial de reduccion en MT CO2eq | I23: COMPOST | J23: Mt CO2eq | K23: 0 | L23: 0 | M23: 0 | N23: 0 | O23: 0 | P23: 0 | Q23: 0 | R23: 0 | S23: 0 | T23: 0 | U23: 0 | V23: 0 | W23: 0 | X23: 0 | Y23: 0 | Z23: =[1]RESIDUOS!P19+[1]RESIDUOS!P22+[1]RESIDUOS!P27+[1]RESIDUOS!P28+[1]RESIDUOS!P29 -> 0 | AA23: 0.0025578424 | AB23: 0.0051156849 | AC23: 0.0082985274 | AD23: 0.01148137 | AE23: 0.014664212 | AF23: 0.017847055 | AG23: 0.021029897 | AH23: 0.02421274 | AI23: 0.027395582 | AJ23: 0.030578424
G24: Emisiones de Relleno Mt CO2eq | I24: LANFILL | J24: Mt CO2eq | K24: 0.892383 | L24: 1.0328 | M24: 1.17331 | N24: 1.22974 | O24: 1.28636 | P24: 1.72014 | Q24: 2.15416 | R24: 2.43503 | S24: 2.71607 | T24: 2.89799 | U24: 3.07969 | V24: 3.29902 | W24: 3.4497 | X24: 3.82725 | Y24: 4.23791 | Z24: 4.68269 | AA24: 5.16312 | AB24: 5.69101 | AC24: 6.25949 | AD24: 6.87044 | AE24: 7.53692 | AF24: 8.05819 | AG24: 8.618 | AH24: 9.20531 | AI24: 9.83286 | AJ24: 10.5021
G25: Emisiones de Relleno- PotencialCompost Mt CO2eq | I25: LANFILL | J25: Mt CO2eq | K25: =ROUND(K24-K23,4) -> 0.8924 | L25: =ROUND(L24-L23,4) -> 1.0328 | M25: =ROUND(M24-M23,4) -> 1.1733 | N25: =ROUND(N24-N23,4) -> 1.2297 | O25: =ROUND(O24-O23,4) -> 1.2864 | P25: =ROUND(P24-P23,4) -> 1.7201 | Q25: =ROUND(Q24-Q23,4) -> 2.1542 | R25: =ROUND(R24-R23,4) -> 2.435 | ... AJ25: =ROUND(AJ24-AJ23,4) -> 10.4715
G26: FE Osemosys Lanfill | I26: LANFILL | J26: MtCO2e/Mt residuos sólidos | K26: 0.66112218 | L26: 0.7210776 | M26: 0.77651457 | N26: 0.69819944 | O26: 0.62124942 | P26: 0.79902605 | Q26: 1.0153933 | R26: 1.0954289 | S26: 1.2462488 | T26: 1.2360819 | U26: 1.191555 | V26: 1.3112676 | W26: 1.2056828 | X26: 1.2357527 | Y26: 1.3246776 | Z26: 1.3891915 | AA26: 1.4563683 | AB26: 1.5288969 | AC26: 1.6041332 | AD26: 1.6820772 | AE26: 1.7653757 | AF26: 1.8513498 | AG26: 1.9426964 | AH26: 2.0367533 | AI26: 2.1361849 | AJ26: 2.2409668
G27: Cantidad de residuos en Relleno Mt con PotencialCompost Mt CO2eq | I27: LANFILL | J27: Residuos sólidos (Mt) | K27: =ROUND(K25/K26,4) -> 1.3498 | L27: =ROUND(L25/L26,4) -> 1.4323 | M27: =ROUND(M25/M26,4) -> 1.511 | N27: =ROUND(N25/N26,4) -> 1.7612 | O27: =ROUND(O25/O26,4) -> 2.0707 | P27: =ROUND(P25/P26,4) -> 2.1527 | Q27: =ROUND(Q25/Q26,4) -> 2.1215 | R27: =ROUND(R25/R26,4) -> 2.2229 | ... AJ27: =ROUND(AJ25/AJ26,4) -> 4.6728
G28: Cantidad de residuos en Relleno Mt | I28: LANFILL | J28: Residuos sólidos (Mt) | K28: 1.3497832 | L28: 1.432344 | M28: 1.5110233 | N28: 1.7613343 | O28: 2.0705863 | P28: 2.1528172 | Q28: 2.1214653 | R28: 2.2229051 | S28: 2.1794234 | T28: 2.3445331 | U28: 2.584637 | V28: 2.5159494 | W28: 2.8611972 | X28: 3.0970527 | Y28: 3.1992433 | Z28: 3.370807 | AA28: 3.5452425 | AB28: 3.7223371 | AC28: 3.9020908 | AD28: 4.0845036 | AE28: 4.2692563 | AF28: 4.352645 | AG28: 4.4361401 | AH28: 4.5195819 | AI28: 4.6030238 | AJ28: 4.6864125
A29: Tegnologia | B29: nombre | C29: unidad | D29: Fuente | E29: Observación | G29: Diferencia de residuos compostables en relleno (vs base) | I29: LANFILL- COMPOST | J29: Residuos sólidos (Mt) | K29: =K28-K27 -> -1.6808966e-05 | L29: =L28-L27 -> 4.4041547e-05 | M29: =M28-M27 -> 2.3342956e-05 | N29: =N28-N27 -> 0.00013428114 | O29: =O28-O27 -> -0.00011373792 | P29: =P28-P27 -> 0.00011723108 | Q29: =Q28-Q27 -> -3.4692908e-05 | R29: =R28-R27 -> 5.0986362e-06 | ... AJ29: =AJ28-AJ27 -> 0.013612505
A30: TSW | B30: Producción de residuos sólidos | C30: Mt | D30: Escenario Tendencial modelo | E30: Poblacion y PPC de NDC | G30: Cantidad de residuos Compost Mt | I30: COMPOST | J30: Residuos sólidos (Mt) | K30: 0.066423773 | L30: 0.077308115 | M30: 0.088861717 | N30: 0.1171375 | O30: 0.13274619 | P30: 0.12501418 | Q30: 0.11934377 | R30: 0.11898209 | S30: 0.11861458 | T30: 0.11886449 | U30: 0.12519444 | V30: 0.11926941 | W30: 0.19280014 | X30: 0.20600395 | Y30: 0.21280127 | Z30: 0.22421303 | AA30: 0.2358158 | AB30: 0.24759545 | AC30: 0.25955197 | AD30: 0.27168536 | AE30: 0.2839744 | AF30: 0.28952109 | AG30: 0.29507486 | AH30: 0.30062509 | AI30: 0.30617532 | AJ30: 0.31172201
A31: LANFILL | B31: Emisiones relleno sanitario | C31: % | D31: Escenario Tendencial modelo | E31: Emisiones NDC- INGEI2022 | G31: Cantidad de residuos Compost Mt +Diferencia de residuos compostables en relleno (vs base) | I31: COMPOST | J31: Residuos sólidos (Mt) | K31: =ROUND(K30+K29,4) -> 0.0664 | L31: =ROUND(L30+L29,4) -> 0.0774 | M31: =ROUND(M30+M29,4) -> 0.0889 | N31: =ROUND(N30+N29,4) -> 0.1173 | O31: =ROUND(O30+O29,4) -> 0.1326 | P31: =ROUND(P30+P29,4) -> 0.1251 | Q31: =ROUND(Q30+Q29,4) -> 0.1193 | R31: =ROUND(R30+R29,4) -> 0.119 | ... AJ31: =ROUND(AJ30+AJ29,4) -> 0.3253
B32: FE OSEMOSYS LANFILL | C32: MtCO2e/Mt de residuos | D32: Escenario Tendencial modelo | E32: Calculado de las INGEI 2022 del NDC/ Mt de residuos (Datos 2014–2023: Boletines INEC (RESIDUOS). Datos 2010–2013: Censo Ambiental Económico en GAD) | G32: nuevos proyectos | I32: COMPOST | J32: Residuos sólidos (Mt) | K32: 0 | L32: 0 | M32: 0 | N32: 0 | O32: 0 | P32: 0 | Q32: 0 | R32: 0 | S32: 0 | T32: 0 | U32: 0 | V32: 0 | W32: 0 | X32: 0 | Y32: 0 | Z32: 0 | AA32: 0.00959 | AB32: 0.01918 | AC32: 0.02877 | AD32: 0.03836 | AE32: 0.04795 | AF32: 0.05754 | AG32: 0.06713 | AH32: 0.07672 | AI32: 0.08631 | AJ32: 0.0959
A33: COMPOST | B33: Potencial de reducción- PROYECTOS | C33: Mt CO2eq | D33: Matriz de iniciativas GCF Readiness Mitigación_Residuos&PI_factibilidad | E33: Sumatoria acumulado del potencial de mitigación al 2035 | G33: Cantidad de residuos Compost Mt +Diferencia de residuos compostables en relleno (vs base)+ NUEVOS PROYECTOS | I33: COMPOST | J33: Residuos sólidos (Mt) | K33: =ROUND(K31+K32,4) -> 0.0664 | L33: =ROUND(L31+L32,4) -> 0.0774 | M33: =ROUND(M31+M32,4) -> 0.0889 | N33: =ROUND(N31+N32,4) -> 0.1173 | O33: =ROUND(O31+O32,4) -> 0.1326 | P33: =ROUND(P31+P32,4) -> 0.1251 | Q33: =ROUND(Q31+Q32,4) -> 0.1193 | R33: =ROUND(R31+R32,4) -> 0.119 | ... AJ33: =ROUND(AJ31+AJ32,4) -> 0.4212
B34: FE OSEMOSYS COMPOST | C34: MtCO2e/Mt de residuos | D34: Escenario Tendencial modelo | E34: NDC- PLAN MICC usan el mismo | G34: % residuos sólidos COMPOST | I34: COMPOST | J34: % | K34: =ROUND(K33/K22,4) -> 0.0163 | L34: =L33/L22 -> 0.018357568 | M34: =M33/M22 -> 0.02044517 | N34: =N33/N22 -> 0.02363274 | O34: =O33/O22 -> 0.02357401 | P34: =P33/P22 -> 0.023616201 | Q34: =Q33/Q22 -> 0.023591344 | R34: =R33/R22 -> 0.023603553 | S34: =S33/S22 -> 0.0235971 | ... AJ34: =AJ33/AJ22 -> 0.047529144
A35: COMPOST | B35: Cantidad de residuos Compost Mt | C35: Mt | D35: Escenario Tendencial modelo | E35: Calculado Mt de residuos metodologia Plan MICC(Datos 2014–2023: Boletines INEC (RESIDUOS). Datos 2010–2013: Censo Ambiental Económico en GAD) | G35: % BAU | I35: COMPOST | K35: 0.016331389 | L35: 0.018335775 | M35: 0.020436365 | N35: 0.0236 | O35: 0.0236 | P35: 0.0236 | Q35: 0.0236 | R35: 0.0236 | S35: 0.0236 | T35: 0.0236 | U35: 0.0236 | V35: 0.0236 | W35: 0.035046692 | X35: 0.035175404 | Y35: 0.035175404 | Z35: 0.035175404 | AA35: 0.035175404 | AB35: 0.035175404 | AC35: 0.035175404 | AD35: 0.035175404 | AE35: 0.035175404 | AF35: 0.035175404 | AG35: 0.035175404 | AH35: 0.035175404 | AI35: 0.035175404 | AJ35: 0.035175404
K36: =ROUND(K34-K35,4) -> 0 | L36: =ROUND(L34-L35,4) -> 0 | M36: =ROUND(M34-M35,4) -> 0 | N36: =ROUND(N34-N35,4) -> 0 | O36: =ROUND(O34-O35,4) -> 0 | P36: =ROUND(P34-P35,4) -> 0 | Q36: =ROUND(Q34-Q35,4) -> 0 | R36: =ROUND(R34-R35,4) -> 0 | ... AJ36: =ROUND(AJ34-AJ35,4) -> 0.0124
G46: Emisiones compost Mt CO2eq | I46: COMPOST | K46: 0.00105287 | L46: 0.00122547 | M46: 0.00139855 | N46: 0.00424994 | O46: 0.00712132 | P46: 0.0061656 | Q46: 0.00520689 | R46: 0.00584163 | S46: 0.0064719 | T46: 0.00676197 | U46: 0.00704751 | V46: 0.00737464 | W46: 0.00645355 | X46: 0.00681727 | Y46: 0.00720036 | Z46: 0.00758296 | AA46: 0.00798501 | AB46: 0.0083687 | AC46: 0.00879148 | AD46: 0.0091925 | AE46: 0.00961417 | AF46: 0.00980409 | AG46: 0.009978 | AH46: 0.0101678 | AI46: 0.010361 | AK46: 0.0105509
G47: Emisiones compost potencial Mt CO2eq | I47: COMPOST | K47: 0 | L47: 0 | M47: 0 | N47: 0 | O47: 0 | P47: 0 | Q47: 0 | R47: 0 | S47: 0 | T47: 0 | U47: 0 | V47: 0 | W47: 0 | X47: 0 | Y47: 0 | Z47: 0 | AA47: 0.0017430699 | AB47: 0.0017430699 | AC47: 0.0018223004 | AD47: 0.0018223004 | AE47: 0.0018223004 | AF47: 0.0018223004 | AG47: 0.0018223004 | AH47: 0.0018223004 | AI47: 0.0018223004 | AK47: 0.0018223004
G48: Emisiones compost Mt CO2eq nuevas | I48: COMPOST | K48: =K46+K47 -> 0.00105287 | L48: =L46+L47 -> 0.00122547 | M48: =M46+M47 -> 0.00139855 | N48: =N46+N47 -> 0.00424994 | O48: =O46+O47 -> 0.00712132 | P48: =P46+P47 -> 0.0061656 | Q48: =Q46+Q47 -> 0.00520689 | R48: =R46+R47 -> 0.00584163 | ... AI48: =AI46+AI47 -> 0.0121833 | AK48: =AK46+AK47 -> 0.0123732
G49: FE COMPOST OsemoSys | I49: COMPOST | K49: 0.015856522 | L49: 0.015853446 | M49: 0.015731747 | N49: 0.036293246 | O49: 0.053664818 | P49: 0.049324805 | Q49: 0.043645344 | R49: 0.049089321 | S49: 0.054569178 | T49: 0.056871065 | U49: 0.056290038 | V49: 0.061815934 | W49: 0.033472745 | X49: 0.03309354 | Y49: 0.033836264 | Z49: 0.033822299 | AA49: 0.033863506 | AB49: 0.033799288 | AC49: 0.033865472 | AD49: 0.033833255 | AE49: 0.0338527 | AF49: 0.033865581 | AG49: 0.033812267 | AH49: 0.033825021 | AI49: 0.033837313 | AK49: 0.033849551
G50: Mt compost nuevo | I50: COMPOST | K50: =K48/K49 -> 0.066399808 | L50: =L48/L49 -> 0.077299915 | M50: =M48/M49 -> 0.088899856 | N50: =N48/N49 -> 0.11710003 | O50: =O48/O49 -> 0.13269997 | P50: =P48/P49 -> 0.12499999 | Q50: =Q48/Q49 -> 0.11930001 | R50: =R48/R49 -> 0.11900002 | ... AI50: =AI48/AI49 -> 0.3600552 | AK50: =AK48/AK49 -> 0.36553515
G51: nuevos proyectos | I51: COMPOST | K51: 0 | L51: 0 | M51: 0 | N51: 0 | O51: 0 | P51: 0 | Q51: 0 | R51: 0 | S51: 0 | T51: 0 | U51: 0 | V51: 0 | W51: 0 | X51: 0 | Y51: 0 | Z51: 0 | AA51: 0.0959 | AB51: 0.0959 | AC51: 0.0959 | AD51: 0.0959 | AE51: 0.0959 | AF51: 0.0959 | AG51: 0.0959 | AH51: 0.0959 | AI51: 0.0959 | AK51: 0.0959
G52: % COMPOST | I52: COMPOST | K52: =K50/K22 -> 0.016325496 | L52: =L50/L22 -> 0.01833383 | M52: =M50/M22 -> 0.020445136 | N52: =N50/N22 -> 0.02359245 | O52: =O50/O22 -> 0.023591784 | P52: =P50/P22 -> 0.023597321 | Q52: =Q50/Q22 -> 0.023591346 | R52: =R50/R22 -> 0.023603556 | ... AI52: =AI50/AI22 -> 0.041365474 | AK52: =AK50/AJ22 -> 0.041247798
A53: Potencial de reduccion en MT CO2eq | K53: 0.016325496 | L53: 0.01833383 | M53: 0.020445136 | N53: 0.02359245 | O53: 0.023591784 | P53: 0.023597321 | Q53: 0.023591346 | R53: 0.023603556 | S53: 0.023597083 | T53: 0.023607052 | U53: 0.023601038 | V53: 0.02360605 | W53: 0.035046692 | X53: 0.035174734 | Y53: 0.035175209 | Z53: 0.035173363 | AA53: 0.042860414 | AB53: 0.042511508 | AC53: 0.042482886 | AD53: 0.042158791 | AE53: 0.041854049 | AF53: 0.041717917 | AG53: 0.041610368 | AH53: 0.041483282 | AI53: 0.041372442 | AK53: 0.041254622
A54: Mitigación=Emisiones en relleno−Emisiones en compostaje
A55: Emisiones en compostaje para una kt residuos
A56: Por Kt de residuo | B56: =((B66*B60))-B63 -> 0.004 | G56: Gg Ch4
A57: Por Kt de residuo | B57: =((B66*B61))-B63 -> 0.0003 | G57: Gg NO2
A58: Por Kt de residuo | B58: =B56*B64+B57*B65 -> 0.1915 | G58: GgCO2eq
A59: 1kt=1Gg
A60: FE CH4 | B60: =4/1000 -> 0.004 | G60: (Gg de NO2/Gg. de desechos tratados
A61: FE NO2 | B61: =0.3/1000 -> 0.0003 | G61: (Gg de CH4/Gg. de desechos tratados
A63: R | B63: 0
A64: GWP CH4 | B64: 28
A65: GWP NO2 | B65: 265
A66: w | B66: 1 | G66: KT
A68: Emisiones del relleno sanitario
A69: Emisiones en compostaje para un 1 kt.
B70: Gg Ch4/Gg | G70: Gg CO2eq/Gg residuo
A71: Por Ton de residuo | B71: =16*(B72*B74*B73*B76*B75)/12 -> 0.05 | G71: =B71*B64 -> 1.4
A72: w SE APLICA A 1 T | B72: 1
A73: DOCf | B73: 0.5
A74: doc | B74: 0.15
A75: F | B75: 0.5
A76: MCF Relleno optimo | B76: 1
A78: W | B78: =11/(G71-B58) -> 9.1021928 | G78: Gg/año
A79: W2028 | B79: =G84/(G71-B58) -> 9.5159288
A80: Emisiones de compostaje | B80: =(B78*B60*B64)+(B78*B61*B65) -> 1.7430699 | G80: Gg CO2eq
A81: Emisiones de compostaje | B81: =B80/1000 -> 0.0017430699 | G81: Mt CO2eq
A82: Emisiones de compostaje | B82: =(B79*B60*B64)+(B79*B61*B65) -> 1.8223004
A83: Emisiones de compostaje 2028 | B83: =B82/1000 -> 0.0018223004 | G83: Mt CO2eq
A84: 2028 | B84: 0.0115 | G84: =B84*1000 -> 11.5
K88: 2010 | L88: 2011 | M88: 2012 | N88: 2013 | O88: 2014 | P88: 2015 | Q88: 2016 | R88: 2017 | S88: 2018 | T88: 2019 | U88: 2020 | V88: 2021 | W88: 2022 | X88: 2023 | Y88: 2024 | Z88: 2025 | AA88: 2026 | AB88: 2027 | AC88: 2028 | AD88: 2029 | AE88: 2030 | AF88: 2031 | AG88: 2032 | AH88: 2033 | AI88: 2034 | AK88: 2035
G89: Producción de residuos sólidos MT nuevo incluido reducción | I89: TSW | K89: 4.0672459 | L89: 4.2162448 | M89: 4.3482153 | N89: 4.9634533 | O89: 5.6248384 | P89: 5.297211 | Q89: 5.0569395 | R89: 5.0416139 | S89: 5.0260414 | T89: 5.0366308 | U89: 5.3048493 | V89: 5.0537886 | W89: 5.5012364 | X89: 5.8564772 | Y89: 6.0497179 | Z89: 6.3741422 | AA89: 6.7025311 | AB89: 7.0374142 | AC89: 7.3773255 | AD89: 7.7222651 | AE89: 8.0716296 | AF89: 8.2293163 | AG89: 8.3872041 | AH89: 8.5449914 | AI89: 8.7027786 | AK89: 8.8604653

Sheet Iniciativas_residuos
A3: Nro. | B3: Nombre de la Iniciativa | C3: INICIO | D3: ¿Cual es el potencial de mitigación al 2035? [kT CO2eq/ año] | E3: ¿Cual es el potencial de mitigación al 2035? [MT CO2eq/ año] acumulado | F3: tegnologia OsemoSYs
A4: 1 | B4: Captura de biogás y generación eléctrica con gas de relleno | C4: 2026-2029 | D4: 30 | E4: =D4/1000 -> 0.03 | F4: LANDFILL
A5: 2 | B5: Captura activa y quema de biogás | C5: 2026-2035 | D5: 1710 | E5: =D5/1000 -> 1.71 | F5: LANDFILL
A6: 3 | B6: Planta de compostaje municipal | C6: 2026-2035 | D6: 11 | E6: =D6/1000 -> 0.011 | F6: COMPOST
A7: 4 | B7: Compostaje privado o de pequeña escala | C7: 2026-2035 | D7: 6.97 | E7: =D7/1000 -> 0.00697 | F7: COMPOST
A8: 5 | B8: Captura de biogás y generación eléctrica con gas de relleno | C8: 2025-2028 | D8: =215.107*4 -> 860.428 | E8: =D8/1000 -> 0.860428 | F8: LANDFILL | G8: 215 | H8: kt CO2eq
A9: 6 | B9: Compostaje mancomunado | C9: 2028-2035 | D9: 5 | E9: =D9/1000 -> 0.005 | F9: COMPOST
A10: 7 | B10: Complejo ambiental | C10: 2029-2035 | D10: 90 | E10: =D10/1000 -> 0.09 | F10: LANDFILL
A11: 8 | B11: Captura activa y quema de biogás | C11: 2026-2035 | D11: 50 | E11: =D11/1000 -> 0.05 | F11: LANDFILL_ELEC
A12: 9 | B12: Reduccion de PPC | C12: 2026-2035 | D12: 4 | E12: =D12/1000 -> 0.004 | F12: TSW
A13: 10 | B13: Planta de Lombricultura región amazonica | C13: 2026-2035 | D13: 0.02 | E13: =D13/1000 -> 2e-05 | F13: COMPOST
A14: 11 | B14: Planta de compostaje para el mercado | C14: 2026-2035 | D14: 7.5 | E14: =D14/1000 -> 0.0075 | F14: COMPOST
A15: 12 | B15: Tratamiento biológico de residuos orgánicos en instalaciones aeroportuarias | C15: 2026-2035 | D15: 0.1084245 | E15: =D15/1000 -> 0.0001084245 | F15: COMPOST
A16: 13 | B16: Lombricultura | C16: 2028-2035 | D16: 2.45 | E16: =D16/1000 -> 0.00245 | F16: COMPOST

Sheet RecuperacionMetanoRellenos
D1: 2010 | E1: 2011 | F1: 2012 | G1: 2013 | H1: 2014 | I1: 2015 | J1: 2016 | K1: 2017 | L1: 2018 | M1: 2019 | N1: 2020 | O1: 2021 | P1: 2022 | Q1: 2023 | R1: 2024 | S1: 2025 | T1: 2026 | U1: 2027 | V1: 2028 | W1: 2029 | X1: 2030 | Y1: 2031 | Z1: 2032 | AA1: 2033 | AB1: 2034 | AC1: 2035
C3: Recuperacion de metano
C4: Escenario | D4: Reducción de emisiones por recuperación de emisiones [MtCO2eq]
C5: PAC
C6: Biogas para electricidad 2 | D6: 0 | E6: 0 | F6: 0 | G6: 0 | H6: 0 | I6: 0 | J6: 0 | K6: 0 | L6: 0 | M6: 0 | N6: 0 | O6: 0.006 | P6: 0.012 | Q6: 0.018 | R6: 0.024 | S6: =[1]RESIDUOS!P17 -> 0 | T6: =[1]RESIDUOS!Q17 -> 0.0075 | U6: =[1]RESIDUOS!R17 -> 0.015 | V6: =[1]RESIDUOS!S17 -> 0.0225 | W6: =[1]RESIDUOS!T17 -> 0.03 | X6: =[1]RESIDUOS!U17 -> 0 | Y6: =[1]RESIDUOS!V17 -> 0 | Z6: =[1]RESIDUOS!W17 -> 0 | ... AC6: =[1]RESIDUOS!Z17 -> 0
C7: Biogas para electricidad 2 | D7: 0 | E7: 0 | F7: 0 | G7: 0 | H7: 0 | I7: 0 | J7: 0 | K7: 0 | L7: 0 | M7: 0.215107 | N7: 0.215107 | O7: 0.215107 | P7: 0.215107 | Q7: 0.215107 | R7: 0.215107 | S7: 0.215107 | T7: 0.215107 | U7: 0.215107 | V7: 0.215107 | W7: 0 | X7: 0 | Y7: 0 | Z7: 0 | AA7: 0 | AB7: 0 | AC7: 0
C8: Complejo Ambiental | D8: 0 | E8: 0 | F8: 0 | G8: 0 | H8: 0 | I8: 0 | J8: 0 | K8: 0 | L8: 0 | M8: 0 | N8: 0 | O8: 0 | P8: 0 | Q8: 0 | R8: 0 | S8: =[1]RESIDUOS!P23 -> 0 | T8: =[1]RESIDUOS!Q23 -> 0 | U8: =[1]RESIDUOS!R23 -> 0 | V8: =[1]RESIDUOS!S23 -> 0 | W8: =[1]RESIDUOS!T23 -> 0.012857143 | X8: =[1]RESIDUOS!U23 -> 0.025714286 | Y8: =[1]RESIDUOS!V23 -> 0.038571429 | Z8: =[1]RESIDUOS!W23 -> 0.051428571 | ... AC8: =[1]RESIDUOS!Z23 -> 0.09
C9: Captura y Quema de Biogás 1 | D9: 0 | E9: 0 | F9: 0 | G9: 0 | H9: 0 | I9: 0 | J9: 0 | K9: 0 | L9: 0 | M9: 0 | N9: 0 | O9: 0 | P9: 0 | Q9: 0 | R9: 0 | S9: =[1]RESIDUOS!P18 -> 0 | T9: =[1]RESIDUOS!Q18 -> 0.171 | U9: =[1]RESIDUOS!R18 -> 0.171 | V9: =[1]RESIDUOS!S18 -> 0.171 | W9: =[1]RESIDUOS!T18 -> 0.171 | X9: =[1]RESIDUOS!U18 -> 0.171 | Y9: =[1]RESIDUOS!V18 -> 0.171 | Z9: =[1]RESIDUOS!W18 -> 0.171 | ... AC9: =[1]RESIDUOS!Z18 -> 0.171
C10: Captura y Quema de Biogás 2 | D10: 0 | E10: 0 | F10: 0 | G10: 0 | H10: 0 | I10: 0 | J10: 0 | K10: 0 | L10: 0 | M10: 0 | N10: 0 | O10: 0 | P10: 0 | Q10: 0 | R10: 0 | S10: =[1]RESIDUOS!P24 -> 0 | T10: =[1]RESIDUOS!Q24 -> 0.005 | U10: =[1]RESIDUOS!R24 -> 0.01 | V10: =[1]RESIDUOS!S24 -> 0.015 | W10: =[1]RESIDUOS!T24 -> 0.02 | X10: =[1]RESIDUOS!U24 -> 0.025 | Y10: =[1]RESIDUOS!V24 -> 0.03 | Z10: =[1]RESIDUOS!W24 -> 0.035 | ... AC10: =[1]RESIDUOS!Z24 -> 0.05
D11: =SUM(D6:D10) -> 0 | E11: =SUM(E6:E10) -> 0 | F11: =SUM(F6:F10) -> 0 | G11: =SUM(G6:G10) -> 0 | H11: =SUM(H6:H10) -> 0 | I11: =SUM(I6:I10) -> 0 | J11: =SUM(J6:J10) -> 0 | K11: =SUM(K6:K10) -> 0 | ... AC11: =SUM(AC6:AC10) -> 0.311

Sheet ProduccionAguasResiduales
C1: Ecuador | D1: 2010 | E1: 2011 | F1: 2012 | G1: 2013 | H1: 2014 | I1: 2015 | J1: 2016 | K1: 2017 | L1: 2018 | M1: 2019 | N1: 2020 | O1: 2021 | P1: 2022 | Q1: 2023 | R1: 2024 | S1: 2025 | T1: 2026 | U1: 2027 | V1: 2028 | W1: 2029 | X1: 2030 | Y1: 2031 | Z1: 2032 | AA1: 2033 | AB1: 2034 | AC1: 2035
C4: RESIDUOS LÍQUIDOS
C5: TENDENCIAL NACIONAL
C6: Población | D6: 14883661 | E6: 15160587 | F6: 15440550 | G6: 15717514 | H6: 15994366 | I6: 16269171 | J6: 16532265 | K6: 16792803 | L6: 17023408 | M6: 17267986 | N6: 17510643 | O6: 17751277 | P6: 17989912 | Q6: 18226512 | R6: 18460936 | S6: 18693140 | T6: 18922864 | U6: 19150021 | V6: 19374448 | W6: 19596113 | X6: 19814767 | Y6: 20030293 | Z6: 20242540 | AA6: 20451333 | AB6: 20656586 | AC6: 20858149
C8: Producción de aguas residuales-PLAN MICC | D8: 3.2042 | E8: 3.7105 | F8: 4.2169 | G8: 4.5908 | H8: 4.9647 | I8: 5.1418 | J8: 5.3186 | K8: 5.3311 | L8: 4.0447617 | M8: 4.0075542 | N8: 4.0575662 | O8: 4.1197164 | P8: 4.4630366 | Q8: 4.8134584 | R8: 5.1708445 | S8: 5.1532093 | T8: 5.3459067 | U8: 6.2833728 | V8: 6.6671083 | W8: 7.0570333 | X8: 7.4529215 | Y8: 7.8545824 | Z8: 8.2618042 | AA8: 8.6743553 | AB8: 9.0920319 | AC8: 9.5145957
C12: Producción per cápita PPC [m3/año]
C13: BAU | D13: =(D8*1000000000)/D6 -> 215.28305 | E13: =(E8*1000000000)/E6 -> 244.74646 | F13: =(F8*1000000000)/F6 -> 273.10556 | G13: =(G8*1000000000)/G6 -> 292.08181 | H13: =(H8*1000000000)/H6 -> 310.40305 | I13: =(I8*1000000000)/I6 -> 316.04561 | J13: =(J8*1000000000)/J6 -> 321.7103 | K13: =(K8*1000000000)/K6 -> 317.46338 | ... AC13: =(AC8*1000000000)/AC6 -> 456.15724
C15: Producción de aguas residuales [miles de millones de m3] | D15: 3.2042 | E15: 3.7105 | F15: 4.2169 | G15: 4.5908 | H15: 4.9647 | I15: 5.1418 | J15: 5.3186 | K15: 5.3311 | L15: 4.0447617 | M15: 4.0075542 | N15: 4.0575662 | O15: 4.1197164 | P15: 4.4630366 | Q15: 4.8134584 | R15: 5.1708445 | S15: 5.1532093 | T15: 5.3459067 | U15: 6.2833728 | V15: 6.6671083 | W15: 7.0570333 | X15: 7.4529215 | Y15: 7.8545824 | Z15: 8.2618042 | AA15: 8.6743553 | AB15: 9.0920319 | AC15: 9.5145957

Sheet ParticipacionTechsAguasTN
D1: Ecuador | E1: 2010 | F1: 2011 | G1: 2012 | H1: 2013 | I1: 2014 | J1: 2015 | K1: 2016 | L1: 2017 | M1: 2018 | N1: 2019 | O1: 2020 | P1: 2021 | Q1: 2022 | R1: 2023 | S1: 2024 | T1: 2025 | U1: 2026 | V1: 2027 | W1: 2028 | X1: 2029 | Y1: 2030 | Z1: 2031 | AA1: 2032 | AB1: 2033 | AC1: 2034 | AD1: 2035
D4: Aguas residuales (PORCENTAJES)
C6: Códigos OSeMOSYS | D6: Escenario BAU
D8: Distribución de las aguas residuales
D9: % Residuos sin tratamiento | E9: 0.6565534 | F9: 0.69742451 | G9: 0.69980012 | H9: 0.7012527 | I9: 0.70027943 | J9: 0.69450317 | K9: 0.69551616 | L9: 0.75829876 | M9: 0.715625 | N9: 0.77178423 | O9: 0.76859504 | P9: 0.7696281 | Q9: 0.72970195 | R9: 0.74717369 | S9: 0.74717369 | T9: 0.74717369 | U9: 0.74717369 | V9: 0.74717369 | W9: 0.74717369 | X9: 0.74717369 | Y9: 0.74717369 | Z9: 0.74717369 | AA9: 0.74717369 | AB9: 0.74717369 | AC9: 0.74717369 | AD9: 0.74717369
D10: % Alcantarillado | E10: 0.3434466 | F10: 0.30257549 | G10: 0.30019988 | H10: 0.2987473 | I10: 0.29972057 | J10: 0.30549683 | K10: 0.30448384 | L10: 0.24170124 | M10: 0.284375 | N10: 0.22821577 | O10: 0.23140496 | P10: 0.2303719 | Q10: 0.27029805 | R10: 0.25282631 | S10: 0.25282631 | T10: 0.25282631 | U10: 0.25282631 | V10: 0.25282631 | W10: 0.25282631 | X10: 0.25282631 | Y10: 0.25282631 | Z10: 0.25282631 | AA10: 0.25282631 | AB10: 0.25282631 | AC10: 0.25282631 | AD10: 0.25282631
D11: % Tanques sépticos/ tratamiento descentralizado | E11: 0 | F11: 0 | G11: 0 | H11: 0 | I11: 0 | J11: 0 | K11: 0 | L11: 0 | M11: 0 | N11: 0 | O11: 0 | P11: 0 | Q11: =P11 -> 0 | R11: =Q11 -> 0 | S11: =R11 -> 0 | T11: =S11 -> 0 | U11: =T11 -> 0 | V11: =U11 -> 0 | W11: =V11 -> 0 | X11: =W11 -> 0 | ... AD11: =AC11 -> 0
C12: STWW | D12: % Total | E12: =SUM(E9:E11) -> 1 | F12: =SUM(F9:F11) -> 1 | G12: =SUM(G9:G11) -> 1 | H12: =SUM(H9:H11) -> 1 | I12: =SUM(I9:I11) -> 1 | J12: =SUM(J9:J11) -> 1 | K12: =SUM(K9:K11) -> 1 | L12: =SUM(L9:L11) -> 1 | ... AD12: =SUM(AD9:AD11) -> 1
D14: Distribución de las aguas residuales que van al alcantarillado
D15: % Con tratamiento (ESTO ES CON RESPECTO A LO QUE VA A ACANTARILLADO) | E15: 0.3434466 | F15: 0.30257549 | G15: 0.30019988 | H15: 0.2987473 | I15: 0.29972057 | J15: 0.30549683 | K15: 0.30448384 | L15: 0.24170124 | M15: 0.284375 | N15: 0.22821577 | O15: 0.23140496 | P15: 0.2303719 | Q15: 0.27029805 | R15: 0.25282631 | S15: 0.25282631 | T15: 0.25282631 | U15: 0.25282631 | V15: 0.25282631 | W15: 0.25282631 | X15: 0.25282631 | Y15: 0.25282631 | Z15: 0.25282631 | AA15: 0.25282631 | AB15: 0.25282631 | AC15: 0.25282631 | AD15: 0.25282631
D16: % Sin tratamiento (ESTO ES CON RESPECTO A LO QUE VA A ACANTARILLADO) | E16: 0.6565534 | F16: 0.69742451 | G16: 0.69980012 | H16: 0.7012527 | I16: 0.70027943 | J16: 0.69450317 | K16: 0.69551616 | L16: 0.75829876 | M16: 0.715625 | N16: 0.77178423 | O16: 0.76859504 | P16: 0.7696281 | Q16: 0.72970195 | R16: 0.74717369 | S16: 0.74717369 | T16: 0.74717369 | U16: 0.74717369 | V16: 0.74717369 | W16: 0.74717369 | X16: 0.74717369 | Y16: 0.74717369 | Z16: 0.74717369 | AA16: 0.74717369 | AB16: 0.74717369 | AC16: 0.74717369 | AD16: 0.74717369
E17: =SUM(E15:E16) -> 1 | F17: =SUM(F15:F16) -> 1 | G17: =SUM(G15:G16) -> 1 | H17: =SUM(H15:H16) -> 1 | I17: =SUM(I15:I16) -> 1 | J17: =SUM(J15:J16) -> 1 | K17: =SUM(K15:K16) -> 1 | L17: =SUM(L15:L16) -> 1 | ... AD17: =SUM(AD15:AD16) -> 1
D18: Distribución de las aguas residuales que van al alcantarillado
D19: % Con tratamiento (ESTO ES CON RESPECTO AL TOTAL DE AGUAS RESIDUALES) | E19: =E10*E15 -> 0.11795557 | F19: =F10*F15 -> 0.09155193 | G19: =G10*G15 -> 0.090119966 | H19: =H10*H15 -> 0.089249951 | I19: =I10*I15 -> 0.089832422 | J19: =J10*J15 -> 0.093328312 | K19: =K10*K15 -> 0.092710407 | L19: =L10*L15 -> 0.058419492 | ... AD19: =AD10*AD15 -> 0.063921143
C20: WWWT;SEWERWWWT;SEWERWW | D20: % Sin tratamiento (ESTO ES CON RESPECTO AL TOTAL DE AGUAS RESIDUALES) | E20: =E16*E10 -> 0.22549103 | F20: =F16*F10 -> 0.21102356 | G20: =G16*G10 -> 0.21007991 | H20: =H16*H10 -> 0.20949735 | I20: =I16*I10 -> 0.20988815 | J20: =J16*J10 -> 0.21216852 | K20: =K16*K10 -> 0.21177343 | L20: =L16*L10 -> 0.18328175 | ... AD20: =AD16*AD10 -> 0.18890517
D21: Total | E21: =E19+E20 -> 0.3434466 | F21: =F19+F20 -> 0.30257549 | G21: =G19+G20 -> 0.30019988 | H21: =H19+H20 -> 0.2987473 | I21: =I19+I20 -> 0.29972057 | J21: =J19+J20 -> 0.30549683 | K21: =K19+K20 -> 0.30448384 | L21: =L19+L20 -> 0.24170124 | ... AD21: =AD19+AD20 -> 0.25282631
C22: WWWOT;TWWWOT | D22: % de aguas residuales sin tratamiento y sin alcantarillado | E22: =E9+E20 -> 0.88204443 | F22: =F9+F20 -> 0.90844807 | G22: =G9+G20 -> 0.90988003 | H22: =H9+H20 -> 0.91075005 | I22: =I9+I20 -> 0.91016758 | J22: =J9+J20 -> 0.90667169 | K22: =K9+K20 -> 0.90728959 | L22: =L9+L20 -> 0.94158051 | ... AD22: =AD9+AD20 -> 0.93607886
D27: Aguas residuales [miles millones de m3]
C29: Códigos OSeMOSYS | D29: Escenario BAU
D31: Distribución de las aguas residuales
D32: Residuos sin tratamiento | E32: =E9*E47 -> 2.1037284 | F32: =F9*F47 -> 2.5877936 | G32: =G9*G47 -> 2.9509871 | H32: =H9*H47 -> 3.2193109 | I32: =I9*I47 -> 3.4766773 | J32: =J9*J47 -> 3.5709964 | K32: =K9*K47 -> 3.6991723 | L32: =L9*L47 -> 4.0425665 | ... X32: =X9*X47 -> 5.2728296 | Y32: =Y10*Y47 -> 1.8842946 | Z32: =Z9*Z47 -> 5.8687373 | AA32: =AA9*AA47 -> 6.1730028 | AB32: =AB9*AB47 -> 6.4812501 | AC32: =AC9*AC47 -> 6.7933271 | AD32: =AD9*AD47 -> 7.1090556
D33: Alcantarillado | E33: =E47*E10 -> 1.1004716 | F33: =F47*F10 -> 1.1227064 | G33: =G47*G10 -> 1.2659129 | H33: =H47*H10 -> 1.3714891 | I33: =I47*I10 -> 1.4880227 | J33: =J47*J10 -> 1.5708036 | K33: =K47*K10 -> 1.6194277 | L33: =L47*L10 -> 1.2885335 | ... AD33: =AD47*AD10 -> 2.4055401
C34: STWW | D34: Tanques sépticos/ tratamiento descentralizado | E34: =E11*E47 -> 0 | F34: =F11*F47 -> 0 | G34: =G11*G47 -> 0 | H34: =H11*H47 -> 0 | I34: =I11*I47 -> 0 | J34: =J11*J47 -> 0 | K34: =K11*K47 -> 0 | L34: =L11*L47 -> 0 | ... AD34: =AD11*AD47 -> 0
D35: Total | E35: =SUM(E32:E34) -> 3.2042 | F35: =SUM(F32:F34) -> 3.7105 | G35: =SUM(G32:G34) -> 4.2169 | H35: =SUM(H32:H34) -> 4.5908 | I35: =SUM(I32:I34) -> 4.9647 | J35: =SUM(J32:J34) -> 5.1418 | K35: =SUM(K32:K34) -> 5.3186 | L35: =SUM(L32:L34) -> 5.3311 | ... AD35: =SUM(AD32:AD34) -> 9.5145957
D37: Distribución de las aguas residuales que van al alcantarillado
D38: Con tratamiento (ESTO ES CON RESPECTO A LO QUE VA A ACANTARILLADO) | E38: =E15*E47 -> 1.1004716 | F38: =F15*F47 -> 1.1227064 | G38: =G15*G47 -> 1.2659129 | H38: =H15*H47 -> 1.3714891 | I38: =I15*I47 -> 1.4880227 | J38: =J15*J47 -> 1.5708036 | K38: =K15*K47 -> 1.6194277 | L38: =L15*L47 -> 1.2885335 | ... AD38: =AD15*AD47 -> 2.4055401
D39: Sin tratamiento (ESTO ES CON RESPECTO A LO QUE VA A ACANTARILLADO) | E39: =E16*E47 -> 2.1037284 | F39: =F16*F47 -> 2.5877936 | G39: =G16*G47 -> 2.9509871 | H39: =H16*H47 -> 3.2193109 | I39: =I16*I47 -> 3.4766773 | J39: =J16*J47 -> 3.5709964 | K39: =K16*K47 -> 3.6991723 | L39: =L16*L47 -> 4.0425665 | ... AD39: =AD16*AD47 -> 7.1090556
E40: =SUM(E38:E39) -> 3.2042 | F40: =SUM(F38:F39) -> 3.7105 | G40: =SUM(G38:G39) -> 4.2169 | H40: =SUM(H38:H39) -> 4.5908 | I40: =SUM(I38:I39) -> 4.9647 | J40: =SUM(J38:J39) -> 5.1418 | K40: =SUM(K38:K39) -> 5.3186 | L40: =SUM(L38:L39) -> 5.3311 | ... AD40: =SUM(AD38:AD39) -> 9.5145957
D41: Distribución de las aguas residuales que van al alcantarillado
C42: WWWT;SEWERWWWT;SEWERWW | D42: Con tratamiento (ESTO ES CON RESPECTO AL TOTAL DE AGUAS RESIDUALES) | E42: =E19*E47 -> 0.37795323 | F42: =F19*F47 -> 0.33970344 | G42: =G19*G47 -> 0.38002688 | H42: =H19*H47 -> 0.40972867 | I42: =I19*I47 -> 0.44599103 | J42: =J19*J47 -> 0.47987552 | K42: =K19*K47 -> 0.49308957 | L42: =L19*L47 -> 0.31144015 | ... AD42: =AD19*AD47 -> 0.60818383
D43: Sin tratamiento (ESTO ES CON RESPECTO AL TOTAL DE AGUAS RESIDUALES) | E43: =E20*E47 -> 0.72251837 | F43: =F20*F47 -> 0.78300294 | G43: =G20*G47 -> 0.88588598 | H43: =H20*H47 -> 0.96176044 | I43: =I20*I47 -> 1.0420317 | J43: =J20*J47 -> 1.0909281 | K43: =K20*K47 -> 1.1263382 | L43: =L20*L47 -> 0.97709335 | ... AD43: =AD20*AD47 -> 1.7973563
D44: Total | E44: =E21*E47 -> 1.1004716 | F44: =F21*F47 -> 1.1227064 | G44: =G21*G47 -> 1.2659129 | H44: =H21*H47 -> 1.3714891 | I44: =I21*I47 -> 1.4880227 | J44: =J21*J47 -> 1.5708036 | K44: =K21*K47 -> 1.6194277 | L44: =L21*L47 -> 1.2885335 | ... AD44: =AD21*AD47 -> 2.4055401
C45: WWWOT;TWWWOT | E45: =E22*E47 -> 2.8262468 | F45: =F22*F47 -> 3.3707966 | G45: =G22*G47 -> 3.8368731 | H45: =H22*H47 -> 4.1810713 | I45: =I22*I47 -> 4.518709 | J45: =J22*J47 -> 4.6619245 | K45: =K22*K47 -> 4.8255104 | L45: =L22*L47 -> 5.0196598 | ... AD45: =AD22*AD47 -> 8.9064119
C47: TSW | D47: Producción de aguas residuales | E47: 3.2042 | F47: 3.7105 | G47: 4.2169 | H47: 4.5908 | I47: 4.9647 | J47: 5.1418 | K47: 5.3186 | L47: 5.3311 | M47: 4.0447617 | N47: 4.0075542 | O47: 4.0575662 | P47: 4.1197164 | Q47: 4.4630366 | R47: 4.8134584 | S47: 5.1708445 | T47: 5.1532093 | U47: 5.3459067 | V47: 6.2833728 | W47: 6.6671083 | X47: 7.0570333 | Y47: 7.4529215 | Z47: 7.8545824 | AA47: 8.2618042 | AB47: 8.6743553 | AC47: 9.0920319 | AD47: 9.5145957
G50: TWWWOT | I50: SEWERWWWT + STW | J50: SEWERWW | M50: STWW
D51: Fuente | E51: año | F51: millones de m3 | G51: %agua residual no tratada | H51: %sin alcantarillado | I51: %agua residual tratada | J51: % Alcantarillado | K51: %Aguas residuales tratadas que van alcantarilla | L51: % sin tratamiento va alcantarillado | M51: % tratadas va sin alcantarillado | N51: % no tratadas sin alcantarillado | O51: % Tanques sépticos/ tratamiento descentralizado | P51: % agua tratada a alcantarillado Normalizado | Q51: % agua no tratada a alcantarillado normalizado
D52: Reporte de la Gestión, Gasto e Inversión en Protección Ambiental de los Municipios y Consejos Provinciales 2010 | E52: 2010 | F52: 3.2042 | G52: 0.589 | H52: 0.18 | I52: 0.411 | J52: 0.824 | K52: 0.283 | L52: =J52-K52 -> 0.541 | M52: =I52-K52 -> 0.128 | N52: =L69/G69 -> 0.459 | O52: 0 | P52: =K52/J52 -> 0.3434466 | Q52: =L52/J52 -> 0.6565534
D53: Reporte de la Gestión, Gasto e Inversión en Protección Ambiental de los Municipios y Consejos Provinciales 2011 | E53: 2011 | F53: 3.7105 | G53: 0.521 | H53: 0.058244444 | I53: 0.479 | J53: 0.94175556 | K53: 0.28495215 | L53: =J53-K53 -> 0.6568034 | M53: =I53-K53 -> 0.19404785 | N53: =L70/G70 -> 0.3431966 | O53: 0 | P53: =K53/J53 -> 0.30257549 | Q53: =L53/J53 -> 0.69742451
D54: Reporte de la Gestión, Gasto e Inversión en Protección Ambiental de los Municipios y Consejos Provinciales 2012 | E54: 2012 | F54: 4.2169 | G54: 0.502 | H54: 0.055477778 | I54: 0.498 | J54: 0.94452222 | K54: 0.28354545 | L54: =J54-K54 -> 0.66097677 | M54: =I54-K54 -> 0.21445455 | N54: =L71/G71 -> 0.33902323 | O54: 0 | P54: =K54/J54 -> 0.30019988 | Q54: =L54/J54 -> 0.69980012
D55: Reporte de la Gestión, Gasto e Inversión en Protección Ambiental de los Municipios y Consejos Provinciales 2014 | E55: 2013 | F55: 4.5908 | G55: 0.502 | H55: 0.052711111 | I55: 0.498 | J55: 0.94728889 | K55: 0.283 | L55: =J55-K55 -> 0.66428889 | M55: =I55-K55 -> 0.215 | N55: =L72/G72 -> 0.33571111 | O55: 0 | P55: =K55/J55 -> 0.2987473 | Q55: =L55/J55 -> 0.7012527
D56: Reporte de la Gestión, Gasto e Inversión en Protección Ambiental de los Municipios y Consejos Provinciales 2014 | E56: 2014 | F56: 4.9647 | G56: 0.441 | H56: 0.049944444 | I56: =I55+(((2014-2013)*(I57-I55))/(2015-2013)) -> 0.559 | J56: 0.95005556 | K56: 0.2847512 | L56: =J56-K56 -> 0.66530436 | M56: =I56-K56 -> 0.2742488 | N56: =L73/G73 -> 0.33469564 | O56: 0 | P56: =K56/J56 -> 0.29972057 | Q56: =L56/J56 -> 0.70027943
D57: Información Ambiental Económica en Gobiernos Autónomos Descentraliza 2015 | E57: 2015 | F57: 5.1418 | G57: 0.38 | H57: 0.054 | I57: 0.62 | J57: 0.946 | K57: 0.289 | L57: =J57-K57 -> 0.657 | M57: =I57-K57 -> 0.331 | N57: =L74/G74 -> 0.343 | O57: 0 | P57: =K57/J57 -> 0.30549683 | Q57: =L57/J57 -> 0.69450317
D58: Información Ambiental Económica en Gobiernos Autónomos Descentraliza 2016 | E58: 2016 | F58: 5.3186 | G58: 0.367 | H58: 0.041 | I58: 0.633 | J58: 0.959 | K58: 0.292 | L58: =J58-K58 -> 0.667 | M58: =I58-K58 -> 0.341 | N58: =L75/G75 -> 0.333 | O58: 0 | P58: =K58/J58 -> 0.30448384 | Q58: =L58/J58 -> 0.69551616
D59: Información Ambiental Económica en Gobiernos Autónomos Descentraliza 2017 | E59: 2017 | F59: 5.3311 | G59: 0.262 | H59: 0.036 | I59: 0.738 | J59: 0.964 | K59: 0.233 | L59: =J59-K59 -> 0.731 | M59: =I59-K59 -> 0.505 | N59: =L76/G76 -> 0.269 | O59: 0 | P59: =K59/J59 -> 0.24170124 | Q59: =L59/J59 -> 0.75829876
D60: Información Ambiental Económica en Gobiernos Autónomos Descentraliza 2018 | E60: 2018 | F60: 4.0447617 | G60: 0.335 | H60: 0.04 | I60: 0.665 | J60: 0.96 | K60: 0.273 | L60: =J60-K60 -> 0.687 | M60: =I60-K60 -> 0.392 | N60: =L77/G77 -> 0.313 | O60: 0 | P60: =K60/J60 -> 0.284375 | Q60: =L60/J60 -> 0.715625
D61: Información Ambiental Económica en Gobiernos Autónomos Descentraliza 2019 | E61: 2019 | F61: 4.0075542 | G61: 0.299 | H61: 0.036 | I61: 0.701 | J61: 0.964 | K61: 0.22 | L61: =J61-K61 -> 0.744 | M61: =I61-K61 -> 0.481 | N61: =L78/G78 -> 0.256 | O61: 0 | P61: =K61/J61 -> 0.22821577 | Q61: =L61/J61 -> 0.77178423
D62: Información Ambiental Económica en Gobiernos Autónomos Descentraliza 2020 | E62: 2020 | F62: 4.0575662 | G62: 0.262 | H62: 0.032 | I62: 0.738 | J62: 0.968 | K62: 0.224 | L62: =J62-K62 -> 0.744 | M62: =I62-K62 -> 0.514 | N62: =L79/G79 -> 0.256 | O62: 0 | P62: =K62/J62 -> 0.23140496 | Q62: =L62/J62 -> 0.76859504
D63: Información Ambiental Económica en Gobiernos Autónomos Descentraliza 2021 | E63: 2021 | F63: 4.1197164 | G63: 0.258 | H63: 0.032 | I63: 0.742 | J63: 0.968 | K63: 0.223 | L63: =J63-K63 -> 0.745 | M63: =I63-K63 -> 0.519 | N63: =L80/G80 -> 0.255 | O63: 0 | P63: =K63/J63 -> 0.2303719 | Q63: =L63/J63 -> 0.7696281
D64: Información Ambiental Económica en Gobiernos Autónomos Descentraliza 2022 | E64: 2022 | F64: 4.4630366 | G64: 0.247 | H64: 0.027 | I64: 0.753 | J64: 0.973 | K64: 0.263 | L64: =J64-K64 -> 0.71 | M64: =I64-K64 -> 0.49 | N64: =L81/G81 -> 0.29 | O64: 0 | P64: =K64/J64 -> 0.27029805 | Q64: =L64/J64 -> 0.72970195
D65: Información Ambiental Económica en Gobiernos Autónomos Descentraliza 2023 | E65: 2023 | F65: 4.8134584 | G65: 0.256 | H65: 0.027 | I65: 0.744 | J65: 0.973 | K65: 0.246 | L65: =J65-K65 -> 0.727 | M65: =I65-K65 -> 0.498 | N65: =L82/G82 -> 0.273 | O65: 0 | P65: =K65/J65 -> 0.25282631 | Q65: =L65/J65 -> 0.74717369
E68: año | F68: millones de m3 | G68: agua residual no tratada | H68: agua residual tratada | I68: sin tratamiento- alcantarillado | J68: tratadas que van alcantarilla | K68: tratadas va sin alcantarillado | L68: no tratadas sin alcantarillado | M68: agua tratada a alcantarillado Normalizado | N68: agua no tratada a alcantarillado normalizado
E69: 2010 | F69: 3.2042 | G69: =F52*G52 -> 1.8872738 | H69: =F52*I52 -> 1.3169262 | I69: =G69*L52 -> 1.0210151 | J69: =H69*K52 -> 0.37269011 | K69: =H69*M52 -> 0.16856655 | L69: =G69-I69 -> 0.86625867 | M69: =P52*H69 -> 0.45229383 | N69: =G69*Q52 -> 1.239096
E70: 2011 | F70: 3.7105 | G70: =F53*G53 -> 1.9331705 | H70: =F53*I53 -> 1.7773295 | I70: =G70*L53 -> 1.269713 | J70: =H70*K53 -> 0.50645387 | K70: =H70*M53 -> 0.34488696 | L70: =G70-I70 -> 0.66345754 | M70: =P53*H70 -> 0.53777635 | N70: =G70*Q53 -> 1.3482405
E71: 2012 | F71: 4.2169 | G71: =F54*G54 -> 2.1168838 | H71: =F54*I54 -> 2.1000162 | I71: =G71*L54 -> 1.399211 | J71: =H71*K54 -> 0.59545005 | K71: =H71*M54 -> 0.45035802 | L71: =G71-I71 -> 0.71767279 | M71: =P54*H71 -> 0.6304246 | N71: =G71*Q54 -> 1.4813955
E72: 2013 | F72: 4.5908 | G72: =F55*G55 -> 2.3045816 | H72: =F55*I55 -> 2.2862184 | I72: =G72*L55 -> 1.530908 | J72: =H72*K55 -> 0.64699981 | K72: =H72*M55 -> 0.49153696 | L72: =G72-I72 -> 0.77367365 | M72: =P55*H72 -> 0.68300158 | N72: =G72*Q55 -> 1.6160941
E73: 2014 | F73: 4.9647 | G73: =F56*G56 -> 2.1894327 | H73: =F56*I56 -> 2.7752673 | I73: =G73*L56 -> 1.4566391 | J73: =H73*K56 -> 0.79026068 | K73: =H73*M56 -> 0.76111374 | L73: =G73-I73 -> 0.73279358 | M73: =P56*H73 -> 0.83180471 | N73: =G73*Q56 -> 1.5332147
E74: 2015 | F74: 5.1418 | G74: =F57*G57 -> 1.953884 | H74: =F57*I57 -> 3.187916 | I74: =G74*L57 -> 1.2837018 | J74: =H74*K57 -> 0.92130772 | K74: =H74*M57 -> 1.0552002 | L74: =G74-I74 -> 0.67018221 | M74: =P57*H74 -> 0.97389823 | N74: =G74*Q57 -> 1.3569786
E75: 2016 | F75: 5.3186 | G75: =F58*G58 -> 1.9519262 | H75: =F58*I58 -> 3.3666738 | I75: =G75*L58 -> 1.3019348 | J75: =H75*K58 -> 0.98306875 | K75: =H75*M58 -> 1.1480358 | L75: =G75-I75 -> 0.64999142 | M75: =P58*H75 -> 1.0250978 | N75: =G75*Q58 -> 1.3575962
E76: 2017 | F76: 5.3311 | G76: =F59*G59 -> 1.3967482 | H76: =F59*I59 -> 3.9343518 | I76: =G76*L59 -> 1.0210229 | J76: =H76*K59 -> 0.91670397 | K76: =H76*M59 -> 1.9868477 | L76: =G76-I76 -> 0.37572527 | M76: =P59*H76 -> 0.95093773 | N76: =G76*Q59 -> 1.0591524
E77: 2018 | F77: 4.0447617 | G77: =F60*G60 -> 1.3549952 | H77: =F60*I60 -> 2.6897666 | I77: =G77*L60 -> 0.93088169 | J77: =H77*K60 -> 0.73430627 | K77: =H77*M60 -> 1.0543885 | L77: =G77-I77 -> 0.42411349 | M77: =P60*H77 -> 0.76490236 | N77: =G77*Q60 -> 0.96966843
E78: 2019 | F78: 4.0075542 | G78: =F61*G61 -> 1.1982587 | H78: =F61*I61 -> 2.8092955 | I78: =G78*L61 -> 0.89150448 | J78: =H78*K61 -> 0.61804501 | K78: =H78*M61 -> 1.3512711 | L78: =G78-I78 -> 0.30675423 | M78: =P61*H78 -> 0.64112553 | N78: =G78*Q61 -> 0.92479717
E79: 2020 | F79: 4.0575662 | G79: =F62*G62 -> 1.0630823 | H79: =F62*I62 -> 2.9944839 | I79: =G79*L62 -> 0.79093326 | J79: =H79*K62 -> 0.67076438 | K79: =H79*M62 -> 1.5391647 | L79: =G79-I79 -> 0.27214908 | M79: =P62*H79 -> 0.69293841 | N79: =G79*Q62 -> 0.81707982
E80: 2021 | F80: 4.1197164 | G80: =F63*G63 -> 1.0628868 | H80: =F63*I63 -> 3.0568295 | I80: =G80*L63 -> 0.79185068 | J80: =H80*K63 -> 0.68167299 | K80: =H80*M63 -> 1.5864945 | L80: =G80-I80 -> 0.27103614 | M80: =P63*H80 -> 0.70420763 | N80: =G80*Q63 -> 0.81802756
... E82: 2023 | F82: 4.8134584 | G82: =F65*G65 -> 1.2322454 | H82: =F65*I65 -> 3.5812131 | I82: =G82*L65 -> 0.89584237 | J82: =H82*K65 -> 0.88097841 | K82: =H82*M65 -> 1.7834441 | L82: =G82-I82 -> 0.33640298 | M82: =P65*H82 -> 0.90542488 | N82: =G82*Q65 -> 0.92070131

Sheet ParticipacionTechsAguasBAU
D1: Ecuador | E1: 2010 | F1: 2011 | G1: 2012 | H1: 2013 | I1: 2014 | J1: 2015 | K1: 2016 | L1: 2017 | M1: 2018 | N1: 2019 | O1: 2020 | P1: 2021 | Q1: 2022 | R1: 2023 | S1: 2024 | T1: 2025 | U1: 2026 | V1: 2027 | W1: 2028 | X1: 2029 | Y1: 2030 | Z1: 2031 | AA1: 2032 | AB1: 2033 | AC1: 2034 | AD1: 2035 | AE1: 2036 | AF1: 2037 | AG1: 2038 | AH1: 2039 | AI1: 2040 | AJ1: 2041 | AK1: 2042 | AL1: 2043 | AM1: 2044 | AN1: 2045 | AO1: 2046 | AP1: 2047 | AQ1: 2048 | AR1: 2049 | AS1: 2050 | AT1: 2051 | AU1: 2052 | AV1: 2053 | AW1: 2054 | AX1: 2055 | AY1: 2056 | AZ1: 2057 | BA1: 2058 | BB1: 2059 | BC1: 2060 | BD1: 2061 | BE1: 2062 | BF1: 2063 | BG1: 2064 | BH1: 2065 | BI1: 2066 | BJ1: 2067 | BK1: 2068 | BL1: 2069 | BM1: 2070
D4: Aguas residuales (PORCENTAJES)
C6: Códigos OSeMOSYS | D6: Escenario BAU
D8: Distribución de las aguas residuales
C9: TWWWOT | D9: % agua residual sin tratamiento | E9: 0.589 | F9: 0.521 | G9: 0.502 | H9: 0.502 | I9: 0.441 | J9: 0.38 | K9: 0.367 | L9: 0.262 | M9: 0.335 | N9: 0.299 | O9: 0.262 | P9: 0.258 | Q9: 0.247 | R9: 0.256 | S9: 0.256 | T9: 0.256 | U9: 0.256 | V9: 0.256 | W9: 0.256 | X9: 0.256 | Y9: 0.256 | Z9: 0.256 | AA9: 0.256 | AB9: 0.256 | AC9: 0.256 | AD9: 0.256 | AE9: 0.256 | AF9: 0.256 | AG9: 0.256 | AH9: 0.256 | AI9: 0.256 | AJ9: 0.256 | AK9: 0.256 | AL9: 0.256 | AM9: 0.256 | AN9: 0.256 | AO9: 0.256 | AP9: 0.256 | AQ9: 0.256 | AR9: 0.256 | AS9: 0.256 | AT9: 0.256 | AU9: 0.256 | AV9: 0.256 | AW9: 0.256 | AX9: 0.256 | AY9: 0.256 | AZ9: 0.256 | BA9: 0.256 | BB9: 0.256 | BC9: 0.256 | BD9: 0.256 | BE9: 0.256 | BF9: 0.256 | BG9: 0.256 | BH9: 0.256 | BI9: 0.256 | BJ9: 0.256 | BK9: 0.256 | BL9: 0.256 | BM9: 0.256
C10: WWT | D10: % agua residual tratada | E10: 0.411 | F10: 0.479 | G10: 0.498 | H10: 0.498 | I10: =H10+(((2014-2013)*(J10-H10))/(2015-2013)) -> 0.559 | J10: 0.62 | K10: 0.633 | L10: 0.738 | M10: 0.665 | N10: 0.701 | O10: 0.738 | P10: 0.742 | Q10: 0.753 | R10: 0.744 | S10: 0.744 | T10: 0.744 | U10: 0.744 | V10: 0.744 | W10: 0.744 | X10: 0.744 | Y10: 0.744 | Z10: 0.744 | AA10: 0.744 | AB10: 0.744 | AC10: 0.744 | AD10: 0.744 | AE10: 0.744 | AF10: 0.744 | AG10: 0.744 | AH10: 0.744 | AI10: 0.744 | AJ10: 0.744 | AK10: 0.744 | AL10: 0.744 | AM10: 0.744 | AN10: 0.744 | AO10: 0.744 | AP10: 0.744 | AQ10: 0.744 | AR10: 0.744 | AS10: 0.744 | AT10: 0.744 | AU10: 0.744 | AV10: 0.744 | AW10: 0.744 | AX10: 0.744 | AY10: 0.744 | AZ10: 0.744 | BA10: 0.744 | BB10: 0.744 | BC10: 0.744 | BD10: 0.744 | BE10: 0.744 | BF10: 0.744 | BG10: 0.744 | BH10: 0.744 | BI10: 0.744 | BJ10: 0.744 | BK10: 0.744 | BL10: 0.744 | BM10: 0.744
C11: STWW | D11: % Tanques sépticos/ tratamiento descentralizado | E11: 0 | F11: 0 | G11: 0 | H11: 0 | I11: 0 | J11: 0 | K11: 0 | L11: 0 | M11: 0 | N11: 0 | O11: 0 | P11: 0 | Q11: =P11 -> 0 | R11: =Q11 -> 0 | S11: =R11 -> 0 | T11: =S11 -> 0 | U11: =T11 -> 0 | V11: =U11 -> 0 | W11: =V11 -> 0 | X11: =W11 -> 0 | ... BM11: =BL11 -> 0
D12: % Total | E12: =SUM(E9:E11) -> 1 | F12: =SUM(F9:F11) -> 1 | G12: =SUM(G9:G11) -> 1 | H12: =SUM(H9:H11) -> 1 | I12: =SUM(I9:I11) -> 1 | J12: =SUM(J9:J11) -> 1 | K12: =SUM(K9:K11) -> 1 | L12: =SUM(L9:L11) -> 1 | ... BM12: =SUM(BM9:BM11) -> 1
D14: Distribución de las aguas residuales que van al alcantarillado
C15: SEWERWWWT; SEWERWW | D15: % Con tratamiento (ESTO ES CON RESPECTO A LO QUE VA A ACANTARILLADO) | E15: 0.3434466 | F15: 0.30257549 | G15: 0.30019988 | H15: 0.2987473 | I15: 0.29972057 | J15: 0.30549683 | K15: 0.30448384 | L15: 0.24170124 | M15: 0.284375 | N15: 0.22821577 | O15: 0.23140496 | P15: 0.2303719 | Q15: 0.27029805 | R15: 0.25282631 | S15: 0.25282631 | T15: 0.25282631 | U15: 0.25282631 | V15: 0.25282631 | W15: 0.25282631 | X15: 0.25282631 | Y15: 0.25282631 | Z15: 0.25282631 | AA15: 0.25282631 | AB15: 0.25282631 | AC15: 0.25282631 | AD15: 0.25282631 | AE15: 0.25282631 | AF15: 0.25282631 | AG15: 0.25282631 | AH15: 0.25282631 | AI15: 0.25282631 | AJ15: 0.25282631 | AK15: 0.25282631 | AL15: 0.25282631 | AM15: 0.25282631 | AN15: 0.25282631 | AO15: 0.25282631 | AP15: 0.25282631 | AQ15: 0.25282631 | AR15: 0.25282631 | AS15: 0.25282631 | AT15: 0.25282631 | AU15: 0.25282631 | AV15: 0.25282631 | AW15: 0.25282631 | AX15: 0.25282631 | AY15: 0.25282631 | AZ15: 0.25282631 | BA15: 0.25282631 | BB15: 0.25282631 | BC15: 0.25282631 | BD15: 0.25282631 | BE15: 0.25282631 | BF15: 0.25282631 | BG15: 0.25282631 | BH15: 0.25282631 | BI15: 0.25282631 | BJ15: 0.25282631 | BK15: 0.25282631 | BL15: 0.25282631 | BM15: 0.25282631
C16: SEWERWWWOT; SEWERWW | D16: % Sin tratamiento (ESTO ES CON RESPECTO A LO QUE VA A ACANTARILLADO) | E16: 0.6565534 | F16: 0.69742451 | G16: 0.69980012 | H16: 0.7012527 | I16: 0.70027943 | J16: 0.69450317 | K16: 0.69551616 | L16: 0.75829876 | M16: 0.715625 | N16: 0.77178423 | O16: 0.76859504 | P16: 0.7696281 | Q16: 0.72970195 | R16: 0.74717369 | S16: 0.74717369 | T16: 0.74717369 | U16: 0.74717369 | V16: 0.74717369 | W16: 0.74717369 | X16: 0.74717369 | Y16: 0.74717369 | Z16: 0.74717369 | AA16: 0.74717369 | AB16: 0.74717369 | AC16: 0.74717369 | AD16: 0.74717369 | AE16: 0.74717369 | AF16: 0.74717369 | AG16: 0.74717369 | AH16: 0.74717369 | AI16: 0.74717369 | AJ16: 0.74717369 | AK16: 0.74717369 | AL16: 0.74717369 | AM16: 0.74717369 | AN16: 0.74717369 | AO16: 0.74717369 | AP16: 0.74717369 | AQ16: 0.74717369 | AR16: 0.74717369 | AS16: 0.74717369 | AT16: 0.74717369 | AU16: 0.74717369 | AV16: 0.74717369 | AW16: 0.74717369 | AX16: 0.74717369 | AY16: 0.74717369 | AZ16: 0.74717369 | BA16: 0.74717369 | BB16: 0.74717369 | BC16: 0.74717369 | BD16: 0.74717369 | BE16: 0.74717369 | BF16: 0.74717369 | BG16: 0.74717369 | BH16: 0.74717369 | BI16: 0.74717369 | BJ16: 0.74717369 | BK16: 0.74717369 | BL16: 0.74717369 | BM16: 0.74717369
E17: =SUM(E15:E16) -> 1 | F17: =SUM(F15:F16) -> 1 | G17: =SUM(G15:G16) -> 1 | H17: =SUM(H15:H16) -> 1 | I17: =SUM(I15:I16) -> 1 | J17: =SUM(J15:J16) -> 1 | K17: =SUM(K15:K16) -> 1 | L17: =SUM(L15:L16) -> 1 | ... BM17: =SUM(BM15:BM16) -> 1
D18: Distribución de las aguas residuales que van al alcantarillado
C19: WWWT;SEWERWWWT;SEWERWW | D19: % Con tratamiento (ESTO ES CON RESPECTO AL TOTAL DE AGUAS RESIDUALES) | E19: 0.283 | F19: 0.28495215 | G19: 0.28354545 | H19: 0.283 | I19: 0.2847512 | J19: 0.289 | K19: 0.292 | L19: 0.233 | M19: 0.273 | N19: 0.22 | O19: 0.224 | P19: 0.223 | Q19: 0.263 | R19: 0.246 | S19: 0.246 | T19: 0.246 | U19: 0.246 | V19: 0.246 | W19: 0.246 | X19: 0.246 | Y19: 0.246 | Z19: 0.246 | AA19: 0.246 | AB19: 0.246 | AC19: 0.246 | AD19: 0.246 | AE19: 0.246 | AF19: 0.246 | AG19: 0.246 | AH19: 0.246 | AI19: 0.246 | AJ19: 0.246 | AK19: 0.246 | AL19: 0.246 | AM19: 0.246 | AN19: 0.246 | AO19: 0.246 | AP19: 0.246 | AQ19: 0.246 | AR19: 0.246 | AS19: 0.246 | AT19: 0.246 | AU19: 0.246 | AV19: 0.246 | AW19: 0.246 | AX19: 0.246 | AY19: 0.246 | AZ19: 0.246 | BA19: 0.246 | BB19: 0.246 | BC19: 0.246 | BD19: 0.246 | BE19: 0.246 | BF19: 0.246 | BG19: 0.246 | BH19: 0.246 | BI19: 0.246 | BJ19: 0.246 | BK19: 0.246 | BL19: 0.246 | BM19: 0.246
C20: WWOT;SEWERWWWT;SEWERWW | D20: % Sin tratamiento (ESTO ES CON RESPECTO AL TOTAL DE AGUAS RESIDUALES) | E20: 0.541 | F20: 0.6568034 | G20: 0.66097677 | H20: 0.66428889 | I20: 0.66530436 | J20: 0.657 | K20: 0.667 | L20: 0.731 | M20: 0.687 | N20: 0.744 | O20: 0.744 | P20: 0.745 | Q20: 0.71 | R20: 0.727 | S20: 0.727 | T20: 0.727 | U20: 0.727 | V20: 0.727 | W20: 0.727 | X20: 0.727 | Y20: 0.727 | Z20: 0.727 | AA20: 0.727 | AB20: 0.727 | AC20: 0.727 | AD20: 0.727 | AE20: 0.727 | AF20: 0.727 | AG20: 0.727 | AH20: 0.727 | AI20: 0.727 | AJ20: 0.727 | AK20: 0.727 | AL20: 0.727 | AM20: 0.727 | AN20: 0.727 | AO20: 0.727 | AP20: 0.727 | AQ20: 0.727 | AR20: 0.727 | AS20: 0.727 | AT20: 0.727 | AU20: 0.727 | AV20: 0.727 | AW20: 0.727 | AX20: 0.727 | AY20: 0.727 | AZ20: 0.727 | BA20: 0.727 | BB20: 0.727 | BC20: 0.727 | BD20: 0.727 | BE20: 0.727 | BF20: 0.727 | BG20: 0.727 | BH20: 0.727 | BI20: 0.727 | BJ20: 0.727 | BK20: 0.727 | BL20: 0.727 | BM20: 0.727
D21: Total | E21: =E19+E20 -> 0.824 | F21: =F19+F20 -> 0.94175556 | G21: =G19+G20 -> 0.94452222 | H21: =H19+H20 -> 0.94728889 | I21: =I19+I20 -> 0.95005556 | J21: =J19+J20 -> 0.946 | K21: =K19+K20 -> 0.959 | L21: =L19+L20 -> 0.964 | ... BM21: =BM19+BM20 -> 0.973
C23: WWWOT;TWWWOT | D23: % de aguas residuales sin tratamiento y sin alcantarillado | E23: 0.459 | F23: 0.3431966 | G23: 0.33902323 | H23: 0.33571111 | I23: 0.33469564 | J23: 0.343 | K23: 0.333 | L23: 0.269 | M23: 0.313 | N23: 0.256 | O23: 0.256 | P23: 0.255 | Q23: 0.29 | R23: 0.273 | S23: 0.273 | T23: 0.273 | U23: 0.273 | V23: 0.273 | W23: 0.273 | X23: 0.273 | Y23: 0.273 | Z23: 0.273 | AA23: 0.273 | AB23: 0.273 | AC23: 0.273 | AD23: 0.273 | AE23: 0.273 | AF23: 0.273 | AG23: 0.273 | AH23: 0.273 | AI23: 0.273 | AJ23: 0.273 | AK23: 0.273 | AL23: 0.273 | AM23: 0.273 | AN23: 0.273 | AO23: 0.273 | AP23: 0.273 | AQ23: 0.273 | AR23: 0.273 | AS23: 0.273 | AT23: 0.273 | AU23: 0.273 | AV23: 0.273 | AW23: 0.273 | AX23: 0.273 | AY23: 0.273 | AZ23: 0.273 | BA23: 0.273 | BB23: 0.273 | BC23: 0.273 | BD23: 0.273 | BE23: 0.273 | BF23: 0.273 | BG23: 0.273 | BH23: 0.273 | BI23: 0.273 | BJ23: 0.273 | BK23: 0.273 | BL23: 0.273 | BM23: 0.273
D28: Aguas residuales [miles millones de m3]
C30: Códigos OSeMOSYS | D30: Escenario BAU
D32: Distribución de las aguas residuales
C33: TWWWOT | D33: Residuos sin tratamiento | E33: =E9*E48 -> 1.8872738 | F33: =F9*F48 -> 1.9331705 | G33: =G9*G48 -> 2.1168838 | H33: =H9*H48 -> 2.3045816 | I33: =I9*I48 -> 2.1894327 | J33: =J9*J48 -> 1.953884 | K33: =K9*K48 -> 1.9519262 | L33: =L9*L48 -> 1.3967482 | ... X33: =X9*X48 -> 1.8066005 | Y33: =Y10*Y48 -> 5.5449736 | Z33: =Z9*Z48 -> 2.0107731 | AA33: =AA9*AA48 -> 2.1150219 | AB33: =AB9*AB48 -> 2.220635 | AC33: =AC9*AC48 -> 2.3275602 | AD33: =AD9*AD48 -> 2.4357365 | AE33: =AE9*AE48 -> 2.5451079 | AF33: =AF9*AF48 -> 2.6556069 | AG33: =AG9*AG48 -> 2.7671763 | ... BM33: =BM9*BM48 -> 6.4219758
C34: WWT | D34: Agua residual tratada | E34: =E48*E10 -> 1.3169262 | F34: =F48*F10 -> 1.7773295 | G34: =G48*G10 -> 2.1000162 | H34: =H48*H10 -> 2.2862184 | I34: =I48*I10 -> 2.7752673 | J34: =J48*J10 -> 3.187916 | K34: =K48*K10 -> 3.3666738 | L34: =L48*L10 -> 3.9343518 | ... BM34: =BM48*BM10 -> 18.663867
C35: STWW | D35: Tanques sépticos/ tratamiento descentralizado | E35: =E11*E48 -> 0 | F35: =F11*F48 -> 0 | G35: =G11*G48 -> 0 | H35: =H11*H48 -> 0 | I35: =I11*I48 -> 0 | J35: =J11*J48 -> 0 | K35: =K11*K48 -> 0 | L35: =L11*L48 -> 0 | ... BM35: =BM11*BM48 -> 0
D36: Total | E36: =SUM(E33:E35) -> 3.2042 | F36: =SUM(F33:F35) -> 3.7105 | G36: =SUM(G33:G35) -> 4.2169 | H36: =SUM(H33:H35) -> 4.5908 | I36: =SUM(I33:I35) -> 4.9647 | J36: =SUM(J33:J35) -> 5.1418 | K36: =SUM(K33:K35) -> 5.3186 | L36: =SUM(L33:L35) -> 5.3311 | ... BM36: =SUM(BM33:BM35) -> 25.085843
D38: Distribución de las aguas residuales que van al alcantarillado
C39: SEWERWWWT; SEWERWW | D39: Con tratamiento (ESTO ES CON RESPECTO A LO QUE VA A ACANTARILLADO) | E39: =E15*E48 -> 1.1004716 | F39: =F15*F48 -> 1.1227064 | G39: =G15*G48 -> 1.2659129 | H39: =H15*H48 -> 1.3714891 | I39: =I15*I48 -> 1.4880227 | J39: =J15*J48 -> 1.5708036 | K39: =K15*K48 -> 1.6194277 | L39: =L15*L48 -> 1.2885335 | ... BM39: =BM15*BM48 -> 6.3423611
C40: SEWERWWWOT; SEWERWW | D40: Sin tratamiento (ESTO ES CON RESPECTO A LO QUE VA A ACANTARILLADO) | E40: =E16*E48 -> 2.1037284 | F40: =F16*F48 -> 2.5877936 | G40: =G16*G48 -> 2.9509871 | H40: =H16*H48 -> 3.2193109 | I40: =I16*I48 -> 3.4766773 | J40: =J16*J48 -> 3.5709964 | K40: =K16*K48 -> 3.6991723 | L40: =L16*L48 -> 4.0425665 | ... BM40: =BM16*BM48 -> 18.743482
E41: =SUM(E39:E40) -> 3.2042 | F41: =SUM(F39:F40) -> 3.7105 | G41: =SUM(G39:G40) -> 4.2169 | H41: =SUM(H39:H40) -> 4.5908 | I41: =SUM(I39:I40) -> 4.9647 | J41: =SUM(J39:J40) -> 5.1418 | K41: =SUM(K39:K40) -> 5.3186 | L41: =SUM(L39:L40) -> 5.3311 | ... BM41: =SUM(BM39:BM40) -> 25.085843
D42: Distribución de las aguas residuales que van al alcantarillado
C43: WWWT;SEWERWWWT;SEWERWW | D43: Con tratamiento (ESTO ES CON RESPECTO AL TOTAL DE AGUAS RESIDUALES) | E43: =E19*E48 -> 0.9067886 | F43: =F19*F48 -> 1.057315 | G43: =G19*G48 -> 1.1956828 | H43: =H19*H48 -> 1.2991964 | I43: =I19*I48 -> 1.4137043 | J43: =J19*J48 -> 1.4859802 | K43: =K19*K48 -> 1.5530312 | L43: =L19*L48 -> 1.2421463 | ... BM43: =BM19*BM48 -> 6.1711174
C44: WWWOT;TWWWOT, SEWERWWWOT | D44: Sin tratamiento (ESTO ES CON RESPECTO AL TOTAL DE AGUAS RESIDUALES) | E44: =E20*E48 -> 1.7334722 | F44: =F20*F48 -> 2.437069 | G44: =G20*G48 -> 2.7872729 | H44: =H20*H48 -> 3.0496174 | I44: =I20*I48 -> 3.3030366 | J44: =J20*J48 -> 3.3781626 | K44: =K20*K48 -> 3.5475062 | L44: =L20*L48 -> 3.8970341 | ... BM44: =BM20*BM48 -> 18.237408
D45: Total | E45: =E21*E48 -> 2.6402608 | F45: =F21*F48 -> 3.494384 | G45: =G21*G48 -> 3.9829558 | H45: =H21*H48 -> 4.3488138 | I45: =I21*I48 -> 4.7167408 | J45: =J21*J48 -> 4.8641428 | K45: =K21*K48 -> 5.1005374 | L45: =L21*L48 -> 5.1391804 | ... BM45: =BM21*BM48 -> 24.408525
E46: =E23*E48 -> 1.4707278 | F46: =F23*F48 -> 1.273431 | G46: =G23*G48 -> 1.4296271 | H46: =H23*H48 -> 1.5411826 | I46: =I23*I48 -> 1.6616634 | J46: =J23*J48 -> 1.7636374 | K46: =K23*K48 -> 1.7710938 | L46: =L23*L48 -> 1.4340659 | ... BM46: =BM23*BM48 -> 6.8484351
C48: IWW | D48: Producción de aguas residuales | E48: 3.2042 | F48: 3.7105 | G48: 4.2169 | H48: 4.5908 | I48: 4.9647 | J48: 5.1418 | K48: 5.3186 | L48: 5.3311 | M48: 4.0447617 | N48: 4.0075542 | O48: 4.0575662 | P48: 4.1197164 | Q48: 4.4630366 | R48: 4.8134584 | S48: 5.1708445 | T48: 5.1532093 | U48: 5.3459067 | V48: 6.2833728 | W48: 6.6671083 | X48: 7.0570333 | Y48: 7.4529215 | Z48: 7.8545824 | AA48: 8.2618042 | AB48: 8.6743553 | AC48: 9.0920319 | AD48: 9.5145957 | AE48: 9.9418279 | AF48: 10.373465 | AG48: 10.809282 | AH48: 11.249024 | AI48: 11.692443 | AJ48: 12.139325 | AK48: 12.58943 | AL48: 13.04249 | AM48: 13.498279 | AN48: 13.956518 | AO48: 14.416971 | AP48: 14.879436 | AQ48: 15.343607 | AR48: 15.809288 | AS48: 16.276289 | AT48: 16.739104 | AU48: 17.201696 | AV48: 17.663715 | AW48: 18.124811 | AX48: 18.584629 | AY48: 19.042813 | AZ48: 19.499006 | BA48: 19.95285 | BB48: 20.403984 | BC48: 20.852051 | BD48: 21.296691 | BE48: 21.737547 | BF48: 22.174261 | BG48: 22.606479 | BH48: 23.033848 | BI48: 23.456018 | BJ48: 23.872644 | BK48: 24.283382 | BL48: 24.687893 | BM48: 25.085843
G52: TWWWOT | I52: SEWERWWWT + STW | J52: SEWERWW | M52: STWW | T52: 2030 | U52: 2050 | V52: 2070
E53: año | F53: millones de m3 | G53: %agua residual no tratada | H53: %sin alcantarillado | I53: %agua residual tratada | J53: % Alcantarillado | K53: %Aguas residuales tratadas que van alcantarilla | L53: % sin tratamiento va alcantarillado | M53: % tratadas va sin alcantarillado | N53: % no tratadas sin alcantarillado | O53: % Tanques sépticos/ tratamiento descentralizado | P53: % agua tratada a alcantarillado Normalizado | Q53: % agua no tratada a alcantarillado normalizado | S53: m Agua tratada | T53: =(Y10-R10)/(Y1-R1) -> 0 | U53: =(AS10-Y10)/($AS$1-$Y$1) -> 0 | V53: =(BM16-AS16)/($BM$1-$AS$1) -> 0
E54: 2010 | F54: 3.2042 | G54: 0.589 | H54: 0.18 | I54: 0.411 | J54: 0.824 | K54: 0.283 | L54: =J54-K54 -> 0.541 | M54: =I54-K54 -> 0.128 | N54: =L71/G71 -> 0.459 | O54: 0 | P54: =K54/J54 -> 0.3434466 | Q54: =L54/J54 -> 0.6565534 | S54: b Agua tratada | T54: =R10-T53*$R$1 -> 0.744 | U54: =Y10-U53*$Y$1 -> 0.744 | V54: =AS10-V53*$AS$1 -> 0.744
E55: 2011 | F55: 3.7105 | G55: 0.521 | H55: 0.058244444 | I55: 0.479 | J55: 0.94175556 | K55: 0.28495215 | L55: =J55-K55 -> 0.6568034 | M55: =I55-K55 -> 0.19404785 | N55: =L72/G72 -> 0.3431966 | O55: 0 | P55: =K55/J55 -> 0.30257549 | Q55: =L55/J55 -> 0.69742451 | S55: m Agua no tratada alcan | T55: =(Y16-R16)/($Y$1-$R$1) -> 0 | U55: =(AS16-Y16)/($AS$1-$Y$1) -> 0 | V55: =(BM16-AS16)/($BM$1-$AS$1) -> 0
E56: 2012 | F56: 4.2169 | G56: 0.502 | H56: 0.055477778 | I56: 0.498 | J56: 0.94452222 | K56: 0.28354545 | L56: =J56-K56 -> 0.66097677 | M56: =I56-K56 -> 0.21445455 | N56: =L73/G73 -> 0.33902323 | O56: 0 | P56: =K56/J56 -> 0.30019988 | Q56: =L56/J56 -> 0.69980012 | S56: B Agua no tratada alcan | T56: =R16-T55*$R$1 -> 0.74717369 | U56: =Y16-U55*$Y$1 -> 0.74717369 | V56: =AS16-V55*$AS$1 -> 0.74717369
E57: 2013 | F57: 4.5908 | G57: 0.502 | H57: 0.052711111 | I57: 0.498 | J57: 0.94728889 | K57: 0.283 | L57: =J57-K57 -> 0.66428889 | M57: =I57-K57 -> 0.215 | N57: =L74/G74 -> 0.33571111 | O57: 0 | P57: =K57/J57 -> 0.2987473 | Q57: =L57/J57 -> 0.7012527 | S57: m Agua tratada alcan | T57: =(Y19-R19)/($Y$1-$R$1) -> 0 | U57: =(AS19-Y19)/($AS$1-$Y$1) -> 0 | V57: =(BM19-AS19)/($BM$1-$AS$1) -> 0
E58: 2014 | F58: 4.9647 | G58: 0.441 | H58: 0.049944444 | I58: =I57+(((2014-2013)*(I59-I57))/(2015-2013)) -> 0.559 | J58: 0.95005556 | K58: 0.2847512 | L58: =J58-K58 -> 0.66530436 | M58: =I58-K58 -> 0.2742488 | N58: =L75/G75 -> 0.33469564 | O58: 0 | P58: =K58/J58 -> 0.29972057 | Q58: =L58/J58 -> 0.70027943 | S58: b Agua tratada alcan | T58: =R19-T57*$R$1 -> 0.246 | U58: =Y19-U57*$Y$1 -> 0.246 | V58: =AS19-V57*$AS$1 -> 0.246
E59: 2015 | F59: 5.1418 | G59: 0.38 | H59: 0.054 | I59: 0.62 | J59: 0.946 | K59: 0.289 | L59: =J59-K59 -> 0.657 | M59: =I59-K59 -> 0.331 | N59: =L76/G76 -> 0.343 | O59: 0 | P59: =K59/J59 -> 0.30549683 | Q59: =L59/J59 -> 0.69450317 | S59: m Aguano tratada alcan | T59: =(Y20-R20)/($Y$1-$R$1) -> 0 | U59: =(AS20-Y20)/($AS$1-$Y$1) -> 0 | V59: =(BM20-AS20)/($BM$1-$AS$1) -> 0
E60: 2016 | F60: 5.3186 | G60: 0.367 | H60: 0.041 | I60: 0.633 | J60: 0.959 | K60: 0.292 | L60: =J60-K60 -> 0.667 | M60: =I60-K60 -> 0.341 | N60: =L77/G77 -> 0.333 | O60: 0 | P60: =K60/J60 -> 0.30448384 | Q60: =L60/J60 -> 0.69551616 | S60: B Aguano tratada alcan | T60: =R20-T59*$R$1 -> 0.727 | U60: =Y20-U59*$Y$1 -> 0.727 | V60: =AS20-V59*$AS$1 -> 0.727
E61: 2017 | F61: 5.3311 | G61: 0.262 | H61: 0.036 | I61: 0.738 | J61: 0.964 | K61: 0.233 | L61: =J61-K61 -> 0.731 | M61: =I61-K61 -> 0.505 | N61: =L78/G78 -> 0.269 | O61: 0 | P61: =K61/J61 -> 0.24170124 | Q61: =L61/J61 -> 0.75829876 | S61: m No trat, no alc | T61: =(Y23-R23)/($Y$1-$R$1) -> 0 | U61: =(AS23-Y23)/($AS$1-$Y$1) -> 0 | V61: =(BM23-AS23)/($BM$1-$AS$1) -> 0
E62: 2018 | F62: 4.0447617 | G62: 0.335 | H62: 0.04 | I62: 0.665 | J62: 0.96 | K62: 0.273 | L62: =J62-K62 -> 0.687 | M62: =I62-K62 -> 0.392 | N62: =L79/G79 -> 0.313 | O62: 0 | P62: =K62/J62 -> 0.284375 | Q62: =L62/J62 -> 0.715625 | S62: b No trat, no alc | T62: =R23-T61*$R$1 -> 0.273 | U62: =Y23-U61*$Y$1 -> 0.273 | V62: =AS23-V61*$AS$1 -> 0.273
E63: 2019 | F63: 4.0075542 | G63: 0.299 | H63: 0.036 | I63: 0.701 | J63: 0.964 | K63: 0.22 | L63: =J63-K63 -> 0.744 | M63: =I63-K63 -> 0.481 | N63: =L80/G80 -> 0.256 | O63: 0 | P63: =K63/J63 -> 0.22821577 | Q63: =L63/J63 -> 0.77178423
E64: 2020 | F64: 4.0575662 | G64: 0.262 | H64: 0.032 | I64: 0.738 | J64: 0.968 | K64: 0.224 | L64: =J64-K64 -> 0.744 | M64: =I64-K64 -> 0.514 | N64: =L81/G81 -> 0.256 | O64: 0 | P64: =K64/J64 -> 0.23140496 | Q64: =L64/J64 -> 0.76859504
E65: 2021 | F65: 4.1197164 | G65: 0.258 | H65: 0.032 | I65: 0.742 | J65: 0.968 | K65: 0.223 | L65: =J65-K65 -> 0.745 | M65: =I65-K65 -> 0.519 | N65: =L82/G82 -> 0.255 | O65: 0 | P65: =K65/J65 -> 0.2303719 | Q65: =L65/J65 -> 0.7696281
E66: 2022 | F66: 4.4630366 | G66: 0.247 | H66: 0.027 | I66: 0.753 | J66: 0.973 | K66: 0.263 | L66: =J66-K66 -> 0.71 | M66: =I66-K66 -> 0.49 | N66: =L83/G83 -> 0.29 | O66: 0 | P66: =K66/J66 -> 0.27029805 | Q66: =L66/J66 -> 0.72970195
E67: 2023 | F67: 4.8134584 | G67: 0.256 | H67: 0.027 | I67: 0.744 | J67: 0.973 | K67: 0.246 | L67: =J67-K67 -> 0.727 | M67: =I67-K67 -> 0.498 | N67: =L84/G84 -> 0.273 | O67: 0 | P67: =K67/J67 -> 0.25282631 | Q67: =L67/J67 -> 0.74717369
E70: año | F70: millones de m3 | G70: agua residual no tratada | H70: agua residual tratada | I70: sin tratamiento- alcantarillado | J70: tratadas que van alcantarilla | K70: tratadas va sin alcantarillado | L70: no tratadas sin alcantarillado | M70: agua tratada a alcantarillado Normalizado | N70: agua no tratada a alcantarillado normalizado
E71: 2010 | F71: 3.2042 | G71: =F54*G54 -> 1.8872738 | H71: =F54*I54 -> 1.3169262 | I71: =G71*L54 -> 1.0210151 | J71: =H71*K54 -> 0.37269011 | K71: =H71*M54 -> 0.16856655 | L71: =G71-I71 -> 0.86625867 | M71: =P54*H71 -> 0.45229383 | N71: =G71*Q54 -> 1.239096
E72: 2011 | F72: 3.7105 | G72: =F55*G55 -> 1.9331705 | H72: =F55*I55 -> 1.7773295 | I72: =G72*L55 -> 1.269713 | J72: =H72*K55 -> 0.50645387 | K72: =H72*M55 -> 0.34488696 | L72: =G72-I72 -> 0.66345754 | M72: =P55*H72 -> 0.53777635 | N72: =G72*Q55 -> 1.3482405
E73: 2012 | F73: 4.2169 | G73: =F56*G56 -> 2.1168838 | H73: =F56*I56 -> 2.1000162 | I73: =G73*L56 -> 1.399211 | J73: =H73*K56 -> 0.59545005 | K73: =H73*M56 -> 0.45035802 | L73: =G73-I73 -> 0.71767279 | M73: =P56*H73 -> 0.6304246 | N73: =G73*Q56 -> 1.4813955
E74: 2013 | F74: 4.5908 | G74: =F57*G57 -> 2.3045816 | H74: =F57*I57 -> 2.2862184 | I74: =G74*L57 -> 1.530908 | J74: =H74*K57 -> 0.64699981 | K74: =H74*M57 -> 0.49153696 | L74: =G74-I74 -> 0.77367365 | M74: =P57*H74 -> 0.68300158 | N74: =G74*Q57 -> 1.6160941
E75: 2014 | F75: 4.9647 | G75: =F58*G58 -> 2.1894327 | H75: =F58*I58 -> 2.7752673 | I75: =G75*L58 -> 1.4566391 | J75: =H75*K58 -> 0.79026068 | K75: =H75*M58 -> 0.76111374 | L75: =G75-I75 -> 0.73279358 | M75: =P58*H75 -> 0.83180471 | N75: =G75*Q58 -> 1.5332147
E76: 2015 | F76: 5.1418 | G76: =F59*G59 -> 1.953884 | H76: =F59*I59 -> 3.187916 | I76: =G76*L59 -> 1.2837018 | J76: =H76*K59 -> 0.92130772 | K76: =H76*M59 -> 1.0552002 | L76: =G76-I76 -> 0.67018221 | M76: =P59*H76 -> 0.97389823 | N76: =G76*Q59 -> 1.3569786
E77: 2016 | F77: 5.3186 | G77: =F60*G60 -> 1.9519262 | H77: =F60*I60 -> 3.3666738 | I77: =G77*L60 -> 1.3019348 | J77: =H77*K60 -> 0.98306875 | K77: =H77*M60 -> 1.1480358 | L77: =G77-I77 -> 0.64999142 | M77: =P60*H77 -> 1.0250978 | N77: =G77*Q60 -> 1.3575962
E78: 2017 | F78: 5.3311 | G78: =F61*G61 -> 1.3967482 | H78: =F61*I61 -> 3.9343518 | I78: =G78*L61 -> 1.0210229 | J78: =H78*K61 -> 0.91670397 | K78: =H78*M61 -> 1.9868477 | L78: =G78-I78 -> 0.37572527 | M78: =P61*H78 -> 0.95093773 | N78: =G78*Q61 -> 1.0591524
E79: 2018 | F79: 4.0447617 | G79: =F62*G62 -> 1.3549952 | H79: =F62*I62 -> 2.6897666 | I79: =G79*L62 -> 0.93088169 | J79: =H79*K62 -> 0.73430627 | K79: =H79*M62 -> 1.0543885 | L79: =G79-I79 -> 0.42411349 | M79: =P62*H79 -> 0.76490236 | N79: =G79*Q62 -> 0.96966843
E80: 2019 | F80: 4.0075542 | G80: =F63*G63 -> 1.1982587 | H80: =F63*I63 -> 2.8092955 | I80: =G80*L63 -> 0.89150448 | J80: =H80*K63 -> 0.61804501 | K80: =H80*M63 -> 1.3512711 | L80: =G80-I80 -> 0.30675423 | M80: =P63*H80 -> 0.64112553 | N80: =G80*Q63 -> 0.92479717
E81: 2020 | F81: 4.0575662 | G81: =F64*G64 -> 1.0630823 | H81: =F64*I64 -> 2.9944839 | I81: =G81*L64 -> 0.79093326 | J81: =H81*K64 -> 0.67076438 | K81: =H81*M64 -> 1.5391647 | L81: =G81-I81 -> 0.27214908 | M81: =P64*H81 -> 0.69293841 | N81: =G81*Q64 -> 0.81707982
E82: 2021 | F82: 4.1197164 | G82: =F65*G65 -> 1.0628868 | H82: =F65*I65 -> 3.0568295 | I82: =G82*L65 -> 0.79185068 | J82: =H82*K65 -> 0.68167299 | K82: =H82*M65 -> 1.5864945 | L82: =G82-I82 -> 0.27103614 | M82: =P65*H82 -> 0.70420763 | N82: =G82*Q65 -> 0.81802756
... E84: 2023 | F84: 4.8134584 | G84: =F67*G67 -> 1.2322454 | H84: =F67*I67 -> 3.5812131 | I84: =G84*L67 -> 0.89584237 | J84: =H84*K67 -> 0.88097841 | K84: =H84*M67 -> 1.7834441 | L84: =G84-I84 -> 0.33640298 | M84: =P67*H84 -> 0.90542488 | N84: =G84*Q67 -> 0.92070131

Sheet ParticipacionTechsAguas
D1: Ecuador | E1: 2018 | F1: 2019 | G1: 2020 | H1: 2021 | I1: 2022 | J1: 2023 | K1: 2024 | L1: 2025 | M1: 2026 | N1: 2027 | O1: 2028 | P1: 2029 | Q1: 2030 | R1: 2031 | S1: 2032 | T1: 2033 | U1: 2034 | V1: 2035 | W1: 2036 | X1: 2037 | Y1: 2038 | Z1: 2039 | AA1: 2040 | AB1: 2041 | AC1: 2042 | AD1: 2043 | AE1: 2044 | AF1: 2045 | AG1: 2046 | AH1: 2047 | AI1: 2048 | AJ1: 2049 | AK1: 2050 | AL1: 2051 | AM1: 2052 | AN1: 2053 | AO1: 2054 | AP1: 2055 | AQ1: 2056 | AR1: 2057 | AS1: 2058 | AT1: 2059 | AU1: 2060 | AV1: 2061 | AW1: 2062 | AX1: 2063 | AY1: 2064 | AZ1: 2065 | BA1: 2066 | BB1: 2067 | BC1: 2068 | BD1: 2069 | BE1: 2070
D4: Aguas residuales (PORCENTAJES)
C6: Códigos OSeMOSYS | D6: Escenario: Políticas Anunciadas
D8: Distribución de las aguas residuales
D9: % Residuos sin tratamiento | E9: 0.75 | F9: 0.75 | G9: 0.75 | H9: 0.75 | I9: =H9 -> 0.75 | J9: =I9 -> 0.75 | K9: =V67 -> 0.453 | L9: 0.65 | M9: =X67 -> 0.645 | N9: =Y67 -> 0.64 | O9: =Z67 -> 0.635 | P9: =AA67 -> 0.63 | Q9: =AB67 -> 0.625 | R9: =AC67 -> 0.62 | S9: =AD67 -> 0.615 | T9: =AE67 -> 0.61 | ... AJ9: =AU67 -> 0.53 | AK9: 0.525 | AL9: =AW67 -> 0.51875 | AM9: =AX67 -> 0.5125 | AN9: =AY67 -> 0.50625 | AO9: =AZ67 -> 0.5 | AP9: =BA67 -> 0.49375 | AQ9: =BB67 -> 0.4875 | AR9: =BC67 -> 0.48125 | AS9: =BD67 -> 0.475 | ... BD9: =BO67 -> 0.40625 | BE9: 0.4
D10: % Alcantarillado | E10: 0.25 | F10: 0.25 | G10: 0.25 | H10: 0.25 | I10: =H10 -> 0.25 | J10: =I10 -> 0.25 | K10: =V68 -> 0.537 | L10: 0.33 | M10: =X68 -> 0.3338 | N10: =Y68 -> 0.3376 | O10: =Z68 -> 0.3414 | P10: =AA68 -> 0.3452 | Q10: =AB68 -> 0.349 | R10: =AC68 -> 0.3528 | S10: =AD68 -> 0.3566 | T10: =AE68 -> 0.3604 | ... AJ10: =AU68 -> 0.4212 | AK10: 0.425 | AL10: =AW68 -> 0.42625 | AM10: =AX68 -> 0.4275 | AN10: =AY68 -> 0.42875 | AO10: =AZ68 -> 0.43 | AP10: =BA68 -> 0.43125 | AQ10: =BB68 -> 0.4325 | AR10: =BC68 -> 0.43375 | AS10: =BD68 -> 0.435 | ... BD10: =BO68 -> 0.44875 | BE10: 0.45
C11: STWW | D11: % Tanques sépticos/ tratamiento descentralizado | E11: 0 | F11: 0 | G11: 0 | H11: 0 | I11: =H11 -> 0 | J11: =I11 -> 0 | K11: =V69 -> 0.01 | L11: 0.02 | M11: =X69 -> 0.0212 | N11: =Y69 -> 0.0224 | O11: =Z69 -> 0.0236 | P11: =AA69 -> 0.0248 | Q11: =AB69 -> 0.026 | R11: =AC69 -> 0.0272 | S11: =AD69 -> 0.0284 | T11: =AE69 -> 0.0296 | ... AJ11: =AU69 -> 0.0488 | AK11: 0.05 | AL11: =AW69 -> 0.055 | AM11: =AX69 -> 0.06 | AN11: =AY69 -> 0.065 | AO11: =AZ69 -> 0.07 | AP11: =BA69 -> 0.075 | AQ11: =BB69 -> 0.08 | AR11: =BC69 -> 0.085 | AS11: =BD69 -> 0.09 | ... BD11: =BO69 -> 0.145 | BE11: 0.15
D12: % Total | E12: =SUM(E9:E11) -> 1 | F12: =SUM(F9:F11) -> 1 | G12: =SUM(G9:G11) -> 1 | H12: =SUM(H9:H11) -> 1 | I12: =SUM(I9:I11) -> 1 | J12: =SUM(J9:J11) -> 1 | K12: =SUM(K9:K11) -> 1 | L12: =SUM(L9:L11) -> 1 | ... BE12: =SUM(BE9:BE11) -> 1
D14: Distribución de las aguas residuales que van al alcantarillado
D15: % Con tratamiento (ESTO ES CON RESPECTO A LO QUE VA A ACANTARILLADO) | E15: 0.25 | F15: 0.25 | G15: 0.25 | H15: 0.25 | I15: =H15 -> 0.25 | J15: =I15 -> 0.25 | K15: =J15 -> 0.25 | L15: =K15 -> 0.25 | M15: =L15 -> 0.25 | N15: =M15 -> 0.25 | O15: =N15 -> 0.25 | P15: =O15 -> 0.25 | ... BE15: =BD15 -> 0.25
D16: % Sin tratamiento (ESTO ES CON RESPECTO A LO QUE VA A ACANTARILLADO) | E16: 0.75 | F16: 0.75 | G16: 0.75 | H16: 0.75 | I16: =H16 -> 0.75 | J16: =I16 -> 0.75 | K16: =J16 -> 0.75 | L16: =K16 -> 0.75 | M16: =L16 -> 0.75 | N16: =M16 -> 0.75 | O16: =N16 -> 0.75 | P16: =O16 -> 0.75 | ... BE16: =BD16 -> 0.75
E17: =SUM(E15:E16) -> 1 | F17: =SUM(F15:F16) -> 1 | G17: =SUM(G15:G16) -> 1 | H17: =SUM(H15:H16) -> 1 | I17: =SUM(I15:I16) -> 1 | J17: =SUM(J15:J16) -> 1 | K17: =SUM(K15:K16) -> 1 | L17: =SUM(L15:L16) -> 1 | ... BE17: =SUM(BE15:BE16) -> 1
D18: Distribución de las aguas residuales que van al alcantarillado
C19: WWWT;SEWERWWWT;SEWERWW | D19: % Con tratamiento (ESTO ES CON RESPECTO AL TOTAL DE AGUAS RESIDUALES) | E19: =E10*E15 -> 0.0625 | F19: =F10*F15 -> 0.0625 | G19: =G10*G15 -> 0.0625 | H19: =H10*H15 -> 0.0625 | I19: =I10*I15 -> 0.0625 | J19: =J10*J15 -> 0.0625 | K19: =K10*K15 -> 0.13425 | L19: =L10*L15 -> 0.0825 | ... BE19: =BE10*BE15 -> 0.1125
D20: % Sin tratamiento (ESTO ES CON RESPECTO AL TOTAL DE AGUAS RESIDUALES) | E20: =E10*E16 -> 0.1875 | F20: =F10*F16 -> 0.1875 | G20: =G10*G16 -> 0.1875 | H20: =H10*H16 -> 0.1875 | I20: =I10*I16 -> 0.1875 | J20: =J10*J16 -> 0.1875 | K20: =K10*K16 -> 0.40275 | L20: =L10*L16 -> 0.2475 | ... BE20: =BE10*BE16 -> 0.3375
D21: Total | E21: =SUM(E19+E20) -> 0.25 | F21: =SUM(F19+F20) -> 0.25 | G21: =SUM(G19+G20) -> 0.25 | H21: =SUM(H19+H20) -> 0.25 | I21: =SUM(I19+I20) -> 0.25 | J21: =SUM(J19+J20) -> 0.25 | K21: =SUM(K19+K20) -> 0.537 | L21: =SUM(L19+L20) -> 0.33 | ... BE21: =SUM(BE19+BE20) -> 0.45
C22: WWWOT;TWWWOT | E22: =E9+E20 -> 0.9375 | F22: =F9+F20 -> 0.9375 | G22: =G9+G20 -> 0.9375 | H22: =H9+H20 -> 0.9375 | I22: =I9+I20 -> 0.9375 | J22: =J9+J20 -> 0.9375 | K22: =K9+K20 -> 0.85575 | L22: =L9+L20 -> 0.8975 | ... BE22: =BE9+BE20 -> 0.7375
D23: Escenario: Net Zero 2050
D25: Distribución de las aguas residuales
D26: % Residuos sin tratamiento | E26: 0.75 | F26: 0.75 | G26: 0.75 | H26: 0.75 | I26: =H26 -> 0.75 | J26: =I26 -> 0.75 | K26: =K101 -> 0.7 | L26: 0.65 | M26: =M101 -> 0.636 | N26: =N101 -> 0.622 | O26: =O101 -> 0.608 | P26: =P101 -> 0.594 | Q26: =Q101 -> 0.58 | R26: =R101 -> 0.566 | S26: =S101 -> 0.552 | T26: =T101 -> 0.538 | ... AJ26: =AJ101 -> 0.314 | AK26: 0.3 | AL26: =AL101 -> 0.29 | AM26: =AM101 -> 0.28 | AN26: =AN101 -> 0.27 | AO26: =AO101 -> 0.26 | AP26: =AP101 -> 0.25 | AQ26: =AQ101 -> 0.24 | AR26: =AR101 -> 0.23 | AS26: =AS101 -> 0.22 | ... BD26: =BD101 -> 0.11 | BE26: 0.1
D27: % Alcantarillado | E27: 0.25 | F27: 0.25 | G27: 0.25 | H27: 0.25 | I27: =H27 -> 0.25 | J27: =I27 -> 0.25 | K27: =K102 -> 0.29 | L27: 0.33 | M27: =M102 -> 0.3368 | N27: =N102 -> 0.3436 | O27: =O102 -> 0.3504 | P27: =P102 -> 0.3572 | Q27: =Q102 -> 0.364 | R27: =R102 -> 0.3708 | S27: =S102 -> 0.3776 | T27: =T102 -> 0.3844 | ... AJ27: =AJ102 -> 0.4932 | AK27: 0.5 | AL27: =AL102 -> 0.5 | AM27: =AM102 -> 0.5 | AN27: =AN102 -> 0.5 | AO27: =AO102 -> 0.5 | AP27: =AP102 -> 0.5 | AQ27: =AQ102 -> 0.5 | AR27: =AR102 -> 0.5 | AS27: =AS102 -> 0.5 | ... BD27: =BD102 -> 0.5 | BE27: 0.5
C28: STWW | D28: % Tanques sépticos | E28: 0 | F28: 0 | G28: 0 | H28: 0 | I28: =H28 -> 0 | J28: =I28 -> 0 | K28: =K103 -> 0.01 | L28: 0.02 | M28: =M103 -> 0.0272 | N28: =N103 -> 0.0344 | O28: =O103 -> 0.0416 | P28: =P103 -> 0.0488 | Q28: =Q103 -> 0.056 | R28: =R103 -> 0.0632 | S28: =S103 -> 0.0704 | T28: =T103 -> 0.0776 | ... AJ28: =AJ103 -> 0.1928 | AK28: 0.2 | AL28: =AL103 -> 0.21 | AM28: =AM103 -> 0.22 | AN28: =AN103 -> 0.23 | AO28: =AO103 -> 0.24 | AP28: =AP103 -> 0.25 | AQ28: =AQ103 -> 0.26 | AR28: =AR103 -> 0.27 | AS28: =AS103 -> 0.28 | ... BD28: =BD103 -> 0.39 | BE28: 0.4
D29: % Total | E29: =SUM(E26:E28) -> 1 | F29: =SUM(F26:F28) -> 1 | G29: =SUM(G26:G28) -> 1 | H29: =SUM(H26:H28) -> 1 | I29: =SUM(I26:I28) -> 1 | J29: =SUM(J26:J28) -> 1 | K29: =SUM(K26:K28) -> 1 | L29: =SUM(L26:L28) -> 1 | ... BE29: =SUM(BE26:BE28) -> 1
D31: Distribución de las aguas residuales que van al alcantarillado
D32: % Con tratamiento (ESTO ES CON RESPECTO A LO QUE VA A ACANTARILLADO) | E32: 0.25 | F32: 0.25 | G32: 0.25 | H32: 0.25 | I32: =H32 -> 0.25 | J32: =I32 -> 0.25 | K32: =J32 -> 0.25 | L32: =K32 -> 0.25 | M32: =L32 -> 0.25 | N32: =M32 -> 0.25 | O32: =N32 -> 0.25 | P32: =O32 -> 0.25 | ... BE32: =BD32 -> 0.25
D33: % Sin tratamiento (ESTO ES CON RESPECTO A LO QUE VA A ACANTARILLADO) | E33: 0.75 | F33: 0.75 | G33: 0.75 | H33: 0.75 | I33: =H33 -> 0.75 | J33: =I33 -> 0.75 | K33: =J33 -> 0.75 | L33: =K33 -> 0.75 | M33: =L33 -> 0.75 | N33: =M33 -> 0.75 | O33: =N33 -> 0.75 | P33: =O33 -> 0.75 | ... BE33: =BD33 -> 0.75
E34: =SUM(E32:E33) -> 1 | F34: =SUM(F32:F33) -> 1 | G34: =SUM(G32:G33) -> 1 | H34: =SUM(H32:H33) -> 1 | I34: =SUM(I32:I33) -> 1 | J34: =SUM(J32:J33) -> 1 | K34: =SUM(K32:K33) -> 1 | L34: =SUM(L32:L33) -> 1 | ... BE34: =SUM(BE32:BE33) -> 1
D35: Distribución de las aguas residuales que van al alcantarillado
C36: WWWT;SEWERWWWT;SEWERWW | D36: % Con tratamiento (ESTO ES CON RESPECTO AL TOTAL DE AGUAS RESIDUALES) | E36: =E27*E32 -> 0.0625 | F36: =F27*F32 -> 0.0625 | G36: =G27*G32 -> 0.0625 | H36: =H27*H32 -> 0.0625 | I36: =I27*I32 -> 0.0625 | J36: =J27*J32 -> 0.0625 | K36: =K27*K32 -> 0.0725 | L36: =L27*L32 -> 0.0825 | ... BE36: =BE27*BE32 -> 0.125
D37: % Sin tratamiento (ESTO ES CON RESPECTO AL TOTAL DE AGUAS RESIDUALES) | E37: =E27*E33 -> 0.1875 | F37: =F27*F33 -> 0.1875 | G37: =G27*G33 -> 0.1875 | H37: =H27*H33 -> 0.1875 | I37: =I27*I33 -> 0.1875 | J37: =J27*J33 -> 0.1875 | K37: =K27*K33 -> 0.2175 | L37: =L27*L33 -> 0.2475 | ... BE37: =BE27*BE33 -> 0.375
D38: Total | E38: =SUM(E36+E37) -> 0.25 | F38: =SUM(F36+F37) -> 0.25 | G38: =SUM(G36+G37) -> 0.25 | H38: =SUM(H36+H37) -> 0.25 | I38: =SUM(I36+I37) -> 0.25 | J38: =SUM(J36+J37) -> 0.25 | K38: =SUM(K36+K37) -> 0.29 | L38: =SUM(L36+L37) -> 0.33 | ... BE38: =SUM(BE36+BE37) -> 0.5
C39: WWWOT;TWWWOT | E39: =E26+E37 -> 0.9375 | F39: =F26+F37 -> 0.9375 | G39: =G26+G37 -> 0.9375 | H39: =H26+H37 -> 0.9375 | I39: =I26+I37 -> 0.9375 | J39: =J26+J37 -> 0.9375 | K39: =K26+K37 -> 0.9175 | L39: =L26+L37 -> 0.8975 | ... BE39: =BE26+BE37 -> 0.475
D40: Escenario: Net Zero 2070
D42: Distribución de las aguas residuales
D43: % Residuos sin tratamiento | E43: 0.75 | F43: 0.75 | G43: 0.75 | H43: 0.75 | I43: =H43 -> 0.75 | J43: =I43 -> 0.75 | K43: =K136 -> 0.7 | L43: 0.65 | M43: =M136 -> 0.64222222 | N43: =N136 -> 0.63444444 | O43: =O136 -> 0.62666667 | P43: =P136 -> 0.61888889 | Q43: =Q136 -> 0.61111111 | R43: =R136 -> 0.60333333 | S43: =S136 -> 0.59555556 | T43: =T136 -> 0.58777778 | ... AJ43: =AJ136 -> 0.46333333 | AK43: 0.45555556 | AL43: =AL136 -> 0.44777778 | AM43: =AM136 -> 0.44 | AN43: =AN136 -> 0.43222222 | AO43: =AO136 -> 0.42444444 | AP43: =AP136 -> 0.41666667 | AQ43: =AQ136 -> 0.40888889 | AR43: =AR136 -> 0.40111111 | AS43: =AS136 -> 0.39333333 | ... BD43: =BD136 -> 0.30777778 | BE43: 0.3
D44: % Alcantarillado | E44: 0.25 | F44: 0.25 | G44: 0.25 | H44: 0.25 | I44: =H44 -> 0.25 | J44: =I44 -> 0.25 | K44: =K137 -> 0.29 | L44: 0.33 | M44: =M137 -> 0.33457778 | N44: =N137 -> 0.33915556 | O44: =O137 -> 0.34373333 | P44: =P137 -> 0.34831111 | Q44: =Q137 -> 0.35288889 | R44: =R137 -> 0.35746667 | S44: =S137 -> 0.36204444 | T44: =T137 -> 0.36662222 | ... AJ44: =AJ137 -> 0.43986667 | AK44: 0.44444444 | AL44: =AL137 -> 0.44722222 | AM44: =AM137 -> 0.45 | AN44: =AN137 -> 0.45277778 | AO44: =AO137 -> 0.45555556 | AP44: =AP137 -> 0.45833333 | AQ44: =AQ137 -> 0.46111111 | AR44: =AR137 -> 0.46388889 | AS44: =AS137 -> 0.46666667 | ... BD44: =BD137 -> 0.49722222 | BE44: 0.5
C45: STWW | D45: % Tanques sépticos | E45: 0 | F45: 0 | G45: 0 | H45: 0 | I45: =H45 -> 0 | J45: =I45 -> 0 | K45: =K138 -> 0.01 | L45: 0.02 | M45: =M138 -> 0.0232 | N45: =N138 -> 0.0264 | O45: =O138 -> 0.0296 | P45: =P138 -> 0.0328 | Q45: =Q138 -> 0.036 | R45: =R138 -> 0.0392 | S45: =S138 -> 0.0424 | T45: =T138 -> 0.0456 | ... AJ45: =AJ138 -> 0.0968 | AK45: 0.1 | AL45: =AL138 -> 0.105 | AM45: =AM138 -> 0.11 | AN45: =AN138 -> 0.115 | AO45: =AO138 -> 0.12 | AP45: =AP138 -> 0.125 | AQ45: =AQ138 -> 0.13 | AR45: =AR138 -> 0.135 | AS45: =AS138 -> 0.14 | ... BD45: =BD138 -> 0.195 | BE45: 0.2
D46: % Total | E46: =SUM(E43:E45) -> 1 | F46: =SUM(F43:F45) -> 1 | G46: =SUM(G43:G45) -> 1 | H46: =SUM(H43:H45) -> 1 | I46: =SUM(I43:I45) -> 1 | J46: =SUM(J43:J45) -> 1 | K46: =SUM(K43:K45) -> 1 | L46: =SUM(L43:L45) -> 1 | ... BE46: =SUM(BE43:BE45) -> 1
D48: Distribución de las aguas residuales que van al alcantarillado
D49: % Con tratamiento (ESTO ES CON RESPECTO A LO QUE VA A ACANTARILLADO) | E49: 0.25 | F49: 0.25 | G49: 0.25 | H49: 0.25 | I49: =H49 -> 0.25 | J49: =I49 -> 0.25 | K49: =J49 -> 0.25 | L49: =K49 -> 0.25 | M49: =L49 -> 0.25 | N49: =M49 -> 0.25 | O49: =N49 -> 0.25 | P49: =O49 -> 0.25 | ... BE49: =BD49 -> 0.25
D50: % Sin tratamiento (ESTO ES CON RESPECTO A LO QUE VA A ACANTARILLADO) | E50: 0.75 | F50: 0.75 | G50: 0.75 | H50: 0.75 | I50: =H50 -> 0.75 | J50: =I50 -> 0.75 | K50: =J50 -> 0.75 | L50: =K50 -> 0.75 | M50: =L50 -> 0.75 | N50: =M50 -> 0.75 | O50: =N50 -> 0.75 | P50: =O50 -> 0.75 | ... BE50: =BD50 -> 0.75
E51: =SUM(E49:E50) -> 1 | F51: =SUM(F49:F50) -> 1 | G51: =SUM(G49:G50) -> 1 | H51: =SUM(H49:H50) -> 1 | I51: =SUM(I49:I50) -> 1 | J51: =SUM(J49:J50) -> 1 | K51: =SUM(K49:K50) -> 1 | L51: =SUM(L49:L50) -> 1 | ... BE51: =SUM(BE49:BE50) -> 1
D52: Distribución de las aguas residuales que van al alcantarillado
C53: WWWT;SEWERWWWT;SEWERWW | D53: % Con tratamiento (ESTO ES CON RESPECTO AL TOTAL DE AGUAS RESIDUALES) | E53: =E44*E49 -> 0.0625 | F53: =F44*F49 -> 0.0625 | G53: =G44*G49 -> 0.0625 | H53: =H44*H49 -> 0.0625 | I53: =I44*I49 -> 0.0625 | J53: =J44*J49 -> 0.0625 | K53: =K44*K49 -> 0.0725 | L53: =L44*L49 -> 0.0825 | ... BE53: =BE44*BE49 -> 0.125
D54: % Sin tratamiento (ESTO ES CON RESPECTO AL TOTAL DE AGUAS RESIDUALES) | E54: =E44*E50 -> 0.1875 | F54: =F44*F50 -> 0.1875 | G54: =G44*G50 -> 0.1875 | H54: =H44*H50 -> 0.1875 | I54: =I44*I50 -> 0.1875 | J54: =J44*J50 -> 0.1875 | K54: =K44*K50 -> 0.2175 | L54: =L44*L50 -> 0.2475 | ... BE54: =BE44*BE50 -> 0.375
D55: % Total | E55: =SUM(E53+E54) -> 0.25 | F55: =SUM(F53+F54) -> 0.25 | G55: =SUM(G53+G54) -> 0.25 | H55: =SUM(H53+H54) -> 0.25 | I55: =SUM(I53+I54) -> 0.25 | J55: =SUM(J53+J54) -> 0.25 | K55: =SUM(K53+K54) -> 0.29 | L55: =SUM(L53+L54) -> 0.33 | ... BE55: =SUM(BE53+BE54) -> 0.5
C57: WWWOT;TWWWOT | E57: =E43+E54 -> 0.9375 | F57: =F43+F54 -> 0.9375 | G57: =G43+G54 -> 0.9375 | H57: =H43+H54 -> 0.9375 | I57: =I43+I54 -> 0.9375 | J57: =J43+J54 -> 0.9375 | K57: =K43+K54 -> 0.9175 | L57: =L43+L54 -> 0.8975 | ... BE57: =BE43+BE54 -> 0.675
B60: Interpolación
D61: Escenario: Políticas Anunciadas | H61: 2010 | I61: 2011 | J61: 2012 | K61: 2013 | L61: 2014 | M61: 2015 | N61: 2016 | O61: 2017 | P61: 2018 | Q61: 2019 | R61: 2020 | S61: 2021 | T61: 2022 | U61: 2023 | V61: 2024 | W61: 2025 | X61: 2026 | Y61: 2027 | Z61: 2028 | AA61: 2029 | AB61: 2030 | AC61: 2031 | AD61: 2032 | AE61: 2033 | AF61: 2034 | AG61: 2035 | AH61: 2036 | AI61: 2037 | AJ61: 2038 | AK61: 2039 | AL61: 2040 | AM61: 2041 | AN61: 2042 | AO61: 2043 | AP61: 2044 | AQ61: 2045 | AR61: 2046 | AS61: 2047 | AT61: 2048 | AU61: 2049 | AV61: 2050 | AW61: 2051 | AX61: 2052 | AY61: 2053 | AZ61: 2054 | BA61: 2055 | BB61: 2056 | BC61: 2057 | BD61: 2058 | BE61: 2059 | BF61: 2060 | BG61: 2061 | BH61: 2062 | BI61: 2063 | BJ61: 2064 | BK61: 2065 | BL61: 2066 | BM61: 2067 | BN61: 2068 | BO61: 2069 | BP61: 2070
H63: 0.589 | I63: 0.521 | J63: 0.502 | K63: 0.502 | L63: 0.441 | M63: 0.38 | N63: 0.367 | O63: 0.262 | P63: 0.335 | Q63: 0.299 | R63: 0.262 | S63: 0.258 | T63: 0.247 | U63: 0.256 | V63: 0.27185566 | W63: 0.28771132 | X63: 0.30356698 | Y63: 0.31942264 | Z63: 0.3352783 | AA63: 0.35113396 | AB63: 0.36698962 | AC63: 0.36610406 | AD63: 0.36521851 | AE63: 0.36433295 | AF63: 0.36344739 | AG63: 0.36256183 | AH63: 0.36167627 | AI63: 0.36079072 | AJ63: 0.35990516 | AK63: 0.3590196 | AL63: 0.35813404 | AM63: 0.35724849 | AN63: 0.35636293 | AO63: 0.35547737 | AP63: 0.35459181 | AQ63: 0.35370625 | AR63: 0.3528207 | AS63: 0.35193514 | AT63: 0.35104958 | AU63: 0.35016402 | AV63: 0.34927846 | AW63: 0.34909685 | AX63: 0.34891524 | AY63: 0.34873363 | AZ63: 0.34855202 | BA63: 0.34837041 | BB63: 0.3481888 | BC63: 0.34800719 | BD63: 0.34782558 | BE63: 0.34764397 | BF63: 0.34746236 | BG63: 0.34728075 | BH63: 0.34709914 | BI63: 0.34691753 | BJ63: 0.34673592 | BK63: 0.34655431 | BL63: 0.3463727 | BM63: 0.34619109 | BN63: 0.34600948 | BO63: 0.34582787 | BP63: 0.3543648
H64: 0.411 | I64: 0.479 | J64: 0.498 | K64: 0.498 | L64: 0.559 | M64: 0.62 | N64: 0.633 | O64: 0.738 | P64: 0.665 | Q64: 0.701 | R64: 0.738 | S64: 0.742 | T64: 0.753 | U64: 0.744 | V64: 0.72814434 | W64: 0.71228868 | X64: 0.69643302 | Y64: 0.68057736 | Z64: 0.6647217 | AA64: 0.64886604 | AB64: 0.63301038 | AC64: 0.63389594 | AD64: 0.63478149 | AE64: 0.63566705 | AF64: 0.63655261 | AG64: 0.63743817 | AH64: 0.63832373 | AI64: 0.63920928 | AJ64: 0.64009484 | AK64: 0.6409804 | AL64: 0.64186596 | AM64: 0.64275151 | AN64: 0.64363707 | AO64: 0.64452263 | AP64: 0.64540819 | AQ64: 0.64629375 | AR64: 0.6471793 | AS64: 0.64806486 | AT64: 0.64895042 | AU64: 0.64983598 | AV64: 0.65072154 | AW64: 0.65090315 | AX64: 0.65108476 | AY64: 0.65126637 | AZ64: 0.65144798 | BA64: 0.65162959 | BB64: 0.6518112 | BC64: 0.65199281 | BD64: 0.65217442 | BE64: 0.65235603 | BF64: 0.65253764 | BG64: 0.65271925 | BH64: 0.65290086 | BI64: 0.65308247 | BJ64: 0.65326408 | BK64: 0.65344569 | BL64: 0.6536273 | BM64: 0.65380891 | BN64: 0.65399052 | BO64: 0.65417213 | BP64: 0.6456352
H65: 0 | I65: 0 | J65: 0 | K65: 0 | L65: 0 | M65: 0 | N65: 0 | O65: 0 | P65: 0 | Q65: 0 | R65: 0 | S65: 0 | T65: 0 | U65: 0 | V65: 0 | W65: 0 | X65: 0 | Y65: 0 | Z65: 0 | AA65: 0 | AB65: 0 | AC65: 0 | AD65: 0 | AE65: 0 | AF65: 0 | AG65: 0 | AH65: 0 | AI65: 0 | AJ65: 0 | AK65: 0 | AL65: 0 | AM65: 0 | AN65: 0 | AO65: 0 | AP65: 0 | AQ65: 0 | AR65: 0 | AS65: 0 | AT65: 0 | AU65: 0 | AV65: 0 | AW65: 0 | AX65: 0 | AY65: 0 | AZ65: 0 | BA65: 0 | BB65: 0 | BC65: 0 | BD65: 0 | BE65: 0 | BF65: 0 | BG65: 0 | BH65: 0 | BI65: 0 | BJ65: 0 | BK65: 0 | BL65: 0 | BM65: 0 | BN65: 0 | BO65: 0 | BP65: 0
D66: Distribución de las aguas residuales
D67: % Residuos sin tratamiento | H67: 0.589 | I67: 0.521 | J67: 0.502 | K67: 0.502 | L67: 0.441 | M67: 0.38 | N67: 0.367 | O67: 0.262 | P67: 0.335 | Q67: 0.299 | R67: 0.262 | S67: 0.258 | T67: 0.247 | U67: 0.256 | V67: =$S$72*V61+$S$73 -> 0.453 | W67: =L9 -> 0.65 | X67: =$W$72*X61+$W$73 -> 0.645 | Y67: =$W$72*Y61+$W$73 -> 0.64 | Z67: =$W$72*Z61+$W$73 -> 0.635 | AA67: =$W$72*AA61+$W$73 -> 0.63 | AB67: =$W$72*AB61+$W$73 -> 0.625 | AC67: =$W$72*AC61+$W$73 -> 0.62 | AD67: =$W$72*AD61+$W$73 -> 0.615 | AE67: =$W$72*AE61+$W$73 -> 0.61 | ... AU67: =$W$72*AU61+$W$73 -> 0.53 | AV67: =AK9 -> 0.525 | AW67: =$AV$72*AW61+$AV$73 -> 0.51875 | AX67: =$AV$72*AX61+$AV$73 -> 0.5125 | AY67: =$AV$72*AY61+$AV$73 -> 0.50625 | AZ67: =$AV$72*AZ61+$AV$73 -> 0.5 | BA67: =$AV$72*BA61+$AV$73 -> 0.49375 | BB67: =$AV$72*BB61+$AV$73 -> 0.4875 | BC67: =$AV$72*BC61+$AV$73 -> 0.48125 | BD67: =$AV$72*BD61+$AV$73 -> 0.475 | ... BO67: =$AV$72*BO61+$AV$73 -> 0.40625 | BP67: =BE9 -> 0.4
D68: % Alcantarillado | H68: 0.411 | I68: 0.479 | J68: 0.498 | K68: 0.498 | L68: 0.559 | M68: 0.62 | N68: 0.633 | O68: 0.738 | P68: 0.665 | Q68: 0.701 | R68: 0.738 | S68: 0.742 | T68: 0.753 | U68: 0.744 | V68: =$S$75*V61+$S$76 -> 0.537 | W68: =L10 -> 0.33 | X68: =$W$75*X61+$W$76 -> 0.3338 | Y68: =$W$75*Y61+$W$76 -> 0.3376 | Z68: =$W$75*Z61+$W$76 -> 0.3414 | AA68: =$W$75*AA61+$W$76 -> 0.3452 | AB68: =$W$75*AB61+$W$76 -> 0.349 | AC68: =$W$75*AC61+$W$76 -> 0.3528 | AD68: =$W$75*AD61+$W$76 -> 0.3566 | AE68: =$W$75*AE61+$W$76 -> 0.3604 | ... AU68: =$W$75*AU61+$W$76 -> 0.4212 | AV68: =AK10 -> 0.425 | AW68: =$AV$75*AW61+$AV$76 -> 0.42625 | AX68: =$AV$75*AX61+$AV$76 -> 0.4275 | AY68: =$AV$75*AY61+$AV$76 -> 0.42875 | AZ68: =$AV$75*AZ61+$AV$76 -> 0.43 | BA68: =$AV$75*BA61+$AV$76 -> 0.43125 | BB68: =$AV$75*BB61+$AV$76 -> 0.4325 | BC68: =$AV$75*BC61+$AV$76 -> 0.43375 | BD68: =$AV$75*BD61+$AV$76 -> 0.435 | ... BO68: =$AV$75*BO61+$AV$76 -> 0.44875 | BP68: =BE10 -> 0.45
D69: % Tanques sépticos/ tratamiento descentralizado | H69: 0 | I69: 0 | J69: 0 | K69: 0 | L69: 0 | M69: 0 | N69: 0 | O69: 0 | P69: 0 | Q69: 0 | R69: 0 | S69: 0 | T69: 0 | U69: 0 | V69: =$S$78*V61+$S$79 -> 0.01 | W69: =L11 -> 0.02 | X69: =$W$78*X61+$W$79 -> 0.0212 | Y69: =$W$78*Y61+$W$79 -> 0.0224 | Z69: =$W$78*Z61+$W$79 -> 0.0236 | AA69: =$W$78*AA61+$W$79 -> 0.0248 | AB69: =$W$78*AB61+$W$79 -> 0.026 | AC69: =$W$78*AC61+$W$79 -> 0.0272 | AD69: =$W$78*AD61+$W$79 -> 0.0284 | AE69: =$W$78*AE61+$W$79 -> 0.0296 | ... AU69: =$W$78*AU61+$W$79 -> 0.0488 | AV69: =AK11 -> 0.05 | AW69: =$AV$78*AW61+$AV$79 -> 0.055 | AX69: =$AV$78*AX61+$AV$79 -> 0.06 | AY69: =$AV$78*AY61+$AV$79 -> 0.065 | AZ69: =$AV$78*AZ61+$AV$79 -> 0.07 | BA69: =$AV$78*BA61+$AV$79 -> 0.075 | BB69: =$AV$78*BB61+$AV$79 -> 0.08 | BC69: =$AV$78*BC61+$AV$79 -> 0.085 | BD69: =$AV$78*BD61+$AV$79 -> 0.09 | ... BO69: =$AV$78*BO61+$AV$79 -> 0.145 | BP69: =BE11 -> 0.15
D70: % Total | S70: =SUM(S67:S69) -> 1 | T70: =SUM(T67:T69) -> 1 | U70: =SUM(U67:U69) -> 1 | V70: =SUM(V67:V69) -> 1 | W70: =SUM(W67:W69) -> 1 | X70: =SUM(X67:X69) -> 1 | Y70: =SUM(Y67:Y69) -> 1 | Z70: =SUM(Z67:Z69) -> 1 | ... BP70: =SUM(BP67:BP69) -> 1
R72: m1 | S72: =(W67-U67)/(W61-U61) -> 0.197 | V72: m1 | W72: =(AV67-W67)/(AV61-W61) -> -0.005 | AU72: m1 | AV72: =(BP67-AV67)/(BP61-AV61) -> -0.00625
R73: b1 | S73: =U67-S72*U61 -> -398.275 | V73: b1 | W73: =W67-W72*W61 -> 10.775 | AU73: b1 | AV73: =AV67-AV72*AV61 -> 13.3375
R75: m2 | S75: =(W68-U68)/(W61-U61) -> -0.207 | V75: m2 | W75: =(AV68-W68)/(AV61-W61) -> 0.0038 | AU75: m2 | AV75: =(BP68-AV68)/(BP61-AV61) -> 0.00125
R76: b2 | S76: =U68-S75*U61 -> 419.505 | V76: b2 | W76: =W68-W75*W61 -> -7.365 | AU76: b2 | AV76: =AV68-AV75*AV61 -> -2.1375
R78: m3 | S78: =(W69-U69)/(W61-U61) -> 0.01 | V78: m3 | W78: =(AV69-W69)/(AV61-W61) -> 0.0012 | AU78: m3 | AV78: =(BP69-AV69)/(BP61-AV61) -> 0.005
R79: b3 | S79: =U69-S78*U61 -> -20.23 | V79: b3 | W79: =W69-W78*W61 -> -2.41 | AU79: b3 | AV79: =AV69-AV78*AV61 -> -10.2
H82: 2021 | I82: 2022 | J82: 2023 | K82: 2024 | L82: 2025 | M82: 2026 | N82: 2027 | O82: 2028 | P82: 2029 | Q82: 2030 | R82: 2031 | S82: 2032 | T82: 2033 | U82: 2034 | V82: 2035 | W82: 2036 | X82: 2037 | Y82: 2038 | Z82: 2039 | AA82: 2040 | AB82: 2041 | AC82: 2042 | AD82: 2043 | AE82: 2044 | AF82: 2045 | AG82: 2046 | AH82: 2047 | AI82: 2048 | AJ82: 2049 | AK82: 2050 | AL82: 2051 | AM82: 2052 | AN82: 2053 | AO82: 2054 | AP82: 2055 | AQ82: 2056 | AR82: 2057 | AS82: 2058 | AT82: 2059 | AU82: 2060 | AV82: 2061 | AW82: 2062 | AX82: 2063 | AY82: 2064 | AZ82: 2065 | BA82: 2066 | BB82: 2067 | BC82: 2068 | BD82: 2069 | BE82: 2070
D84: Distribución de las aguas residuales que van al alcantarillado
D85: % Con tratamiento | H85: =H15 -> 0.25 | I85: =H85 -> 0.25 | J85: =I85 -> 0.25 | K85: =$H$89*K82+$H$90 -> 0.25 | L85: =L15 -> 0.25 | M85: =$L$89*M82+$L$90 -> 0.25 | N85: =$L$89*N82+$L$90 -> 0.25 | O85: =$L$89*O82+$L$90 -> 0.25 | P85: =$L$89*P82+$L$90 -> 0.25 | Q85: =$L$89*Q82+$L$90 -> 0.25 | R85: =$L$89*R82+$L$90 -> 0.25 | S85: =$L$89*S82+$L$90 -> 0.25 | T85: =$L$89*T82+$L$90 -> 0.25 | ... AJ85: =$L$89*AJ82+$L$90 -> 0.25 | AK85: =AK15 -> 0.25 | AL85: =$AK$89*AL82+$AK$90 -> 0.25 | AM85: =$AK$89*AM82+$AK$90 -> 0.25 | AN85: =$AK$89*AN82+$AK$90 -> 0.25 | AO85: =$AK$89*AO82+$AK$90 -> 0.25 | AP85: =$AK$89*AP82+$AK$90 -> 0.25 | AQ85: =$AK$89*AQ82+$AK$90 -> 0.25 | AR85: =$AK$89*AR82+$AK$90 -> 0.25 | AS85: =$AK$89*AS82+$AK$90 -> 0.25 | ... BD85: =$AK$89*BD82+$AK$90 -> 0.25 | BE85: =BE15 -> 0.25
